{
  "$meta": {
    "sourceFeed": "C:\\Users\\milan\\Desktop\\Git-Projects\\hradiska-strapi\\scripts\\blog-migrate\\data\\arkona-post.json",
    "sourceLabel": "Arkona (D)",
    "postId": "tag:blogger.com,1999:blog-6818054921907446479.post-5938688369749508593",
    "bloggerPostUrl": "http://www.hradiska.sk/2011/03/arkona-retra-ine-pohanske-svatyne.html",
    "repliesLink": "http://www.hradiska.sk/feeds/5938688369749508593/comments/default",
    "extractedAt": "2026-07-04T19:35:47.565Z",
    "coverImageNeedsReview": true,
    "commentCount": 13,
    "comments": [
      {
        "id": "tag:blogger.com,1999:blog-6818054921907446479.post-8438559022052110442",
        "bloggerPostId": "8438559022052110442",
        "author": "Anonymous",
        "authorProfile": null,
        "published": "2019-05-08T11:16:02.851+02:00",
        "updated": "2019-05-08T11:16:02.851+02:00",
        "content": "Arkona je slovanske Varkona (Vrakuna) podla Blazeny Ovsenej. Viac na https://sclabonia.sk/2018/08/cast-2-nemecko-arkona-ukranenland/",
        "inReplyToArticle": "http://www.hradiska.sk/2011/03/arkona-retra-ine-pohanske-svatyne.html",
        "replyToBloggerId": null,
        "replyToFeedHref": null
      },
      {
        "id": "tag:blogger.com,1999:blog-6818054921907446479.post-4342133823003199424",
        "bloggerPostId": "4342133823003199424",
        "author": "Anonymous",
        "authorProfile": null,
        "published": "2018-12-15T18:04:29.894+01:00",
        "updated": "2018-12-15T18:04:29.894+01:00",
        "content": "Treba si uvedomiť že naši predkovia stavali svoje svätyne na magických miestach napríklad západ a východ slnka na okraj útesu je určite jedným takýmto miesto :-) ",
        "inReplyToArticle": "http://www.hradiska.sk/2011/03/arkona-retra-ine-pohanske-svatyne.html",
        "replyToBloggerId": "234374604158309350",
        "replyToFeedHref": "http://www.blogger.com/feeds/6818054921907446479/5938688369749508593/comments/default/234374604158309350"
      },
      {
        "id": "tag:blogger.com,1999:blog-6818054921907446479.post-7587216381487398550",
        "bloggerPostId": "7587216381487398550",
        "author": "Anonymous",
        "authorProfile": "https://www.blogger.com/profile/15327308468165573868",
        "published": "2017-10-06T17:22:15.269+02:00",
        "updated": "2017-10-06T17:22:15.269+02:00",
        "content": "velmi dobry postreh. samozrejme, nepostavili :)",
        "inReplyToArticle": "http://www.hradiska.sk/2011/03/arkona-retra-ine-pohanske-svatyne.html",
        "replyToBloggerId": "234374604158309350",
        "replyToFeedHref": "http://www.blogger.com/feeds/6818054921907446479/5938688369749508593/comments/default/234374604158309350"
      },
      {
        "id": "tag:blogger.com,1999:blog-6818054921907446479.post-234374604158309350",
        "bloggerPostId": "234374604158309350",
        "author": "Anonymous",
        "authorProfile": null,
        "published": "2017-05-29T10:44:32.877+02:00",
        "updated": "2017-05-29T10:44:32.877+02:00",
        "content": "Podľa knihy Thomas William Shore, Origin of the Anglosaxon race, sa na Rujane nikdy nenašli žiadne stopy Teutónskeho kultu a Arkona bola hlavným centrom kultu pohanských Slovanov, Wenedov, kde prinášali dary a obetiny z celej Európy. <br />Ja sa len pytam, či by vtedajší ľudia postavili svoje hlavné centrum kultu na okraji svojho teritória.",
        "inReplyToArticle": "http://www.hradiska.sk/2011/03/arkona-retra-ine-pohanske-svatyne.html",
        "replyToBloggerId": null,
        "replyToFeedHref": null
      },
      {
        "id": "tag:blogger.com,1999:blog-6818054921907446479.post-1407501584962302051",
        "bloggerPostId": "1407501584962302051",
        "author": "Anonymous",
        "authorProfile": null,
        "published": "2016-07-30T08:25:29.530+02:00",
        "updated": "2016-07-30T08:25:29.530+02:00",
        "content": "Moj pocit Arkun -najstrasi kon na ktorom jazdil Svantovit,  praslovania prisli zo severu sibir, najstarsia rasa v Eu,delila sa na kmene co na vsetky svetove strany, mate byt na co hrdy Slovieni :)",
        "inReplyToArticle": "http://www.hradiska.sk/2011/03/arkona-retra-ine-pohanske-svatyne.html",
        "replyToBloggerId": null,
        "replyToFeedHref": null
      },
      {
        "id": "tag:blogger.com,1999:blog-6818054921907446479.post-8506373653681460139",
        "bloggerPostId": "8506373653681460139",
        "author": "Anonymous",
        "authorProfile": null,
        "published": "2014-04-11T00:20:21.014+02:00",
        "updated": "2014-04-11T00:20:21.014+02:00",
        "content": "Pro Roda:<br />Já jsem se zase dočetla, že nejstarší zápis je Arkun a jde nejspíš o jotaci, takže Jarkun, myslím, že od červené barvy střechy chrámu.<br />https://docviewer.yandex.com/?url=ya-disk-public%3A%2F%2F2yS586fmGCVDySKTdryFG%2BeiCz4laurKfUQ1xFm4v%2FQ%3D&amp;name=Shubert_Rujana.pdf&amp;c=5347183aafa1",
        "inReplyToArticle": "http://www.hradiska.sk/2011/03/arkona-retra-ine-pohanske-svatyne.html",
        "replyToBloggerId": null,
        "replyToFeedHref": null
      },
      {
        "id": "tag:blogger.com,1999:blog-6818054921907446479.post-2783835819409545853",
        "bloggerPostId": "2783835819409545853",
        "author": "rod",
        "authorProfile": "http://vsieti.sk",
        "published": "2012-10-24T23:32:57.883+02:00",
        "updated": "2012-10-24T23:32:57.883+02:00",
        "content": "pre memosk29<br /><br />&quot;Podivne je aj meno arkona, az privelmi to znie rimsky a vobec nie slovansky.&quot;<br /><br />Lebo to nie je slovanske meno, je to zapadnarsky prepis mena &quot;Jarkowa&quot;. <br />(aspon tak som sa docital :)) ",
        "inReplyToArticle": "http://www.hradiska.sk/2011/03/arkona-retra-ine-pohanske-svatyne.html",
        "replyToBloggerId": null,
        "replyToFeedHref": null
      },
      {
        "id": "tag:blogger.com,1999:blog-6818054921907446479.post-1220151559719459387",
        "bloggerPostId": "1220151559719459387",
        "author": "Orgon",
        "authorProfile": "https://www.blogger.com/profile/01396912608531297025",
        "published": "2012-09-05T09:13:46.477+02:00",
        "updated": "2012-09-05T09:13:46.477+02:00",
        "content": "možno tu:  http://www.kap-arkona.de/wohnungen/ferienwohnungen.htm ",
        "inReplyToArticle": "http://www.hradiska.sk/2011/03/arkona-retra-ine-pohanske-svatyne.html",
        "replyToBloggerId": null,
        "replyToFeedHref": null
      },
      {
        "id": "tag:blogger.com,1999:blog-6818054921907446479.post-8496028701235898903",
        "bloggerPostId": "8496028701235898903",
        "author": "Anonymous",
        "authorProfile": null,
        "published": "2012-09-05T00:54:05.176+02:00",
        "updated": "2012-09-05T00:54:05.176+02:00",
        "content": "hmm chystam sa tam o tyzden.. porad ubytko)))<br />",
        "inReplyToArticle": "http://www.hradiska.sk/2011/03/arkona-retra-ine-pohanske-svatyne.html",
        "replyToBloggerId": null,
        "replyToFeedHref": null
      },
      {
        "id": "tag:blogger.com,1999:blog-6818054921907446479.post-2696125743048661378",
        "bloggerPostId": "2696125743048661378",
        "author": "Anonymous",
        "authorProfile": null,
        "published": "2012-09-04T00:03:07.391+02:00",
        "updated": "2012-09-04T00:03:07.391+02:00",
        "content": "Bol som na Arkone skoro mesiac.Stoji to za to:) Videl som zapadat a vychadzat slnko nad morom,hodovali sme na Svantovitovu slavu,sedeli na skale na konci sveta.Dufam,ze sa tam este niekedy vratim.",
        "inReplyToArticle": "http://www.hradiska.sk/2011/03/arkona-retra-ine-pohanske-svatyne.html",
        "replyToBloggerId": null,
        "replyToFeedHref": null
      },
      {
        "id": "tag:blogger.com,1999:blog-6818054921907446479.post-6196956548893688306",
        "bloggerPostId": "6196956548893688306",
        "author": "pecimm",
        "authorProfile": "https://www.blogger.com/profile/17390389262678266511",
        "published": "2012-04-10T11:30:29.542+02:00",
        "updated": "2012-04-10T11:30:29.542+02:00",
        "content": "moj sen ist sa pozriet na Arkonu a Gross Raden..mozno sa mi raz podari :D",
        "inReplyToArticle": "http://www.hradiska.sk/2011/03/arkona-retra-ine-pohanske-svatyne.html",
        "replyToBloggerId": null,
        "replyToFeedHref": null
      },
      {
        "id": "tag:blogger.com,1999:blog-6818054921907446479.post-8041744075099578997",
        "bloggerPostId": "8041744075099578997",
        "author": "memosk",
        "authorProfile": "http://nikde.com",
        "published": "2012-03-29T14:37:24.262+02:00",
        "updated": "2012-03-29T14:37:24.262+02:00",
        "content": "Podivne je aj meno arkona, az privelmi to znie rimsky a vobec nie slovansky.<br /><br />Neviem si pomoct ale priklanam sa stale viac k teorii ze slovania a germani utiekli z Talianskeho poloostrova po expanzii rimanov niekedy v dobe legiend. A az nasledne osidlili daleke rusko",
        "inReplyToArticle": "http://www.hradiska.sk/2011/03/arkona-retra-ine-pohanske-svatyne.html",
        "replyToBloggerId": null,
        "replyToFeedHref": null
      },
      {
        "id": "tag:blogger.com,1999:blog-6818054921907446479.post-6176516313677135436",
        "bloggerPostId": "6176516313677135436",
        "author": "Anonymous",
        "authorProfile": null,
        "published": "2012-03-29T14:31:01.110+02:00",
        "updated": "2012-03-29T14:31:01.110+02:00",
        "content": "Je zaujimave ze s trochou fantazie pripominaju tie oblozene dosky okolo svatine grecke stlpy aj s hlavicami  a podivne zakoncenia striech mozu byt zarodkom portalov ..",
        "inReplyToArticle": "http://www.hradiska.sk/2011/03/arkona-retra-ine-pohanske-svatyne.html",
        "replyToBloggerId": null,
        "replyToFeedHref": null
      }
    ],
    "checks": {
      "nativeHeadings": [],
      "nativeHeadingCount": 0,
      "mapIframeCount": 1,
      "mapIframeSrcs": [
        "http://maps.google.com/?ie=UTF8&t=h&vpsrc=0&ll=54.679488,13.434391&spn=0.034736,0.072956&z=13&output=embed"
      ],
      "nonMapIframeCount": 1,
      "nonMapIframeSrcs": [
        "http://player.vimeo.com/video/35500856"
      ],
      "italicCaptionCount": 0,
      "totalImages": 26,
      "captionedImages": 18,
      "separatorImages": 8
    },
    "sanityFlags": [
      "hasNonMapIframes"
    ]
  },
  "blogPost": {
    "title": "Arkona, Retra a iné pohanské svätyne západných Slovanov",
    "slug": "arkona-retra-a-ine-pohanske-svatyne-zapadnych-slovanov",
    "excerpt": "Nad skalami Arkony týči sa orlie hniezdo Kde údery vĺn bijú o východné veže Statočný orol sedí na skalnom tróne- Ochranca slovanských krajov, slobodný syn nebies Ó slovanský orol, chráň národy Slovanov Ochraňuj slovanské zvyky a reč Ochraňuj nás a…",
    "authorName": "Orgon",
    "publishedAt": "2011-03-27T22:18:00.002+02:00",
    "originalPublishedDate": "2011-03-27T22:18:00.002+02:00",
    "updatedAt": "2020-04-15T09:48:50.224+02:00",
    "readingTime": 11,
    "featured": false,
    "coverImage": {
      "sourceUrl": "https://blogger.googleusercontent.com/img/b/R29vZ2xl/AVvXsEj1nQOu7J2DM5_d4KFJ75V-LQRAFlUh6h2KWinsaPofO993oj8t74HP4Olv1fAHDJ_w2pcjL3WVF3ObMREy9GfLFmQArRQhgWADbmQajoW18q75RmNPtQr8NImTtluJcSLYlWjCokANrc0/s0/retra.jpeg",
      "fallbackUrl": "https://blogger.googleusercontent.com/img/b/R29vZ2xl/AVvXsEj1nQOu7J2DM5_d4KFJ75V-LQRAFlUh6h2KWinsaPofO993oj8t74HP4Olv1fAHDJ_w2pcjL3WVF3ObMREy9GfLFmQArRQhgWADbmQajoW18q75RmNPtQr8NImTtluJcSLYlWjCokANrc0/s1600/retra.jpeg",
      "filename": "retra.jpeg",
      "blogger": {
        "anchorHref": "https://blogger.googleusercontent.com/img/b/R29vZ2xl/AVvXsEj1nQOu7J2DM5_d4KFJ75V-LQRAFlUh6h2KWinsaPofO993oj8t74HP4Olv1fAHDJ_w2pcjL3WVF3ObMREy9GfLFmQArRQhgWADbmQajoW18q75RmNPtQr8NImTtluJcSLYlWjCokANrc0/s1600/retra.jpeg",
        "displayedWidth": 320,
        "displayedHeight": 311,
        "originalWidth": null,
        "originalHeight": null
      }
    },
    "gallery": [
      {
        "sourceUrl": "https://blogger.googleusercontent.com/img/b/R29vZ2xl/AVvXsEj1nQOu7J2DM5_d4KFJ75V-LQRAFlUh6h2KWinsaPofO993oj8t74HP4Olv1fAHDJ_w2pcjL3WVF3ObMREy9GfLFmQArRQhgWADbmQajoW18q75RmNPtQr8NImTtluJcSLYlWjCokANrc0/s0/retra.jpeg",
        "fallbackUrl": "https://blogger.googleusercontent.com/img/b/R29vZ2xl/AVvXsEj1nQOu7J2DM5_d4KFJ75V-LQRAFlUh6h2KWinsaPofO993oj8t74HP4Olv1fAHDJ_w2pcjL3WVF3ObMREy9GfLFmQArRQhgWADbmQajoW18q75RmNPtQr8NImTtluJcSLYlWjCokANrc0/s1600/retra.jpeg",
        "filename": "retra.jpeg",
        "blogger": {
          "anchorHref": "https://blogger.googleusercontent.com/img/b/R29vZ2xl/AVvXsEj1nQOu7J2DM5_d4KFJ75V-LQRAFlUh6h2KWinsaPofO993oj8t74HP4Olv1fAHDJ_w2pcjL3WVF3ObMREy9GfLFmQArRQhgWADbmQajoW18q75RmNPtQr8NImTtluJcSLYlWjCokANrc0/s1600/retra.jpeg",
          "displayedWidth": 320,
          "displayedHeight": 311,
          "originalWidth": null,
          "originalHeight": null
        },
        "caption": "Mnohí sa domnievajú, že Retrou bol ostrov Fischerinsel na jazere Tollensesee"
      },
      {
        "sourceUrl": "https://blogger.googleusercontent.com/img/b/R29vZ2xl/AVvXsEgsTF8aAo_SVexcRGxl4FttZzCzs0kplhgqrmiv_9TK72vi5fZoDeqfPlzWMxB8NSmQK-QYbJJTAnBQGhyphenhyphenTPaMTIBeTWGhF6N8nTRmj2hqjk7FiKyol1svutmG_CjNOqARZr3zkOd4F004/s0/fischerinsel++modla.jpeg",
        "fallbackUrl": "https://blogger.googleusercontent.com/img/b/R29vZ2xl/AVvXsEgsTF8aAo_SVexcRGxl4FttZzCzs0kplhgqrmiv_9TK72vi5fZoDeqfPlzWMxB8NSmQK-QYbJJTAnBQGhyphenhyphenTPaMTIBeTWGhF6N8nTRmj2hqjk7FiKyol1svutmG_CjNOqARZr3zkOd4F004/s1600/fischerinsel++modla.jpeg",
        "filename": "fischerinsel++modla.jpeg",
        "blogger": {
          "anchorHref": "https://blogger.googleusercontent.com/img/b/R29vZ2xl/AVvXsEgsTF8aAo_SVexcRGxl4FttZzCzs0kplhgqrmiv_9TK72vi5fZoDeqfPlzWMxB8NSmQK-QYbJJTAnBQGhyphenhyphenTPaMTIBeTWGhF6N8nTRmj2hqjk7FiKyol1svutmG_CjNOqARZr3zkOd4F004/s1600/fischerinsel++modla.jpeg",
          "displayedWidth": 97,
          "displayedHeight": 320,
          "originalWidth": null,
          "originalHeight": null
        },
        "caption": "Známa modla z Fischerinsel"
      },
      {
        "sourceUrl": "https://blogger.googleusercontent.com/img/b/R29vZ2xl/AVvXsEhzqccGKlAY6zzCPPVV5AnuBVavR6Vt7_jjsxsmcddNnVtB_EitrtZAyl3BwLz9IMb-YA8EehFhqAa0tZwGx6x9UHweRyO1dxHrJszLsQ4bM5aLdIumnekH6aQPFwldnQvm_tSp-KdsUXQ/s0/vnutro+svatyne.jpg",
        "fallbackUrl": "https://blogger.googleusercontent.com/img/b/R29vZ2xl/AVvXsEhzqccGKlAY6zzCPPVV5AnuBVavR6Vt7_jjsxsmcddNnVtB_EitrtZAyl3BwLz9IMb-YA8EehFhqAa0tZwGx6x9UHweRyO1dxHrJszLsQ4bM5aLdIumnekH6aQPFwldnQvm_tSp-KdsUXQ/s1600/vnutro+svatyne.jpg",
        "filename": "vnutro+svatyne.jpg",
        "blogger": {
          "anchorHref": "https://blogger.googleusercontent.com/img/b/R29vZ2xl/AVvXsEhzqccGKlAY6zzCPPVV5AnuBVavR6Vt7_jjsxsmcddNnVtB_EitrtZAyl3BwLz9IMb-YA8EehFhqAa0tZwGx6x9UHweRyO1dxHrJszLsQ4bM5aLdIumnekH6aQPFwldnQvm_tSp-KdsUXQ/s1600/vnutro+svatyne.jpg",
          "displayedWidth": null,
          "displayedHeight": null,
          "originalWidth": null,
          "originalHeight": null
        },
        "caption": null
      },
      {
        "sourceUrl": "https://blogger.googleusercontent.com/img/b/R29vZ2xl/AVvXsEgYOH3Tv2Dll3LFlezKTHnKpLfNSXT2VUmu_rnu-tlwrzeZTRmZckTTFDmE7Mn_g8IZR7ZDdf7XsReZ1x71X6JekBXvR044F5aW65MPHI1iBo8ApY9ekKm6YMJq7zhp7xgxIvI8ubvUwqo/s0/800px-Burgwall_Arkona.jpg",
        "fallbackUrl": "https://blogger.googleusercontent.com/img/b/R29vZ2xl/AVvXsEgYOH3Tv2Dll3LFlezKTHnKpLfNSXT2VUmu_rnu-tlwrzeZTRmZckTTFDmE7Mn_g8IZR7ZDdf7XsReZ1x71X6JekBXvR044F5aW65MPHI1iBo8ApY9ekKm6YMJq7zhp7xgxIvI8ubvUwqo/s1600/800px-Burgwall_Arkona.jpg",
        "filename": "800px-Burgwall_Arkona.jpg",
        "blogger": {
          "anchorHref": "https://blogger.googleusercontent.com/img/b/R29vZ2xl/AVvXsEgYOH3Tv2Dll3LFlezKTHnKpLfNSXT2VUmu_rnu-tlwrzeZTRmZckTTFDmE7Mn_g8IZR7ZDdf7XsReZ1x71X6JekBXvR044F5aW65MPHI1iBo8ApY9ekKm6YMJq7zhp7xgxIvI8ubvUwqo/s1600/800px-Burgwall_Arkona.jpg",
          "displayedWidth": 320,
          "displayedHeight": 240,
          "originalWidth": null,
          "originalHeight": null
        },
        "caption": "Pohľad na časť hradiska Arkona. Ako je vidieť, väčšia časť sa zrútila spolu s útesom do mora"
      },
      {
        "sourceUrl": "https://blogger.googleusercontent.com/img/b/R29vZ2xl/AVvXsEhpnM__2JkE4bq7uf_g5njcMRM7fatCMAlc6u1pQeBTrMxqyjuzv1rL-Ri3KQ6P8TEJleZ8vkK4qTH6-skGiv-Cz0rruvru68BI81ucMoVefzetj6Vi2HioPuK1HulXPsHhVeTdN1-_grs/s0/Retra+2.jpeg",
        "fallbackUrl": "https://blogger.googleusercontent.com/img/b/R29vZ2xl/AVvXsEhpnM__2JkE4bq7uf_g5njcMRM7fatCMAlc6u1pQeBTrMxqyjuzv1rL-Ri3KQ6P8TEJleZ8vkK4qTH6-skGiv-Cz0rruvru68BI81ucMoVefzetj6Vi2HioPuK1HulXPsHhVeTdN1-_grs/s1600/Retra+2.jpeg",
        "filename": "Retra+2.jpeg",
        "blogger": {
          "anchorHref": "https://blogger.googleusercontent.com/img/b/R29vZ2xl/AVvXsEhpnM__2JkE4bq7uf_g5njcMRM7fatCMAlc6u1pQeBTrMxqyjuzv1rL-Ri3KQ6P8TEJleZ8vkK4qTH6-skGiv-Cz0rruvru68BI81ucMoVefzetj6Vi2HioPuK1HulXPsHhVeTdN1-_grs/s1600/Retra+2.jpeg",
          "displayedWidth": 320,
          "displayedHeight": 178,
          "originalWidth": null,
          "originalHeight": null
        },
        "caption": null
      },
      {
        "sourceUrl": "https://blogger.googleusercontent.com/img/b/R29vZ2xl/AVvXsEipsA2INRRc16jktz1a5DuUs2jK7JhwAE_oVuDypDoTHmMfKobdv2zcda3TaBagVzX77aj4FqX1yP4Es6ZbX4aDi_5KsVPFGDIYfqCoZCSxn7HduwiwWTUmJNXh9pkDW2dTmdYLLXxkptY/s0/arkona2.jpg",
        "fallbackUrl": "https://blogger.googleusercontent.com/img/b/R29vZ2xl/AVvXsEipsA2INRRc16jktz1a5DuUs2jK7JhwAE_oVuDypDoTHmMfKobdv2zcda3TaBagVzX77aj4FqX1yP4Es6ZbX4aDi_5KsVPFGDIYfqCoZCSxn7HduwiwWTUmJNXh9pkDW2dTmdYLLXxkptY/s1600/arkona2.jpg",
        "filename": "arkona2.jpg",
        "blogger": {
          "anchorHref": "https://blogger.googleusercontent.com/img/b/R29vZ2xl/AVvXsEipsA2INRRc16jktz1a5DuUs2jK7JhwAE_oVuDypDoTHmMfKobdv2zcda3TaBagVzX77aj4FqX1yP4Es6ZbX4aDi_5KsVPFGDIYfqCoZCSxn7HduwiwWTUmJNXh9pkDW2dTmdYLLXxkptY/s1600/arkona2.jpg",
          "displayedWidth": 320,
          "displayedHeight": 240,
          "originalWidth": null,
          "originalHeight": null
        },
        "caption": "Mys Arkona dnes"
      },
      {
        "sourceUrl": "https://blogger.googleusercontent.com/img/b/R29vZ2xl/AVvXsEjG7-tRabMtFLK0pvN5k5O_JOgkpzQozUhCPjXQ7lW1bFkF6H9-V0Dq2tF6E6wHRBc-ZVdRGfYit3EzgGHQxjz-r7o4qoIt_SbZ5PNHaFP4D3YvGuXEQ2fD7BRlI6XL4glH09bgLXL77YA/s0/450px-Svantevit-Statue.jpg",
        "fallbackUrl": "https://blogger.googleusercontent.com/img/b/R29vZ2xl/AVvXsEjG7-tRabMtFLK0pvN5k5O_JOgkpzQozUhCPjXQ7lW1bFkF6H9-V0Dq2tF6E6wHRBc-ZVdRGfYit3EzgGHQxjz-r7o4qoIt_SbZ5PNHaFP4D3YvGuXEQ2fD7BRlI6XL4glH09bgLXL77YA/s1600/450px-Svantevit-Statue.jpg",
        "filename": "450px-Svantevit-Statue.jpg",
        "blogger": {
          "anchorHref": "https://blogger.googleusercontent.com/img/b/R29vZ2xl/AVvXsEjG7-tRabMtFLK0pvN5k5O_JOgkpzQozUhCPjXQ7lW1bFkF6H9-V0Dq2tF6E6wHRBc-ZVdRGfYit3EzgGHQxjz-r7o4qoIt_SbZ5PNHaFP4D3YvGuXEQ2fD7BRlI6XL4glH09bgLXL77YA/s1600/450px-Svantevit-Statue.jpg",
          "displayedWidth": 240,
          "displayedHeight": 320,
          "originalWidth": null,
          "originalHeight": null
        },
        "caption": "Socha Svantovíta dnes"
      },
      {
        "sourceUrl": "https://blogger.googleusercontent.com/img/b/R29vZ2xl/AVvXsEg0bRGT0lY7MtIQenbXdx56YFqivx4Eyz1H4zccBTtG8ua8gAxfh9WKkSt5HzayvXCAoXunpsKV3lp7yfgFtCcLy88SZrCBDPY8RPMN-xcSdA9oSdMTdQBBqCHY2AfQrddsQBvjEIFW88k/s0/zvrhnutie+Svantovi%CC%81ta.JPG",
        "fallbackUrl": "https://blogger.googleusercontent.com/img/b/R29vZ2xl/AVvXsEg0bRGT0lY7MtIQenbXdx56YFqivx4Eyz1H4zccBTtG8ua8gAxfh9WKkSt5HzayvXCAoXunpsKV3lp7yfgFtCcLy88SZrCBDPY8RPMN-xcSdA9oSdMTdQBBqCHY2AfQrddsQBvjEIFW88k/s1600/zvrhnutie+Svantovi%CC%81ta.JPG",
        "filename": "zvrhnutie+Svantovíta.JPG",
        "blogger": {
          "anchorHref": "https://blogger.googleusercontent.com/img/b/R29vZ2xl/AVvXsEg0bRGT0lY7MtIQenbXdx56YFqivx4Eyz1H4zccBTtG8ua8gAxfh9WKkSt5HzayvXCAoXunpsKV3lp7yfgFtCcLy88SZrCBDPY8RPMN-xcSdA9oSdMTdQBBqCHY2AfQrddsQBvjEIFW88k/s1600/zvrhnutie+Svantovi%CC%81ta.JPG",
          "displayedWidth": 320,
          "displayedHeight": 188,
          "originalWidth": null,
          "originalHeight": null
        },
        "caption": "Zničenie Arkony"
      },
      {
        "sourceUrl": "https://blogger.googleusercontent.com/img/b/R29vZ2xl/AVvXsEidV23yPFFuRCXZLXQLUNHTRFJRhLao-3vT2ndYLbB21BdGOoAlkQq3UGYZjmDz6O2uZ26C2MkeF7wo_qA2zFQBIMwPQMliUpD9-jzbvOBtxOral__V_X_BoCbe3_WvkV8YH1trHqd89To/s0/arkona+temnozor.jpg",
        "fallbackUrl": "https://blogger.googleusercontent.com/img/b/R29vZ2xl/AVvXsEidV23yPFFuRCXZLXQLUNHTRFJRhLao-3vT2ndYLbB21BdGOoAlkQq3UGYZjmDz6O2uZ26C2MkeF7wo_qA2zFQBIMwPQMliUpD9-jzbvOBtxOral__V_X_BoCbe3_WvkV8YH1trHqd89To/s1600/arkona+temnozor.jpg",
        "filename": "arkona+temnozor.jpg",
        "blogger": {
          "anchorHref": "https://blogger.googleusercontent.com/img/b/R29vZ2xl/AVvXsEidV23yPFFuRCXZLXQLUNHTRFJRhLao-3vT2ndYLbB21BdGOoAlkQq3UGYZjmDz6O2uZ26C2MkeF7wo_qA2zFQBIMwPQMliUpD9-jzbvOBtxOral__V_X_BoCbe3_WvkV8YH1trHqd89To/s1600/arkona+temnozor.jpg",
          "displayedWidth": 320,
          "displayedHeight": 308,
          "originalWidth": null,
          "originalHeight": null
        },
        "caption": "Hradisko Arkona - umelecká predstava (Temnozor)"
      },
      {
        "sourceUrl": "https://blogger.googleusercontent.com/img/b/R29vZ2xl/AVvXsEg15DOKbnDTcrNzIv0jzF79KTROfh3W-QmuxDu373gSbgzlgCflQuu28_-1_Ikz9pjGm5OMSJCCn4z-R9AJpOLFPdxkm1b9cVTUjt1gNhdBVqJ1qoLymhTUKHcn5KMq_Oms4N3qa0CSrSU/s0/arkona.jpg",
        "fallbackUrl": "https://blogger.googleusercontent.com/img/b/R29vZ2xl/AVvXsEg15DOKbnDTcrNzIv0jzF79KTROfh3W-QmuxDu373gSbgzlgCflQuu28_-1_Ikz9pjGm5OMSJCCn4z-R9AJpOLFPdxkm1b9cVTUjt1gNhdBVqJ1qoLymhTUKHcn5KMq_Oms4N3qa0CSrSU/s1600/arkona.jpg",
        "filename": "arkona.jpg",
        "blogger": {
          "anchorHref": "https://blogger.googleusercontent.com/img/b/R29vZ2xl/AVvXsEg15DOKbnDTcrNzIv0jzF79KTROfh3W-QmuxDu373gSbgzlgCflQuu28_-1_Ikz9pjGm5OMSJCCn4z-R9AJpOLFPdxkm1b9cVTUjt1gNhdBVqJ1qoLymhTUKHcn5KMq_Oms4N3qa0CSrSU/s1600/arkona.jpg",
          "displayedWidth": 320,
          "displayedHeight": 205,
          "originalWidth": null,
          "originalHeight": null
        },
        "caption": "Arkona - jeden z pokusov o \"rekonštrukciu\""
      },
      {
        "sourceUrl": "https://blogger.googleusercontent.com/img/b/R29vZ2xl/AVvXsEiI8wy5CXA59x48O7xZlM2UHhAqfbcUhRV9qYT_O1YAncFZ8_1_Axch_MZZv0gCks9HKx5JLrih1c6v-EoppQfpEMkgaYu8C4Uao2wCNu4M4bVrpQhlKqEqGDKp9lryRaVqY0h7aJXujIE/s0/ark1.jpg",
        "fallbackUrl": "https://blogger.googleusercontent.com/img/b/R29vZ2xl/AVvXsEiI8wy5CXA59x48O7xZlM2UHhAqfbcUhRV9qYT_O1YAncFZ8_1_Axch_MZZv0gCks9HKx5JLrih1c6v-EoppQfpEMkgaYu8C4Uao2wCNu4M4bVrpQhlKqEqGDKp9lryRaVqY0h7aJXujIE/s1600/ark1.jpg",
        "filename": "ark1.jpg",
        "blogger": {
          "anchorHref": "https://blogger.googleusercontent.com/img/b/R29vZ2xl/AVvXsEiI8wy5CXA59x48O7xZlM2UHhAqfbcUhRV9qYT_O1YAncFZ8_1_Axch_MZZv0gCks9HKx5JLrih1c6v-EoppQfpEMkgaYu8C4Uao2wCNu4M4bVrpQhlKqEqGDKp9lryRaVqY0h7aJXujIE/s1600/ark1.jpg",
          "displayedWidth": 264,
          "displayedHeight": 320,
          "originalWidth": null,
          "originalHeight": null
        },
        "caption": "Fiktívna podoba svätyne v Arkone"
      },
      {
        "sourceUrl": "https://blogger.googleusercontent.com/img/b/R29vZ2xl/AVvXsEh29g4Bui63XwrqDg2xooM3RWSdn_RWW3_abYyamnN__KKNxE7dqSqPoeDp48m_UlZrsxB4TAPB36zqD13xBae5GUQvLye9NzbvETzboMizsxN6AVZd4AH61ynvWPnZT8g8pumrfzLAVj0/s0/arkona.jpg",
        "fallbackUrl": "https://blogger.googleusercontent.com/img/b/R29vZ2xl/AVvXsEh29g4Bui63XwrqDg2xooM3RWSdn_RWW3_abYyamnN__KKNxE7dqSqPoeDp48m_UlZrsxB4TAPB36zqD13xBae5GUQvLye9NzbvETzboMizsxN6AVZd4AH61ynvWPnZT8g8pumrfzLAVj0/s1600/arkona.jpg",
        "filename": "arkona.jpg",
        "blogger": {
          "anchorHref": "https://blogger.googleusercontent.com/img/b/R29vZ2xl/AVvXsEh29g4Bui63XwrqDg2xooM3RWSdn_RWW3_abYyamnN__KKNxE7dqSqPoeDp48m_UlZrsxB4TAPB36zqD13xBae5GUQvLye9NzbvETzboMizsxN6AVZd4AH61ynvWPnZT8g8pumrfzLAVj0/s1600/arkona.jpg",
          "displayedWidth": null,
          "displayedHeight": null,
          "originalWidth": null,
          "originalHeight": null
        },
        "caption": null
      },
      {
        "sourceUrl": "https://blogger.googleusercontent.com/img/b/R29vZ2xl/AVvXsEj947J0bEEvLpIHsCWAe9P3GVQWbkQV1J5juEf_EcC4DQF_3QrMjM16yNwH1CvGPv9VkVy_cyG_UZWaOUL9fLxj8p2x4BDemH9m_S9htUBf479mfxGahlV3XFtanp5SpXqfGHvAO3KJa5k/s0/Nepomenovany%CC%81.jpg",
        "fallbackUrl": "https://blogger.googleusercontent.com/img/b/R29vZ2xl/AVvXsEj947J0bEEvLpIHsCWAe9P3GVQWbkQV1J5juEf_EcC4DQF_3QrMjM16yNwH1CvGPv9VkVy_cyG_UZWaOUL9fLxj8p2x4BDemH9m_S9htUBf479mfxGahlV3XFtanp5SpXqfGHvAO3KJa5k/s1600/Nepomenovany%CC%81.jpg",
        "filename": "Nepomenovaný.jpg",
        "blogger": {
          "anchorHref": "https://blogger.googleusercontent.com/img/b/R29vZ2xl/AVvXsEj947J0bEEvLpIHsCWAe9P3GVQWbkQV1J5juEf_EcC4DQF_3QrMjM16yNwH1CvGPv9VkVy_cyG_UZWaOUL9fLxj8p2x4BDemH9m_S9htUBf479mfxGahlV3XFtanp5SpXqfGHvAO3KJa5k/s1600/Nepomenovany%CC%81.jpg",
          "displayedWidth": 320,
          "displayedHeight": 179,
          "originalWidth": null,
          "originalHeight": null
        },
        "caption": null
      },
      {
        "sourceUrl": "https://blogger.googleusercontent.com/img/b/R29vZ2xl/AVvXsEim4JmYT1qIIymsakpACh6K7Ob91uOWcSL7PSYjGnQWDHJsoi4wwe5ThzqK3uGKI5z_VVIa9zLNaMbBDlvnWgMR9iU4sKiWLd-tSlPa6lF-8QdbFY4zxRvdYN31D-drqYx1XtOSmEWRDgE/s0/gross_raden.jpg",
        "fallbackUrl": "https://blogger.googleusercontent.com/img/b/R29vZ2xl/AVvXsEim4JmYT1qIIymsakpACh6K7Ob91uOWcSL7PSYjGnQWDHJsoi4wwe5ThzqK3uGKI5z_VVIa9zLNaMbBDlvnWgMR9iU4sKiWLd-tSlPa6lF-8QdbFY4zxRvdYN31D-drqYx1XtOSmEWRDgE/s1600/gross_raden.jpg",
        "filename": "gross_raden.jpg",
        "blogger": {
          "anchorHref": "https://blogger.googleusercontent.com/img/b/R29vZ2xl/AVvXsEim4JmYT1qIIymsakpACh6K7Ob91uOWcSL7PSYjGnQWDHJsoi4wwe5ThzqK3uGKI5z_VVIa9zLNaMbBDlvnWgMR9iU4sKiWLd-tSlPa6lF-8QdbFY4zxRvdYN31D-drqYx1XtOSmEWRDgE/s1600/gross_raden.jpg",
          "displayedWidth": null,
          "displayedHeight": null,
          "originalWidth": null,
          "originalHeight": null
        },
        "caption": null
      },
      {
        "sourceUrl": "https://blogger.googleusercontent.com/img/b/R29vZ2xl/AVvXsEiXg2fmwIJPxPZP2YT9rGt1TfV14csdjJztc2qgmLGtddIrwFIRxEPTRseRcxFS6zDk7RSbeOlL3PlpPg0hSwj5mucGru3Sk5Mm9CVRUDthgMqIr_ggODna6lHoaTPCJPFuPGbTvsFXvA4/s0/gross-raden-tempel-2.jpg",
        "fallbackUrl": "https://blogger.googleusercontent.com/img/b/R29vZ2xl/AVvXsEiXg2fmwIJPxPZP2YT9rGt1TfV14csdjJztc2qgmLGtddIrwFIRxEPTRseRcxFS6zDk7RSbeOlL3PlpPg0hSwj5mucGru3Sk5Mm9CVRUDthgMqIr_ggODna6lHoaTPCJPFuPGbTvsFXvA4/s1600/gross-raden-tempel-2.jpg",
        "filename": "gross-raden-tempel-2.jpg",
        "blogger": {
          "anchorHref": "https://blogger.googleusercontent.com/img/b/R29vZ2xl/AVvXsEiXg2fmwIJPxPZP2YT9rGt1TfV14csdjJztc2qgmLGtddIrwFIRxEPTRseRcxFS6zDk7RSbeOlL3PlpPg0hSwj5mucGru3Sk5Mm9CVRUDthgMqIr_ggODna6lHoaTPCJPFuPGbTvsFXvA4/s1600/gross-raden-tempel-2.jpg",
          "displayedWidth": 320,
          "displayedHeight": 213,
          "originalWidth": null,
          "originalHeight": null
        },
        "caption": "Hradisko Gross Raden bolo zrekonštruované - Približná podoba pohanskej svätyne"
      },
      {
        "sourceUrl": "https://blogger.googleusercontent.com/img/b/R29vZ2xl/AVvXsEgNrNKPK2uQ8s5EBlPo2MBIetqQj0S0gCPfBjq7FQiDfAfEHpsxX32F738ULB56CunGpwDpv-zH523S2-NM6GlFjPsY6cb8U5tjOBMgwWbo-5oaghz31Gto4tD1M3CsXwIMEHQ2CP1jQhE/s0/gross-raden-tempel-3.jpg",
        "fallbackUrl": "https://blogger.googleusercontent.com/img/b/R29vZ2xl/AVvXsEgNrNKPK2uQ8s5EBlPo2MBIetqQj0S0gCPfBjq7FQiDfAfEHpsxX32F738ULB56CunGpwDpv-zH523S2-NM6GlFjPsY6cb8U5tjOBMgwWbo-5oaghz31Gto4tD1M3CsXwIMEHQ2CP1jQhE/s1600/gross-raden-tempel-3.jpg",
        "filename": "gross-raden-tempel-3.jpg",
        "blogger": {
          "anchorHref": "https://blogger.googleusercontent.com/img/b/R29vZ2xl/AVvXsEgNrNKPK2uQ8s5EBlPo2MBIetqQj0S0gCPfBjq7FQiDfAfEHpsxX32F738ULB56CunGpwDpv-zH523S2-NM6GlFjPsY6cb8U5tjOBMgwWbo-5oaghz31Gto4tD1M3CsXwIMEHQ2CP1jQhE/s1600/gross-raden-tempel-3.jpg",
          "displayedWidth": 320,
          "displayedHeight": 213,
          "originalWidth": null,
          "originalHeight": null
        },
        "caption": "Čelný pohľad na svätyňu"
      },
      {
        "sourceUrl": "https://blogger.googleusercontent.com/img/b/R29vZ2xl/AVvXsEij3hbecX3VjGm8IeZtbD4yClMgK4cYrSoqq8eZAhaMAavjAYUJ4Cqn3gM9d4HdgGbLNVn9hhUoA75XD6FoViIx0_02LVLwUyLgelVnz2RnW3zJOa59Od5k9bIs2pPGtMJ64y70Hjk_wJY/s0/kaparkona1.jpg",
        "fallbackUrl": "https://blogger.googleusercontent.com/img/b/R29vZ2xl/AVvXsEij3hbecX3VjGm8IeZtbD4yClMgK4cYrSoqq8eZAhaMAavjAYUJ4Cqn3gM9d4HdgGbLNVn9hhUoA75XD6FoViIx0_02LVLwUyLgelVnz2RnW3zJOa59Od5k9bIs2pPGtMJ64y70Hjk_wJY/s1600/kaparkona1.jpg",
        "filename": "kaparkona1.jpg",
        "blogger": {
          "anchorHref": "https://blogger.googleusercontent.com/img/b/R29vZ2xl/AVvXsEij3hbecX3VjGm8IeZtbD4yClMgK4cYrSoqq8eZAhaMAavjAYUJ4Cqn3gM9d4HdgGbLNVn9hhUoA75XD6FoViIx0_02LVLwUyLgelVnz2RnW3zJOa59Od5k9bIs2pPGtMJ64y70Hjk_wJY/s1600/kaparkona1.jpg",
          "displayedWidth": 320,
          "displayedHeight": 207,
          "originalWidth": null,
          "originalHeight": null
        },
        "caption": "1960"
      },
      {
        "sourceUrl": "https://blogger.googleusercontent.com/img/b/R29vZ2xl/AVvXsEgLwJA4CA0-yQ7EdTddfhDSPWY7U-6jVzkaUmd16TSv2dogsQqzck9CCS3YUKuJ8ZSHMP8IjNNEF8dqLPIl9AMdu0B4ospLuVSEFSn8j3Yq8PsZQLfmMhV9bXOnXTo_eD63SJaQ9BYOr5I/s0/kaparkona11.jpg",
        "fallbackUrl": "https://blogger.googleusercontent.com/img/b/R29vZ2xl/AVvXsEgLwJA4CA0-yQ7EdTddfhDSPWY7U-6jVzkaUmd16TSv2dogsQqzck9CCS3YUKuJ8ZSHMP8IjNNEF8dqLPIl9AMdu0B4ospLuVSEFSn8j3Yq8PsZQLfmMhV9bXOnXTo_eD63SJaQ9BYOr5I/s1600/kaparkona11.jpg",
        "filename": "kaparkona11.jpg",
        "blogger": {
          "anchorHref": "https://blogger.googleusercontent.com/img/b/R29vZ2xl/AVvXsEgLwJA4CA0-yQ7EdTddfhDSPWY7U-6jVzkaUmd16TSv2dogsQqzck9CCS3YUKuJ8ZSHMP8IjNNEF8dqLPIl9AMdu0B4ospLuVSEFSn8j3Yq8PsZQLfmMhV9bXOnXTo_eD63SJaQ9BYOr5I/s1600/kaparkona11.jpg",
          "displayedWidth": 320,
          "displayedHeight": 240,
          "originalWidth": null,
          "originalHeight": null
        },
        "caption": "Val z vnútornej strany"
      },
      {
        "sourceUrl": "https://blogger.googleusercontent.com/img/b/R29vZ2xl/AVvXsEjOKC9j09eOyS4qnvu-02u8cUXHc5aAdfXTtAjqGKLkSxGQce5kRL3qSMS4wlvgRFn58GbG1L0wkYfKyviRC5ytUKv1i6tiTOzkJDTbABvdDudvgWHURRZVg5TNTbNun68JiT_rBIP-iq0/s0/kaparkona12.jpg",
        "fallbackUrl": "https://blogger.googleusercontent.com/img/b/R29vZ2xl/AVvXsEjOKC9j09eOyS4qnvu-02u8cUXHc5aAdfXTtAjqGKLkSxGQce5kRL3qSMS4wlvgRFn58GbG1L0wkYfKyviRC5ytUKv1i6tiTOzkJDTbABvdDudvgWHURRZVg5TNTbNun68JiT_rBIP-iq0/s1600/kaparkona12.jpg",
        "filename": "kaparkona12.jpg",
        "blogger": {
          "anchorHref": "https://blogger.googleusercontent.com/img/b/R29vZ2xl/AVvXsEjOKC9j09eOyS4qnvu-02u8cUXHc5aAdfXTtAjqGKLkSxGQce5kRL3qSMS4wlvgRFn58GbG1L0wkYfKyviRC5ytUKv1i6tiTOzkJDTbABvdDudvgWHURRZVg5TNTbNun68JiT_rBIP-iq0/s1600/kaparkona12.jpg",
          "displayedWidth": 320,
          "displayedHeight": 240,
          "originalWidth": null,
          "originalHeight": null
        },
        "caption": "Opevnenie z vonkajšej strany"
      },
      {
        "sourceUrl": "https://blogger.googleusercontent.com/img/b/R29vZ2xl/AVvXsEgqoXegz94xqyZ8RPTJk8nsu_GEtZ6AdLMFeU0VnlY87BhmmL2OLJ4YGNtzNp_22nrQkdiElj7z8i8C_dqw8pMJHOde8Yv8LByVJMps_vy65E8r02y9M5p0kcQ6uDbsm_ZvlL19v2Envvw/s0/kaparkona2.jpg",
        "fallbackUrl": "https://blogger.googleusercontent.com/img/b/R29vZ2xl/AVvXsEgqoXegz94xqyZ8RPTJk8nsu_GEtZ6AdLMFeU0VnlY87BhmmL2OLJ4YGNtzNp_22nrQkdiElj7z8i8C_dqw8pMJHOde8Yv8LByVJMps_vy65E8r02y9M5p0kcQ6uDbsm_ZvlL19v2Envvw/s1600/kaparkona2.jpg",
        "filename": "kaparkona2.jpg",
        "blogger": {
          "anchorHref": "https://blogger.googleusercontent.com/img/b/R29vZ2xl/AVvXsEgqoXegz94xqyZ8RPTJk8nsu_GEtZ6AdLMFeU0VnlY87BhmmL2OLJ4YGNtzNp_22nrQkdiElj7z8i8C_dqw8pMJHOde8Yv8LByVJMps_vy65E8r02y9M5p0kcQ6uDbsm_ZvlL19v2Envvw/s1600/kaparkona2.jpg",
          "displayedWidth": 320,
          "displayedHeight": 284,
          "originalWidth": null,
          "originalHeight": null
        },
        "caption": "1938"
      },
      {
        "sourceUrl": "https://blogger.googleusercontent.com/img/b/R29vZ2xl/AVvXsEhUYWsTguXlskG2E_ERkdDYsToPqVKDVyhrb3UuWWPMhy0X89PaeQyrYvmgABZzQFxUn2UFZAyBRrrNxl-zjLHN0tSviSiPR2B91iIx1sCQdBhtNvlikshrblsqaJ_WUmA-548Sc96pSbM/s0/kaparkona2012_3.jpg",
        "fallbackUrl": "https://blogger.googleusercontent.com/img/b/R29vZ2xl/AVvXsEhUYWsTguXlskG2E_ERkdDYsToPqVKDVyhrb3UuWWPMhy0X89PaeQyrYvmgABZzQFxUn2UFZAyBRrrNxl-zjLHN0tSviSiPR2B91iIx1sCQdBhtNvlikshrblsqaJ_WUmA-548Sc96pSbM/s1600/kaparkona2012_3.jpg",
        "filename": "kaparkona2012_3.jpg",
        "blogger": {
          "anchorHref": "https://blogger.googleusercontent.com/img/b/R29vZ2xl/AVvXsEhUYWsTguXlskG2E_ERkdDYsToPqVKDVyhrb3UuWWPMhy0X89PaeQyrYvmgABZzQFxUn2UFZAyBRrrNxl-zjLHN0tSviSiPR2B91iIx1sCQdBhtNvlikshrblsqaJ_WUmA-548Sc96pSbM/s1600/kaparkona2012_3.jpg",
          "displayedWidth": 320,
          "displayedHeight": 217,
          "originalWidth": null,
          "originalHeight": null
        },
        "caption": null
      },
      {
        "sourceUrl": "https://blogger.googleusercontent.com/img/b/R29vZ2xl/AVvXsEism1ts660Nslrl9hZ01YYHKtZ78-Wxwcifow4D6Itq9xElSBnU_Z5nuSvyZmC_TYBPrP4-g4J2Kkb9Es3rlJ8azzazGZ0wssFJj38MSHP0dP1n1josvYYhHalLOqzGrk6KjfmV68WkRGg/s0/kaparkona5.jpg",
        "fallbackUrl": "https://blogger.googleusercontent.com/img/b/R29vZ2xl/AVvXsEism1ts660Nslrl9hZ01YYHKtZ78-Wxwcifow4D6Itq9xElSBnU_Z5nuSvyZmC_TYBPrP4-g4J2Kkb9Es3rlJ8azzazGZ0wssFJj38MSHP0dP1n1josvYYhHalLOqzGrk6KjfmV68WkRGg/s1600/kaparkona5.jpg",
        "filename": "kaparkona5.jpg",
        "blogger": {
          "anchorHref": "https://blogger.googleusercontent.com/img/b/R29vZ2xl/AVvXsEism1ts660Nslrl9hZ01YYHKtZ78-Wxwcifow4D6Itq9xElSBnU_Z5nuSvyZmC_TYBPrP4-g4J2Kkb9Es3rlJ8azzazGZ0wssFJj38MSHP0dP1n1josvYYhHalLOqzGrk6KjfmV68WkRGg/s1600/kaparkona5.jpg",
          "displayedWidth": 320,
          "displayedHeight": 240,
          "originalWidth": null,
          "originalHeight": null
        },
        "caption": null
      },
      {
        "sourceUrl": "https://blogger.googleusercontent.com/img/b/R29vZ2xl/AVvXsEihPXP4FyGdJjt8mg6w3rZA1IxonLf4nwF6op1Syft2vsUoD2Ad4x4TVwkcC9RjBT2tg1pXYTsOldJv7YbOaHAuwIWarzHur8k3ZjSqw14lwMabzmjZra_hE7xievqShvQNyoKBX3wGJPA/s0/kaparkona7.jpg",
        "fallbackUrl": "https://blogger.googleusercontent.com/img/b/R29vZ2xl/AVvXsEihPXP4FyGdJjt8mg6w3rZA1IxonLf4nwF6op1Syft2vsUoD2Ad4x4TVwkcC9RjBT2tg1pXYTsOldJv7YbOaHAuwIWarzHur8k3ZjSqw14lwMabzmjZra_hE7xievqShvQNyoKBX3wGJPA/s1600/kaparkona7.jpg",
        "filename": "kaparkona7.jpg",
        "blogger": {
          "anchorHref": "https://blogger.googleusercontent.com/img/b/R29vZ2xl/AVvXsEihPXP4FyGdJjt8mg6w3rZA1IxonLf4nwF6op1Syft2vsUoD2Ad4x4TVwkcC9RjBT2tg1pXYTsOldJv7YbOaHAuwIWarzHur8k3ZjSqw14lwMabzmjZra_hE7xievqShvQNyoKBX3wGJPA/s1600/kaparkona7.jpg",
          "displayedWidth": 276,
          "displayedHeight": 320,
          "originalWidth": null,
          "originalHeight": null
        },
        "caption": "Rekonšrtukcia brány"
      },
      {
        "sourceUrl": "https://blogger.googleusercontent.com/img/b/R29vZ2xl/AVvXsEjNw-wSaYD59yKxciwLD6YxFwFNclel3zDa3NDDw-SiuK_5pka1PQocuuJPrV_DTGMOHLb1JJ5yt2kleSyBpT9ZC_8XbObSiDowHjWzVvB7f5VAo-KBp0Y3IHhQP2RXZri5sBC_H1KAlHk/s0/kaparkona8.jpg",
        "fallbackUrl": "https://blogger.googleusercontent.com/img/b/R29vZ2xl/AVvXsEjNw-wSaYD59yKxciwLD6YxFwFNclel3zDa3NDDw-SiuK_5pka1PQocuuJPrV_DTGMOHLb1JJ5yt2kleSyBpT9ZC_8XbObSiDowHjWzVvB7f5VAo-KBp0Y3IHhQP2RXZri5sBC_H1KAlHk/s1600/kaparkona8.jpg",
        "filename": "kaparkona8.jpg",
        "blogger": {
          "anchorHref": "https://blogger.googleusercontent.com/img/b/R29vZ2xl/AVvXsEjNw-wSaYD59yKxciwLD6YxFwFNclel3zDa3NDDw-SiuK_5pka1PQocuuJPrV_DTGMOHLb1JJ5yt2kleSyBpT9ZC_8XbObSiDowHjWzVvB7f5VAo-KBp0Y3IHhQP2RXZri5sBC_H1KAlHk/s1600/kaparkona8.jpg",
          "displayedWidth": 320,
          "displayedHeight": 240,
          "originalWidth": null,
          "originalHeight": null
        },
        "caption": "Pohľady z útesu"
      },
      {
        "sourceUrl": "https://blogger.googleusercontent.com/img/b/R29vZ2xl/AVvXsEjynKDA9JiYKAu4uifskTliiNwHhTBOx1g7q13vq3uE75MARvHOPDvA6UoTCA4l0IeSJshGkK31DHnicZGj0yg7phNBDma8GZeiyjlrvdkAKW4lZ0b_r4RrTeYXGTmX-bjaUY9CGt3OJno/s0/kaparkona9.jpg",
        "fallbackUrl": "https://blogger.googleusercontent.com/img/b/R29vZ2xl/AVvXsEjynKDA9JiYKAu4uifskTliiNwHhTBOx1g7q13vq3uE75MARvHOPDvA6UoTCA4l0IeSJshGkK31DHnicZGj0yg7phNBDma8GZeiyjlrvdkAKW4lZ0b_r4RrTeYXGTmX-bjaUY9CGt3OJno/s1600/kaparkona9.jpg",
        "filename": "kaparkona9.jpg",
        "blogger": {
          "anchorHref": "https://blogger.googleusercontent.com/img/b/R29vZ2xl/AVvXsEjynKDA9JiYKAu4uifskTliiNwHhTBOx1g7q13vq3uE75MARvHOPDvA6UoTCA4l0IeSJshGkK31DHnicZGj0yg7phNBDma8GZeiyjlrvdkAKW4lZ0b_r4RrTeYXGTmX-bjaUY9CGt3OJno/s1600/kaparkona9.jpg",
          "displayedWidth": 320,
          "displayedHeight": 240,
          "originalWidth": null,
          "originalHeight": null
        },
        "caption": null
      },
      {
        "sourceUrl": "https://blogger.googleusercontent.com/img/b/R29vZ2xl/AVvXsEh4PjpXPqi0TQPCCTDbDsGgpgXnHEADfsxz2Ebs6pJvG64439ErUlglfrQcvOJS6isxBcuXQK9LGT8LV_hvoz2UUeVhXY6RvtK5y7BvHGDEFlRRN4S1FHDxBytCgWlbQ02a2lygP7dHQVQ/s0/1168.jpg",
        "fallbackUrl": "https://blogger.googleusercontent.com/img/b/R29vZ2xl/AVvXsEh4PjpXPqi0TQPCCTDbDsGgpgXnHEADfsxz2Ebs6pJvG64439ErUlglfrQcvOJS6isxBcuXQK9LGT8LV_hvoz2UUeVhXY6RvtK5y7BvHGDEFlRRN4S1FHDxBytCgWlbQ02a2lygP7dHQVQ/s1600/1168.jpg",
        "filename": "1168.jpg",
        "blogger": {
          "anchorHref": "https://blogger.googleusercontent.com/img/b/R29vZ2xl/AVvXsEh4PjpXPqi0TQPCCTDbDsGgpgXnHEADfsxz2Ebs6pJvG64439ErUlglfrQcvOJS6isxBcuXQK9LGT8LV_hvoz2UUeVhXY6RvtK5y7BvHGDEFlRRN4S1FHDxBytCgWlbQ02a2lygP7dHQVQ/s1600/1168.jpg",
          "displayedWidth": 320,
          "displayedHeight": 279,
          "originalWidth": null,
          "originalHeight": null
        },
        "caption": "Dobytie Arkony 1168"
      }
    ],
    "tags": [
      "Náboženstvo a Legendy"
    ],
    "category": null,
    "location": {
      "name": "Mys Arkona, Rujana",
      "latitude": 54.679488,
      "longitude": 13.434391,
      "region": null,
      "country": "Nemecko"
    },
    "keyFacts": [
      {
        "label": "Obdobie",
        "value": "Pohanské chrámy v Polabí a Pobaltí ešte v 12. storočí (u nás pohanstvo končí v 9. stor.)",
        "icon": "calendar"
      },
      {
        "label": "Poloha",
        "value": "Arkona — ostrov Rujana (Rügen)",
        "icon": "map"
      },
      {
        "label": "Božstvo Retry / Riedegostu",
        "value": "Svarožič, neskôr Radegast / Radigast",
        "icon": "crown"
      },
      {
        "label": "Božstvo Arkony",
        "value": "Svantovít — socha so štyrmi hlavami a štyrmi krkmi",
        "icon": "star"
      },
      {
        "label": "Svantovítova družina",
        "value": "300 jazdcov na koňoch",
        "icon": "shield"
      },
      {
        "label": "Kľúčové svätyne",
        "value": "Riedegost-Retra, Arkona, Štetín, Wolin, Wolgast, Gochov, Gross Raden, Korenica",
        "icon": "building"
      },
      {
        "label": "Ďalší bohovia",
        "value": "Triglav, Rugievit, Porevit, Porenut, Gerovit-Jarovit",
        "icon": "flag"
      },
      {
        "label": "Pramene (kronikári)",
        "value": "Thietmar Merseburský, Adam Brémsky, Helmold, Ebbon, Herbord",
        "icon": "scroll"
      },
      {
        "label": "Kmene",
        "value": "Ratari a Ráni",
        "icon": "users"
      },
      {
        "label": "Zničenie Arkony",
        "value": "Dánsky kráľ Valdemar, r. 1168",
        "icon": "sword"
      }
    ],
    "timeline": [
      {
        "year": "1018",
        "title": "Smrť Thietmara — najstaršia správa o Svarožičovi",
        "description": "Kronikár Thietmar Merseburský, ktorý podal najstaršiu a vierohodnú správu o bohu Svarožičovi a svätyni Riedegost, zomrel roku 1018.",
        "type": "event"
      },
      {
        "year": "1068",
        "title": "Ukoristenie posvätného koňa Retry",
        "description": "Veštebného koňa svätyne, ktorý prekračoval kopije, ukoristil zrejme v bitke biskup Burchard z Halberstadtu.",
        "type": "event"
      },
      {
        "year": "koniec 11. – 12. stor.",
        "title": "Zánik svätyne Retra",
        "description": "Text neuvádza presný rok, len rozpätie „koncom 11. alebo v 12. stor.“.",
        "type": "destruction"
      },
      {
        "year": "po roku 1128",
        "title": "Rozsekanie sochy Triglava v Štetíne",
        "description": "Biskup Otto dal sochu Triglava rozsekať a tri strieborné hlavy poslať do Ríma.",
        "type": "destruction"
      },
      {
        "year": "1168",
        "title": "Vyvrátenie Arkony Dánmi",
        "description": "Rivali Ránov Dáni vyvrátili Arkonu; kráľ Valdemar dal sochu Svantovíta potupiť, rozsekať a spáliť, Slovania boli nútení ku krstu.",
        "type": "destruction"
      },
      {
        "year": "1921",
        "title": "Schuchhardt hľadal Svantovítov chrám v Arkone",
        "description": "Nemecký archeológ objavil zvyšky štvorcovej stavby, ktoré pokladal za hľadanú svätyňu.",
        "type": "discovery"
      },
      {
        "year": "1922",
        "title": "Pokus lokalizovať Retru na Feldberg",
        "description": "Schuchhardt sa pokúsil stotožniť Retru s hradiskom Feldberg pri rovnomennom jazere.",
        "type": "discovery"
      },
      {
        "year": "1967",
        "title": "Herrmann vyvrátil stotožnenie Feldbergu s Retrou",
        "description": "Novšie výskumy ukázali, že feldberská svätyňa je iného typu a staršia (7.–8. stor.), teda nie totožná s Retrou.",
        "type": "discovery"
      },
      {
        "year": "1969–1970",
        "title": "Revízny výskum Berlekampa v Arkone",
        "description": "Ukázal, že Schuchhardtove „zvyšky chrámu“ boli skôr stopy vnútorného opevnenia; vlastná svätyňa zrejme pohltená morom.",
        "type": "discovery"
      },
      {
        "year": "7.–8. storočie",
        "title": "Vznik svätyne na hradisku Feldberg",
        "description": "Datovanie feldberskej svätyne do staršej doby, dôvod nemožnosti stotožnenia s historickou Retrou.",
        "type": "era"
      }
    ],
    "quotes": [],
    "blocks": [
      {
        "__component": "content.rich-text",
        "body": [
          {
            "type": "paragraph",
            "children": [
              {
                "type": "text",
                "text": "Nad skalami Arkony týči sa orlie hniezdo ",
                "italic": true
              },
              {
                "type": "text",
                "text": "Kde údery vĺn bijú o východné veže ",
                "italic": true
              },
              {
                "type": "text",
                "text": "Statočný orol sedí na skalnom tróne- ",
                "italic": true
              },
              {
                "type": "text",
                "text": "Ochranca slovanských krajov, slobodný syn nebies ",
                "italic": true
              },
              {
                "type": "text",
                "text": "Ó slovanský orol, chráň národy Slovanov ",
                "italic": true
              },
              {
                "type": "text",
                "text": "Ochraňuj slovanské zvyky a reč ",
                "italic": true
              },
              {
                "type": "text",
                "text": "Ochraňuj nás a našu rodnú zem ",
                "italic": true
              },
              {
                "type": "text",
                "text": "Stráž od rána, stráž počas dňa ",
                "italic": true
              },
              {
                "type": "text",
                "text": "Hliadkuj cez polnoc najostrejším zrakom.",
                "italic": true
              },
              {
                "type": "text",
                "text": " \n Absolútna väčšina Slovanských svätýň na našich územiach stála pod holým nebom, ako nám to potvrdzuje aj svätyňa z "
              },
              {
                "type": "link",
                "url": "http://slovanske-hradiska.blogspot.com/search/label/Most%20pri%20Bratislave%20-%20Prv%C3%A1%20staroslovansk%C3%A1%20sv%C3%A4ty%C5%88a%20na%20Slovensku",
                "children": [
                  {
                    "type": "text",
                    "text": "Mostu pri Bratislave"
                  }
                ]
              },
              {
                "type": "text",
                "text": ", ktorá je opísaná na inom mieste. Skutočné pohanské chrámy Slovanov v takej forme ako ich poznáme z neskoršej kresťanskej doby - tzn. zakryté budovy, vznikali iba v Polabskej a Pobaltskej oblasti. Tu nachádzame pohanské chrámy ešte v 12. storočí, zatiaľ čo na našom území pohanstvo vystriedala nová viera v jediného Boha už v priebehu 9. storočia, hlavne pokiaľ ide o väčšie mocenské centrá. Nemeckí obyvatelia Pobaltia a Polabia v priebehu 10. až 12. storočia si brali boj proti pohanstvu za zámienku pre svoje vojnové ciele a v tejto súvislosti nám zanechali početné opisy pohanských bohov a svätýň tamojších Slovanov. "
              }
            ]
          }
        ]
      },
      {
        "__component": "content.rich-text",
        "body": [
          {
            "type": "paragraph",
            "children": [
              {
                "type": "text",
                "text": "Kde východné moria zvučia skaly Arkony ",
                "italic": true
              },
              {
                "type": "text",
                "text": "A nad strmým útesom orol vládne ",
                "italic": true
              },
              {
                "type": "text",
                "text": "Kde v hlbokom údolí osada spočíva ",
                "italic": true
              },
              {
                "type": "text",
                "text": "Ktorú odráža belasá hladina ",
                "italic": true
              },
              {
                "type": "text",
                "text": "Tá prekrásna zem je moja Rujana ",
                "italic": true
              },
              {
                "type": "text",
                "text": "Najmilovanejšia otčina ",
                "italic": true
              },
              {
                "type": "text",
                "text": "RETRA",
                "bold": true
              }
            ]
          }
        ]
      },
      {
        "__component": "content.rich-text",
        "body": [
          {
            "type": "paragraph",
            "children": [
              {
                "type": "text",
                "text": "Najstaršiu zmienku prináša Thietmar, a to o Riedegoste, centre kmeňa Ratarov. Drevená svätyňa tu stála uprostred hája na zvieracích rohoch v základoch, ktoré zrejme plnili apotropaickú funkciu - podobná praktika bola archeologicky zistená napríklad v základoch opevnenia v Gdansku, kde boli nájdené turie rohy. Vonkajšie steny svätyne zdobili početné vyrezávané obrazy bohov a bohýň, vnútri chrámu stáli sochy označené menami bohov v čele s hlavným božstvom Svarožičom, vedľa nich práporce a vojnové odznaky. Podľa Thietmara Merseburského, ktorý zomrel roku 1018 a podal o tomto bohu najstaršie a zároveň veľmi vierohodné správy, sa pôvodne nazýval Svarožič. Svarožič, syn boha Svaroga, boh slnka a ohňa, bol uctievaný v 11. a 12. storočí aj v Rusku. V 11. storočí sa z prameňov o polabských Slovanov meno Svarožič stráca a ten istý boh je nazývaný Radegast alebo Radigast, podľa pôvodného mena svätyne. Thietmar popisuje svätyňu i obrady veľmi podrobne. V kraji Ratarov vraj stál pevný hrad trojbokej podoby s tromi bránami, zvaný Riedegost, obklopený posvätným lesom, v ktorom sa nikdy nerúbali stromy. Dve brány tohto hradu boli prístupné pre všetkých, tretia, najmenšia, na východnej strane, viedla na chodník k jazeru. V hrade bola len jedna svätyňa, majstrovsky zbudovaná z dreva, ktorá spočívala ako už bolo povedané na základe z rohov divokých zvierat. Zvonku bola zdobená obrazmi prekrásne vyrezávaných bohov a bohýň."
              }
            ]
          }
        ]
      },
      {
        "__component": "content.image-block",
        "imageRef": {
          "sourceUrl": "https://blogger.googleusercontent.com/img/b/R29vZ2xl/AVvXsEj1nQOu7J2DM5_d4KFJ75V-LQRAFlUh6h2KWinsaPofO993oj8t74HP4Olv1fAHDJ_w2pcjL3WVF3ObMREy9GfLFmQArRQhgWADbmQajoW18q75RmNPtQr8NImTtluJcSLYlWjCokANrc0/s0/retra.jpeg",
          "fallbackUrl": "https://blogger.googleusercontent.com/img/b/R29vZ2xl/AVvXsEj1nQOu7J2DM5_d4KFJ75V-LQRAFlUh6h2KWinsaPofO993oj8t74HP4Olv1fAHDJ_w2pcjL3WVF3ObMREy9GfLFmQArRQhgWADbmQajoW18q75RmNPtQr8NImTtluJcSLYlWjCokANrc0/s1600/retra.jpeg",
          "filename": "retra.jpeg",
          "blogger": {
            "anchorHref": "https://blogger.googleusercontent.com/img/b/R29vZ2xl/AVvXsEj1nQOu7J2DM5_d4KFJ75V-LQRAFlUh6h2KWinsaPofO993oj8t74HP4Olv1fAHDJ_w2pcjL3WVF3ObMREy9GfLFmQArRQhgWADbmQajoW18q75RmNPtQr8NImTtluJcSLYlWjCokANrc0/s1600/retra.jpeg",
            "displayedWidth": 320,
            "displayedHeight": 311,
            "originalWidth": null,
            "originalHeight": null
          }
        },
        "alt": "Mnohí sa domnievajú, že Retrou bol ostrov Fischerinsel na jazere Tollensesee",
        "caption": "Mnohí sa domnievajú, že Retrou bol ostrov Fischerinsel na jazere Tollensesee",
        "position": "right",
        "showCaption": true,
        "width": "40",
        "aspectRatio": "auto",
        "rounded": true,
        "shadow": true
      },
      {
        "__component": "content.rich-text",
        "body": [
          {
            "type": "paragraph",
            "children": [
              {
                "type": "text",
                "text": "Vnútri svätyne stáli sochy bohov v helmách a pancieroch a každý boh mal naspodku vyryté svoje meno. Prvý medzi nimi bol Svarožič (Zuarasici), obzvlášť uctievaný všetkými pohanmi. Boli tam aj zástavy, ktoré sa vynášali jedine v čase vojny. To všetko strážili kňazi, ktorí jediní mali právo sedieť, keď sa bohom obetovalo alebo keď sa ich snažili uzmieriť; ostatní prítomní stáli. "
              },
              {
                "type": "text",
                "text": "Či vidíš kraj kde čajka lieta ",
                "italic": true
              },
              {
                "type": "text",
                "text": "Nad plážou v slnečnom kúpeli? ",
                "italic": true
              },
              {
                "type": "text",
                "text": "Kde v skalnej úžine tróni odvážny orol. ",
                "italic": true
              },
              {
                "type": "text",
                "text": "Do diaľav si hľadí, chráni svoju dŕžavu ",
                "italic": true
              },
              {
                "type": "text",
                "text": "Pokrytú kŕdľami morských vtákov ",
                "italic": true
              },
              {
                "type": "text",
                "text": "V stovkách zálivov ich hlas možno počuť ",
                "italic": true
              },
              {
                "type": "text",
                "text": "Znova a znova...",
                "italic": true
              }
            ]
          }
        ]
      },
      {
        "__component": "content.rich-text",
        "body": [
          {
            "type": "paragraph",
            "children": [
              {
                "type": "text",
                "text": "Neskorší svedok z konca 11. stor. - Adam Brémsky - poznal túto svätyňu pod menom Retra, zatiaľ čo boha, ktorého zlatá socha mala spočívať na purpurovom lôžku, nazýva Redigastom. Chrám, vzdialený štyri dni cesty od Hamburgu, stál na mieste obklopenom hlbokým jazerom; cezeň viedol drevený most, po ktorom prechádzali tí, ktorí chceli obetovať alebo žiadať veštby tamojšieho orákula. Veštby sa robili pomocou posvätného koňa, ktorý prekračoval určitým spôsobom kopije. R. 1068 ukoristil tohto koňa, zrejme v bitke, kam ho vodili, biskup Burchard z Halberstadte. Retra sama však zanikla zrejme neskôr, koncom 11. alebo v 12. stor."
              }
            ]
          }
        ]
      },
      {
        "__component": "content.image-block",
        "imageRef": {
          "sourceUrl": "https://blogger.googleusercontent.com/img/b/R29vZ2xl/AVvXsEgsTF8aAo_SVexcRGxl4FttZzCzs0kplhgqrmiv_9TK72vi5fZoDeqfPlzWMxB8NSmQK-QYbJJTAnBQGhyphenhyphenTPaMTIBeTWGhF6N8nTRmj2hqjk7FiKyol1svutmG_CjNOqARZr3zkOd4F004/s0/fischerinsel++modla.jpeg",
          "fallbackUrl": "https://blogger.googleusercontent.com/img/b/R29vZ2xl/AVvXsEgsTF8aAo_SVexcRGxl4FttZzCzs0kplhgqrmiv_9TK72vi5fZoDeqfPlzWMxB8NSmQK-QYbJJTAnBQGhyphenhyphenTPaMTIBeTWGhF6N8nTRmj2hqjk7FiKyol1svutmG_CjNOqARZr3zkOd4F004/s1600/fischerinsel++modla.jpeg",
          "filename": "fischerinsel++modla.jpeg",
          "blogger": {
            "anchorHref": "https://blogger.googleusercontent.com/img/b/R29vZ2xl/AVvXsEgsTF8aAo_SVexcRGxl4FttZzCzs0kplhgqrmiv_9TK72vi5fZoDeqfPlzWMxB8NSmQK-QYbJJTAnBQGhyphenhyphenTPaMTIBeTWGhF6N8nTRmj2hqjk7FiKyol1svutmG_CjNOqARZr3zkOd4F004/s1600/fischerinsel++modla.jpeg",
            "displayedWidth": 97,
            "displayedHeight": 320,
            "originalWidth": null,
            "originalHeight": null
          }
        },
        "alt": "Známa modla z Fischerinsel",
        "caption": "Známa modla z Fischerinsel",
        "position": "left",
        "showCaption": true,
        "width": "40",
        "aspectRatio": "auto",
        "rounded": true,
        "shadow": true
      },
      {
        "__component": "content.rich-text",
        "body": [
          {
            "type": "paragraph",
            "children": [
              {
                "type": "text",
                "text": "Archeológ C. Schuchhardt sa v r. 1922 pokúsil lokalizovať Retru na hradisko Feldberg na brehu rovnomenného jazera. Novšie výskumy J. Herrmanna z r. 1967 však tento predpoklad nepotvrdil; hradisko Feldberg malo síce svätyňu, avšak iného typu a okrem toho pochádza z oveľa staršej doby, zo 7.-8. stor., takže s historickou Retrou nemôže byť totožné. Tamojšia svätyňa pozostávala z jednoduchej obdĺžnikovej stavby s náznakom vstupného priestoru, oddelená od hradiska symbolickou priekopou. Jej prítomnosť na tak starobylom hradisku naznačuje, že takéto svätyne vznikali v tejto oblasti veľmi skoro. V dobe, kedy Thietmar písal svoju kroniku, museli mať polabskí Slovania už väčší počet chrámov, pretože podľa jeho svedectva mal každý kraj svoju svätyňu, aj keď každá nemusela byť chrámovou stavbou v pravom slova zmysle."
              }
            ]
          }
        ]
      },
      {
        "__component": "content.image-block",
        "imageRef": {
          "sourceUrl": "https://blogger.googleusercontent.com/img/b/R29vZ2xl/AVvXsEhzqccGKlAY6zzCPPVV5AnuBVavR6Vt7_jjsxsmcddNnVtB_EitrtZAyl3BwLz9IMb-YA8EehFhqAa0tZwGx6x9UHweRyO1dxHrJszLsQ4bM5aLdIumnekH6aQPFwldnQvm_tSp-KdsUXQ/s0/vnutro+svatyne.jpg",
          "fallbackUrl": "https://blogger.googleusercontent.com/img/b/R29vZ2xl/AVvXsEhzqccGKlAY6zzCPPVV5AnuBVavR6Vt7_jjsxsmcddNnVtB_EitrtZAyl3BwLz9IMb-YA8EehFhqAa0tZwGx6x9UHweRyO1dxHrJszLsQ4bM5aLdIumnekH6aQPFwldnQvm_tSp-KdsUXQ/s1600/vnutro+svatyne.jpg",
          "filename": "vnutro+svatyne.jpg",
          "blogger": {
            "anchorHref": "https://blogger.googleusercontent.com/img/b/R29vZ2xl/AVvXsEhzqccGKlAY6zzCPPVV5AnuBVavR6Vt7_jjsxsmcddNnVtB_EitrtZAyl3BwLz9IMb-YA8EehFhqAa0tZwGx6x9UHweRyO1dxHrJszLsQ4bM5aLdIumnekH6aQPFwldnQvm_tSp-KdsUXQ/s1600/vnutro+svatyne.jpg",
            "displayedWidth": null,
            "displayedHeight": null,
            "originalWidth": null,
            "originalHeight": null
          }
        },
        "alt": "Arkona, Retra a iné pohanské svätyne západných Slovanov",
        "caption": "",
        "position": "right",
        "showCaption": false,
        "width": "50",
        "aspectRatio": "auto",
        "rounded": true,
        "shadow": true
      },
      {
        "__component": "content.rich-text",
        "body": [
          {
            "type": "heading",
            "level": 2,
            "children": [
              {
                "type": "text",
                "text": "ARKONA"
              }
            ]
          }
        ]
      },
      {
        "__component": "content.rich-text",
        "body": [
          {
            "type": "paragraph",
            "children": [
              {
                "type": "text",
                "text": "Miesto Svarožiča - Radegasta zaujal Svantovít, boh Ránov zo svätyne v Arkone na ostrove Rujana. Snáď o žiadnom slovanskom bohu sa nenapísalo toľko vedeckých i polovedeckých článkov a štúdií ako o ňom. Niektorí bádatelia uvažovali, že to vlastne nebol pohanský boh, ale pohanské zbožštenie svätého Víta, k čomu zvádzala príbuznosť mena aj niektoré údaje kronikárov. Ale nech už Svantovítovo meno vzniklo z akéhokoľvek základu, je isté, že v 12. storočí nemal s kresťanským svätcom vôbec nič spoločné a že bol plnokrvným pohanským bohom so všetkými prednosťami, mocenskými požiadavkami a atribútmi."
              }
            ]
          }
        ]
      },
      {
        "__component": "content.rich-text",
        "body": [
          {
            "type": "paragraph",
            "children": [
              {
                "type": "text",
                "text": "Z hĺbok mora, z najhlbšieho dna ",
                "italic": true
              },
              {
                "type": "text",
                "text": "Znejú večné zvony tlmené ",
                "italic": true
              },
              {
                "type": "text",
                "text": "Zvonia, aby zvestovali chýry o čarovnom pradávnom meste. ",
                "italic": true
              },
              {
                "type": "text",
                "text": "V náručí prílivu potopené ",
                "italic": true
              },
              {
                "type": "text",
                "text": "Ostali ruiny pevne stáť. ",
                "italic": true
              },
              {
                "type": "text",
                "text": "Zanechávajú zlaté záblesky ",
                "italic": true
              },
              {
                "type": "text",
                "text": "Jagajúce sa na povrchu mora.",
                "italic": true
              }
            ]
          }
        ]
      },
      {
        "__component": "content.image-block",
        "imageRef": {
          "sourceUrl": "https://blogger.googleusercontent.com/img/b/R29vZ2xl/AVvXsEgYOH3Tv2Dll3LFlezKTHnKpLfNSXT2VUmu_rnu-tlwrzeZTRmZckTTFDmE7Mn_g8IZR7ZDdf7XsReZ1x71X6JekBXvR044F5aW65MPHI1iBo8ApY9ekKm6YMJq7zhp7xgxIvI8ubvUwqo/s0/800px-Burgwall_Arkona.jpg",
          "fallbackUrl": "https://blogger.googleusercontent.com/img/b/R29vZ2xl/AVvXsEgYOH3Tv2Dll3LFlezKTHnKpLfNSXT2VUmu_rnu-tlwrzeZTRmZckTTFDmE7Mn_g8IZR7ZDdf7XsReZ1x71X6JekBXvR044F5aW65MPHI1iBo8ApY9ekKm6YMJq7zhp7xgxIvI8ubvUwqo/s1600/800px-Burgwall_Arkona.jpg",
          "filename": "800px-Burgwall_Arkona.jpg",
          "blogger": {
            "anchorHref": "https://blogger.googleusercontent.com/img/b/R29vZ2xl/AVvXsEgYOH3Tv2Dll3LFlezKTHnKpLfNSXT2VUmu_rnu-tlwrzeZTRmZckTTFDmE7Mn_g8IZR7ZDdf7XsReZ1x71X6JekBXvR044F5aW65MPHI1iBo8ApY9ekKm6YMJq7zhp7xgxIvI8ubvUwqo/s1600/800px-Burgwall_Arkona.jpg",
            "displayedWidth": 320,
            "displayedHeight": 240,
            "originalWidth": null,
            "originalHeight": null
          }
        },
        "alt": "Pohľad na časť hradiska Arkona. Ako je vidieť, väčšia časť sa zrútila spolu s útesom do mora",
        "caption": "Pohľad na časť hradiska Arkona. Ako je vidieť, väčšia časť sa zrútila spolu s útesom do mora",
        "position": "right",
        "showCaption": true,
        "width": "50",
        "aspectRatio": "auto",
        "rounded": true,
        "shadow": true
      },
      {
        "__component": "content.rich-text",
        "body": [
          {
            "type": "paragraph",
            "children": [
              {
                "type": "text",
                "text": "Svantovít sa dostal v 12. storočí na popredné miesto medzi pobaltskými a polabskými slovanskými bohmi predovšetkým vďaka obchodným, hospodárskym a vojenským úspechom Rujany a Ránov a tiež preto, že ostatní pohanskí bohovia postupne odpadali. Prinášali mu dary nielen pohania, ale aj kresťanskí panovníci, ak chceli s Ránmi dobre vychádzať. Dane odvádzané Svantovítovi a jeho kňazom boli pravidelné a platili ich domáci i cudzinci. Patrila mu tiež tretina nepriateľskej výzbroje a koristi dobytej vo vojnách. Svantovít mal nielen kňaza, ale aj vlastnú družinu zloženú z 300 jazdcov na koňoch. Títo bojovníci odovzdávali kňazovi pre boha všetku korisť aj zisky z lúpeží a vojen. Majetok Svantovítov bol ukrytý v truhlici pod závorami a zahŕňal peniaze, ozdoby, drahé látky a iné predmety, napr. drahocenný pohár od dánskeho kráľa."
              }
            ]
          }
        ]
      },
      {
        "__component": "content.image-block",
        "imageRef": {
          "sourceUrl": "https://blogger.googleusercontent.com/img/b/R29vZ2xl/AVvXsEhpnM__2JkE4bq7uf_g5njcMRM7fatCMAlc6u1pQeBTrMxqyjuzv1rL-Ri3KQ6P8TEJleZ8vkK4qTH6-skGiv-Cz0rruvru68BI81ucMoVefzetj6Vi2HioPuK1HulXPsHhVeTdN1-_grs/s0/Retra+2.jpeg",
          "fallbackUrl": "https://blogger.googleusercontent.com/img/b/R29vZ2xl/AVvXsEhpnM__2JkE4bq7uf_g5njcMRM7fatCMAlc6u1pQeBTrMxqyjuzv1rL-Ri3KQ6P8TEJleZ8vkK4qTH6-skGiv-Cz0rruvru68BI81ucMoVefzetj6Vi2HioPuK1HulXPsHhVeTdN1-_grs/s1600/Retra+2.jpeg",
          "filename": "Retra+2.jpeg",
          "blogger": {
            "anchorHref": "https://blogger.googleusercontent.com/img/b/R29vZ2xl/AVvXsEhpnM__2JkE4bq7uf_g5njcMRM7fatCMAlc6u1pQeBTrMxqyjuzv1rL-Ri3KQ6P8TEJleZ8vkK4qTH6-skGiv-Cz0rruvru68BI81ucMoVefzetj6Vi2HioPuK1HulXPsHhVeTdN1-_grs/s1600/Retra+2.jpeg",
            "displayedWidth": 320,
            "displayedHeight": 178,
            "originalWidth": null,
            "originalHeight": null
          }
        },
        "alt": "Arkona, Retra a iné pohanské svätyne západných Slovanov",
        "caption": "",
        "position": "center",
        "showCaption": false,
        "width": "60",
        "aspectRatio": "auto",
        "rounded": true,
        "shadow": true
      },
      {
        "__component": "content.rich-text",
        "body": [
          {
            "type": "paragraph",
            "children": [
              {
                "type": "text",
                "text": "Svantovítov chrám nestál na osamelom mieste, ale na planine uprostred mesta, bol však ohradený drevenou palisádou a mal len jeden vchod. Už sama ohrada bola zdobená vyrezávaním a maľbami, napospol vraj hrubými. Vnútri ohrady bola vonkajšia chrámová budova s červenou strechou. Vnútornú chrámovú stavbu tvorili len stĺpy, medzi ktorými boli látkové zásteny. V nej stála ohromná socha v nadľudskej veľkosti so štyrmi krkmi a štyrmi hlavami, z ktorých dve sa pozerali dopredu a dve dozadu. Vlasy mala pristrihnuté do obvyklého účesu obyvateľov Rujany, fúzy taktiež vyholené. V pravej ruke držala kovový roh naplnený vínom. Podľa stavu vína, ktorým kňaz každým rokom roh napĺňal, sa veštila úroda v budúcom roku. Odev sochy siahal k holeniam a nohy boli vyrezané i s kĺbmi tak majstrovsky, že spojenie bolo viditeľné len pri starostlivom pozorovaní. Neďaleko sochy ležalo zubadlo, sedlo a početné božské odznaky, z ktorých vynikal predovšetkým meč so skvostným tepaním pošvy a rukoväťou a strieborným zovňajškom. Do svätyne, ktorej poklady strážila spomenutá družina 300 jazdcov, smel vstúpiť len kňaz, a to so zatajeným dychom - pre každé nadýchnutie sa musel vracať ku vchodu."
              }
            ]
          }
        ]
      },
      {
        "__component": "content.image-block",
        "imageRef": {
          "sourceUrl": "https://blogger.googleusercontent.com/img/b/R29vZ2xl/AVvXsEipsA2INRRc16jktz1a5DuUs2jK7JhwAE_oVuDypDoTHmMfKobdv2zcda3TaBagVzX77aj4FqX1yP4Es6ZbX4aDi_5KsVPFGDIYfqCoZCSxn7HduwiwWTUmJNXh9pkDW2dTmdYLLXxkptY/s0/arkona2.jpg",
          "fallbackUrl": "https://blogger.googleusercontent.com/img/b/R29vZ2xl/AVvXsEipsA2INRRc16jktz1a5DuUs2jK7JhwAE_oVuDypDoTHmMfKobdv2zcda3TaBagVzX77aj4FqX1yP4Es6ZbX4aDi_5KsVPFGDIYfqCoZCSxn7HduwiwWTUmJNXh9pkDW2dTmdYLLXxkptY/s1600/arkona2.jpg",
          "filename": "arkona2.jpg",
          "blogger": {
            "anchorHref": "https://blogger.googleusercontent.com/img/b/R29vZ2xl/AVvXsEipsA2INRRc16jktz1a5DuUs2jK7JhwAE_oVuDypDoTHmMfKobdv2zcda3TaBagVzX77aj4FqX1yP4Es6ZbX4aDi_5KsVPFGDIYfqCoZCSxn7HduwiwWTUmJNXh9pkDW2dTmdYLLXxkptY/s1600/arkona2.jpg",
            "displayedWidth": 320,
            "displayedHeight": 240,
            "originalWidth": null,
            "originalHeight": null
          }
        },
        "alt": "Mys Arkona dnes",
        "caption": "Mys Arkona dnes",
        "position": "right",
        "showCaption": true,
        "width": "40",
        "aspectRatio": "auto",
        "rounded": true,
        "shadow": true
      },
      {
        "__component": "content.rich-text",
        "body": [
          {
            "type": "paragraph",
            "children": [
              {
                "type": "text",
                "text": "U Svantovíta sa tiež veštilo a konali sa posvätné obrady. Keď bola veštba nepriaznivá, odložili vojnové ťaženie alebo obchodné rokovania na dobu vhodnejšiu. Veľký význam mal kult poľnohospodársky. Každým rokom naplnil kňaz Svantovítov roh čerstvým vínom a po roku skúmal, koľko ubudlo. Keď bolo vína dosť, mala byť dobrá úroda, keď málo, neúroda. Podľa toho potom riadili ukladanie zásob a spotrebu potravín v danom roku, aby vystačili aj v rokoch neúrodných. Na poctu Svantovíta a na účely veštby piekli kruhový koláč s medom, ktorý bol takmer tak veľký ako človek. Po obrade nastala veľká slávnosť a hodovanie, pri ktorom konzumovali aj obete predložené bohu. Svantovít mal vlastného bieleho koňa, na ktorom smel jazdiť len kňaz; v noci vraj na ňom jazdil boh sám - to bol kôň spotený a špinavý. Podľa kronikára Helmonda vraj bol Svantovítovi každoročne obetovaný človek, kresťan určený žrebom."
              }
            ]
          }
        ]
      },
      {
        "__component": "content.image-block",
        "imageRef": {
          "sourceUrl": "https://blogger.googleusercontent.com/img/b/R29vZ2xl/AVvXsEjG7-tRabMtFLK0pvN5k5O_JOgkpzQozUhCPjXQ7lW1bFkF6H9-V0Dq2tF6E6wHRBc-ZVdRGfYit3EzgGHQxjz-r7o4qoIt_SbZ5PNHaFP4D3YvGuXEQ2fD7BRlI6XL4glH09bgLXL77YA/s0/450px-Svantevit-Statue.jpg",
          "fallbackUrl": "https://blogger.googleusercontent.com/img/b/R29vZ2xl/AVvXsEjG7-tRabMtFLK0pvN5k5O_JOgkpzQozUhCPjXQ7lW1bFkF6H9-V0Dq2tF6E6wHRBc-ZVdRGfYit3EzgGHQxjz-r7o4qoIt_SbZ5PNHaFP4D3YvGuXEQ2fD7BRlI6XL4glH09bgLXL77YA/s1600/450px-Svantevit-Statue.jpg",
          "filename": "450px-Svantevit-Statue.jpg",
          "blogger": {
            "anchorHref": "https://blogger.googleusercontent.com/img/b/R29vZ2xl/AVvXsEjG7-tRabMtFLK0pvN5k5O_JOgkpzQozUhCPjXQ7lW1bFkF6H9-V0Dq2tF6E6wHRBc-ZVdRGfYit3EzgGHQxjz-r7o4qoIt_SbZ5PNHaFP4D3YvGuXEQ2fD7BRlI6XL4glH09bgLXL77YA/s1600/450px-Svantevit-Statue.jpg",
            "displayedWidth": 240,
            "displayedHeight": 320,
            "originalWidth": null,
            "originalHeight": null
          }
        },
        "alt": "Socha Svantovíta dnes",
        "caption": "Socha Svantovíta dnes",
        "position": "right",
        "showCaption": true,
        "width": "40",
        "aspectRatio": "auto",
        "rounded": true,
        "shadow": true
      },
      {
        "__component": "content.embed",
        "provider": "vimeo",
        "embedId": "35500856",
        "url": "https://player.vimeo.com/video/35500856",
        "caption": ""
      },
      {
        "__component": "content.rich-text",
        "body": [
          {
            "type": "paragraph",
            "children": [
              {
                "type": "text",
                "text": "A námorník,"
              },
              {
                "type": "text",
                "text": "\n"
              },
              {
                "type": "text",
                "text": "Ktorý magický blikot aspoň raz uvidí"
              },
              {
                "type": "text",
                "text": "\n"
              },
              {
                "type": "text",
                "text": "V oslnivej večernej zore"
              },
              {
                "type": "text",
                "text": "\n"
              },
              {
                "type": "text",
                "text": "Na to miesto vždy sa vráti"
              },
              {
                "type": "text",
                "text": "\n"
              },
              {
                "type": "text",
                "text": "Aj keď navôkol mu hrozia útesy."
              },
              {
                "type": "text",
                "text": "\n"
              },
              {
                "type": "text",
                "text": "Na to miesto vždy sa vráti"
              },
              {
                "type": "text",
                "text": "\n"
              },
              {
                "type": "text",
                "text": "Znova a znova..."
              }
            ]
          }
        ]
      },
      {
        "__component": "content.rich-text",
        "body": [
          {
            "type": "paragraph",
            "children": [
              {
                "type": "text",
                "text": "Roku 1168 bola Arkona vyvrátená vojenskými a obchodnými rivalmi Ránov - Dánmi. Dánsky kráľ Valdemar dal sochu Svantovíta pred očami zdesených a pokorených Ránov potupiť, rozsekať a spáliť. Slovanov potom prinútil dať sa pokrstiť."
              }
            ]
          }
        ]
      },
      {
        "__component": "content.rich-text",
        "body": [
          {
            "type": "paragraph",
            "children": [
              {
                "type": "text",
                "text": "R. 1921 sa pokúsil nemecký archeológ C. Schuchhardt Svantovítov chrám nájsť. Objavil zvyšky štvorcovej stavby, v ktorých videl hľadanú svätyňu, ktorej kreslenú rekonštrukciu potom prevzala rada publikácií. Z hľadiska súčasných výskumných metód však nemožno považovať výsledky Schuchhardtova výskumu za spoľahlivé a revízny výskum H. Berlekampa z rokov 1969-1970 skutočne tiež ukázal, že to, čo Schuchhardt považoval za zvyšky chrámu, boli skôr stopy vnútorného opevnenia hradiska, zatiaľ čo vlastná svätyňa stála zrejme na mieste, ktoré už dávno pohltilo more."
              }
            ]
          }
        ]
      },
      {
        "__component": "content.image-block",
        "imageRef": {
          "sourceUrl": "https://blogger.googleusercontent.com/img/b/R29vZ2xl/AVvXsEg0bRGT0lY7MtIQenbXdx56YFqivx4Eyz1H4zccBTtG8ua8gAxfh9WKkSt5HzayvXCAoXunpsKV3lp7yfgFtCcLy88SZrCBDPY8RPMN-xcSdA9oSdMTdQBBqCHY2AfQrddsQBvjEIFW88k/s0/zvrhnutie+Svantovi%CC%81ta.JPG",
          "fallbackUrl": "https://blogger.googleusercontent.com/img/b/R29vZ2xl/AVvXsEg0bRGT0lY7MtIQenbXdx56YFqivx4Eyz1H4zccBTtG8ua8gAxfh9WKkSt5HzayvXCAoXunpsKV3lp7yfgFtCcLy88SZrCBDPY8RPMN-xcSdA9oSdMTdQBBqCHY2AfQrddsQBvjEIFW88k/s1600/zvrhnutie+Svantovi%CC%81ta.JPG",
          "filename": "zvrhnutie+Svantovíta.JPG",
          "blogger": {
            "anchorHref": "https://blogger.googleusercontent.com/img/b/R29vZ2xl/AVvXsEg0bRGT0lY7MtIQenbXdx56YFqivx4Eyz1H4zccBTtG8ua8gAxfh9WKkSt5HzayvXCAoXunpsKV3lp7yfgFtCcLy88SZrCBDPY8RPMN-xcSdA9oSdMTdQBBqCHY2AfQrddsQBvjEIFW88k/s1600/zvrhnutie+Svantovi%CC%81ta.JPG",
            "displayedWidth": 320,
            "displayedHeight": 188,
            "originalWidth": null,
            "originalHeight": null
          }
        },
        "alt": "Zničenie Arkony",
        "caption": "Zničenie Arkony",
        "position": "center",
        "showCaption": true,
        "width": "60",
        "aspectRatio": "auto",
        "rounded": true,
        "shadow": true
      },
      {
        "__component": "content.rich-text",
        "body": [
          {
            "type": "paragraph",
            "children": [
              {
                "type": "text",
                "text": "Na Rujanskom hradisku obklopenom močarinou a vyhľadávanom len v dobách vojnového nebezpečenstva stáli ďalšie tri mohutné svätyne, skvostne zdobené, zastrešené, s purpurovými závesmi miesto stien; najväčšia z nich bola obklopená nádvorím. Uctievali v nich Rugievita, Porevita a Porenuta."
              }
            ]
          }
        ]
      },
      {
        "__component": "content.rich-text",
        "body": [
          {
            "type": "paragraph",
            "children": [
              {
                "type": "text",
                "text": "Množstvo fotografií a krátky text z našej výpravy na Arkonu nájdete v"
              },
              {
                "type": "link",
                "url": "http://www.hradiska.sk/search/label/V%C3%BDprava%20Arkona%202012%20-%20De%C5%88%20druh%C3%BD%20-%20Mys%20Arkona",
                "children": [
                  {
                    "type": "text",
                    "text": "tomto článku"
                  }
                ]
              }
            ]
          }
        ]
      },
      {
        "__component": "content.rich-text",
        "body": [
          {
            "type": "heading",
            "children": [
              {
                "type": "text",
                "text": "ĎALŠIE SVÄTYNE",
                "bold": true
              }
            ],
            "level": 2
          }
        ]
      },
      {
        "__component": "content.rich-text",
        "body": [
          {
            "type": "paragraph",
            "children": [
              {
                "type": "text",
                "text": "Obdivuhodne zdobené svätyne si podľa Ebbona vystavali v hodnote 300 talentov obyvatelia "
              },
              {
                "type": "text",
                "text": "Gochova",
                "bold": true
              },
              {
                "type": "text",
                "text": " (Chozegowa, dnešné Gutzkow); Herbord hovorí len o jednom chráme. Chránili idoly neobyčajnej veľkosti a \"neuveriteľnej krásy\", s ktorými ťažko bolo možné pohnúť, takže ich bolo treba za Ottovho misijného pôsobenia najprv osekať a až potom odtiahnuť na spálenie. Neviditeľný démon, ktorý tu prebýval, ušiel pri speve veriacich, nesúcich kríž, v podobe húfu múch.   "
              }
            ]
          }
        ]
      },
      {
        "__component": "content.image-block",
        "imageRef": {
          "sourceUrl": "https://blogger.googleusercontent.com/img/b/R29vZ2xl/AVvXsEidV23yPFFuRCXZLXQLUNHTRFJRhLao-3vT2ndYLbB21BdGOoAlkQq3UGYZjmDz6O2uZ26C2MkeF7wo_qA2zFQBIMwPQMliUpD9-jzbvOBtxOral__V_X_BoCbe3_WvkV8YH1trHqd89To/s0/arkona+temnozor.jpg",
          "fallbackUrl": "https://blogger.googleusercontent.com/img/b/R29vZ2xl/AVvXsEidV23yPFFuRCXZLXQLUNHTRFJRhLao-3vT2ndYLbB21BdGOoAlkQq3UGYZjmDz6O2uZ26C2MkeF7wo_qA2zFQBIMwPQMliUpD9-jzbvOBtxOral__V_X_BoCbe3_WvkV8YH1trHqd89To/s1600/arkona+temnozor.jpg",
          "filename": "arkona+temnozor.jpg",
          "blogger": {
            "anchorHref": "https://blogger.googleusercontent.com/img/b/R29vZ2xl/AVvXsEidV23yPFFuRCXZLXQLUNHTRFJRhLao-3vT2ndYLbB21BdGOoAlkQq3UGYZjmDz6O2uZ26C2MkeF7wo_qA2zFQBIMwPQMliUpD9-jzbvOBtxOral__V_X_BoCbe3_WvkV8YH1trHqd89To/s1600/arkona+temnozor.jpg",
            "displayedWidth": 320,
            "displayedHeight": 308,
            "originalWidth": null,
            "originalHeight": null
          }
        },
        "alt": "Hradisko Arkona - umelecká predstava (Temnozor)",
        "caption": "Hradisko Arkona - umelecká predstava (Temnozor)",
        "position": "right",
        "showCaption": true,
        "width": "50",
        "aspectRatio": "auto",
        "rounded": true,
        "shadow": true
      },
      {
        "__component": "content.rich-text",
        "body": [
          {
            "type": "paragraph",
            "children": [
              {
                "type": "text",
                "text": "Z ďalších polabských a pomoranských bohov treba spomenúť napr. Rugievita v meste "
              },
              {
                "type": "text",
                "text": "Korenica",
                "bold": true
              },
              {
                "type": "text",
                "text": ", ktorý mal idol z duba so siedmimi tvárami. V Štetíne uctievali Triglava, ktorý mal tiež chrám zdobený rezbami a maľbami a ďalšie menšie svätyne. Bol to mocný boh, \"summus deus\", ktorý mal podobne ako Svantovít a Radegast svätého koňa, s ktorého pomocou sa veštilo. Biskup Otto dal jeho sochu po roku 1128 rozsekať a tri strieborné hlavy poslať do Ríma. K vyvráteniu Triglavových svätýň v Štetíne pomáhal ľud, ktorý vraj si prestal boha vážiť, keď videl, že sa sám nedokáže brániť. Pomoc ľudu však pramenila skôr z iného základu, z útlaku kňazov, bohatých obchodníkov a šľachty, ktorí hájili svoju moc práve v mene Triglavovom. "
              }
            ]
          }
        ]
      },
      {
        "__component": "content.rich-text",
        "body": [
          {
            "type": "paragraph",
            "children": [
              {
                "type": "text",
                "text": "Jedna z najpozoruhodnejších slovanských chrámových stavieb bola objavená v hradisku "
              },
              {
                "type": "text",
                "text": "Gross Raden",
                "bold": true
              },
              {
                "type": "text",
                "text": " na brehu Sternbergského jazera. Na voľnej ploche juhovýchodnej časti polostrova stála jednopriestorová hala (7 x 11 m) spojená úzkym, stélami lemovaným chodníkom s drevenou cestou, ktorá prechádzala hradiskom. Jej obdĺžny pôdorys bol na užších stranách mierne vyklenutý a vybavený vchodmi. Steny tvoril dvojitý rad zašpicatených do zeme zapustených dosák, z ktorých vnútorná rada mala nosnú funkciu a vonkajšia ozdobnú. V okrúhlych alebo skôr kosoštvorcovo zašpicatených vyrezávaných hlaviciach na hornom konci sa nám rysujú náznaky mužských a ženských figúr. Vnútornú plochu chrámu poškodila neskoršia priekopa, takže sa nezachovali stopy po umiestnení prípadného idolu. K inventáru však patrilo 6 konských lebiek, 2 železné kópie, drevený štít a misy na nožičkách. Nad dverami chrámu bola zavesená dobytčia lebka. Hradisko Gross Raden je originálnou domácou architektúrou, ktorá dosvedčuje starú tradíciu slovanských stavieb a vyvracia akékoľvek iné vplyvy (či už keltské alebo škandinávske).  "
              }
            ]
          }
        ]
      },
      {
        "__component": "content.image-block",
        "imageRef": {
          "sourceUrl": "https://blogger.googleusercontent.com/img/b/R29vZ2xl/AVvXsEg15DOKbnDTcrNzIv0jzF79KTROfh3W-QmuxDu373gSbgzlgCflQuu28_-1_Ikz9pjGm5OMSJCCn4z-R9AJpOLFPdxkm1b9cVTUjt1gNhdBVqJ1qoLymhTUKHcn5KMq_Oms4N3qa0CSrSU/s0/arkona.jpg",
          "fallbackUrl": "https://blogger.googleusercontent.com/img/b/R29vZ2xl/AVvXsEg15DOKbnDTcrNzIv0jzF79KTROfh3W-QmuxDu373gSbgzlgCflQuu28_-1_Ikz9pjGm5OMSJCCn4z-R9AJpOLFPdxkm1b9cVTUjt1gNhdBVqJ1qoLymhTUKHcn5KMq_Oms4N3qa0CSrSU/s1600/arkona.jpg",
          "filename": "arkona.jpg",
          "blogger": {
            "anchorHref": "https://blogger.googleusercontent.com/img/b/R29vZ2xl/AVvXsEg15DOKbnDTcrNzIv0jzF79KTROfh3W-QmuxDu373gSbgzlgCflQuu28_-1_Ikz9pjGm5OMSJCCn4z-R9AJpOLFPdxkm1b9cVTUjt1gNhdBVqJ1qoLymhTUKHcn5KMq_Oms4N3qa0CSrSU/s1600/arkona.jpg",
            "displayedWidth": 320,
            "displayedHeight": 205,
            "originalWidth": null,
            "originalHeight": null
          }
        },
        "alt": "Arkona - jeden z pokusov o \"rekonštrukciu\"",
        "caption": "Arkona - jeden z pokusov o \"rekonštrukciu\"",
        "position": "left",
        "showCaption": true,
        "width": "50",
        "aspectRatio": "auto",
        "rounded": true,
        "shadow": true
      },
      {
        "__component": "content.rich-text",
        "body": [
          {
            "type": "paragraph",
            "children": [
              {
                "type": "text",
                "text": "Chrám vo "
              },
              {
                "type": "text",
                "text": "Wolgast",
                "bold": true
              },
              {
                "type": "text",
                "text": ", zasvätený Gerovitovi-Jarovitovi, nebol bližšie opísaný. Vieme len, že počas Ottovom kázania došlo k rozhnevaniu davu, pred ktorého hnevom sa jeden z klerikov zachránil útekom do chrámu, kde sa zmocnil posvätného štítu a pod jeho ochranou potom prešiel bez úhony prekvapeným davom.   "
              }
            ]
          }
        ]
      },
      {
        "__component": "content.rich-text",
        "body": [
          {
            "type": "paragraph",
            "children": [
              {
                "type": "text",
                "text": "Slávne prístavné mesto "
              },
              {
                "type": "text",
                "text": "Wolin",
                "bold": true
              },
              {
                "type": "text",
                "text": " malo chrám zvaný \"continu\", obklopený bažinou a uchovávajúci posvätnú kopiju, zapustenú do veľkého stĺpu. Jeho latinské označenie je asi odvodené od staroslovanského ka.t, ktorému zodpovedá české kút, ruské kušča, srbské Kuča a bulharské kasta (= príbytok). Mnísi sprevádzajúci Otta ich považovali, zrejme vplyvom nedorozumenia, za kopije Júliusa Caesara - Prieflingenský mních totiž uvádza ako variantu názov mesta tiež Julin. Nie je vylúčené, že tu stáli dva chrámy, ako naznačujú dva kostoly postavené po prijatí kresťanstva na rovnakom mieste a zasvätené sv. Václavovi a sv. Vojtechovi. Triglav bol uctievaný tiež vo Woline. Tu sa biskupovi Ottovi Bamberskému podarilo zničiť len svätyňu, zlatého boha ukryl kňaz na vidieku v dutom strome a pohania mu naďalej prinášali obete."
              }
            ]
          }
        ]
      },
      {
        "__component": "content.image-block",
        "imageRef": {
          "sourceUrl": "https://blogger.googleusercontent.com/img/b/R29vZ2xl/AVvXsEiI8wy5CXA59x48O7xZlM2UHhAqfbcUhRV9qYT_O1YAncFZ8_1_Axch_MZZv0gCks9HKx5JLrih1c6v-EoppQfpEMkgaYu8C4Uao2wCNu4M4bVrpQhlKqEqGDKp9lryRaVqY0h7aJXujIE/s0/ark1.jpg",
          "fallbackUrl": "https://blogger.googleusercontent.com/img/b/R29vZ2xl/AVvXsEiI8wy5CXA59x48O7xZlM2UHhAqfbcUhRV9qYT_O1YAncFZ8_1_Axch_MZZv0gCks9HKx5JLrih1c6v-EoppQfpEMkgaYu8C4Uao2wCNu4M4bVrpQhlKqEqGDKp9lryRaVqY0h7aJXujIE/s1600/ark1.jpg",
          "filename": "ark1.jpg",
          "blogger": {
            "anchorHref": "https://blogger.googleusercontent.com/img/b/R29vZ2xl/AVvXsEiI8wy5CXA59x48O7xZlM2UHhAqfbcUhRV9qYT_O1YAncFZ8_1_Axch_MZZv0gCks9HKx5JLrih1c6v-EoppQfpEMkgaYu8C4Uao2wCNu4M4bVrpQhlKqEqGDKp9lryRaVqY0h7aJXujIE/s1600/ark1.jpg",
            "displayedWidth": 264,
            "displayedHeight": 320,
            "originalWidth": null,
            "originalHeight": null
          }
        },
        "alt": "Fiktívna podoba svätyne v Arkone",
        "caption": "Fiktívna podoba svätyne v Arkone",
        "position": "right",
        "showCaption": true,
        "width": "40",
        "aspectRatio": "auto",
        "rounded": true,
        "shadow": true
      },
      {
        "__component": "content.rich-text",
        "body": [
          {
            "type": "paragraph",
            "children": [
              {
                "type": "text",
                "text": "Spracoval: Orgoň"
              }
            ]
          }
        ]
      },
      {
        "__component": "content.rich-text",
        "body": [
          {
            "type": "paragraph",
            "children": [
              {
                "type": "text",
                "text": "Magdalena Beranová: Slované, Panorama Praha, 1988  Pitro M., Vokáč P.: Bohové dávných Slovanú, ISV Nakladatelství, Praha 2002"
              },
              {
                "type": "link",
                "url": "http://www.sho.sk/",
                "children": [
                  {
                    "type": "text",
                    "text": "http://www.sho.sk/"
                  }
                ]
              }
            ]
          }
        ]
      },
      {
        "__component": "content.rich-text",
        "body": [
          {
            "type": "paragraph",
            "children": [
              {
                "type": "text",
                "text": "http//pospolitost.wordpress.com/2009/05/16/svatyne-slovanov/"
              }
            ]
          }
        ]
      },
      {
        "__component": "content.sources",
        "title": "Zdroje a literatúra",
        "intro": null,
        "items": [
          {
            "text": "Spracoval: Orgoň",
            "url": null
          },
          {
            "text": "http://www.sho.sk/",
            "url": "http://www.sho.sk/"
          },
          {
            "text": "Magdalena Beranová: Slované, Panorama Praha, 1988 Pitro M., Vokáč P.: Bohové dávných Slovanú, ISV Nakladatelství, Praha 2002",
            "url": null
          },
          {
            "text": "http://slawenburgen.npage.de/",
            "url": "http://slawenburgen.npage.de/"
          },
          {
            "text": "Ancestral Volkhves - A Ruiny Prehovoria, Ked Stichne Cas",
            "url": "https://www.youtube.com/watch?v=N3zygd7ZYPA"
          }
        ]
      }
    ],
    "citations": [
      {
        "type": "attribution",
        "text": "Spracoval: Orgoň"
      },
      {
        "type": "external-url",
        "url": "http://www.sho.sk/",
        "title": "http://www.sho.sk/"
      },
      {
        "type": "book",
        "text": "Magdalena Beranová: Slované, Panorama Praha, 1988 Pitro M., Vokáč P.: Bohové dávných Slovanú, ISV Nakladatelství, Praha 2002"
      },
      {
        "type": "external-url",
        "url": "http://slawenburgen.npage.de/",
        "title": "http://slawenburgen.npage.de/"
      },
      {
        "type": "external-url",
        "url": "https://www.youtube.com/watch?v=N3zygd7ZYPA",
        "title": "Ancestral Volkhves - A Ruiny Prehovoria, Ked Stichne Cas"
      }
    ]
  }
}