{
  "$meta": {
    "sourceFeed": "C:\\Users\\milan\\Desktop\\Git-Projects\\hradiska-strapi\\scripts\\blog-migrate\\data\\label28-muzla-cenkov.json",
    "sourceLabel": null,
    "postId": "tag:blogger.com,1999:blog-6818054921907446479.post-5370336738199795489",
    "bloggerPostUrl": "http://www.hradiska.sk/2011/09/muzla-cenkov.html",
    "repliesLink": "http://www.hradiska.sk/feeds/5370336738199795489/comments/default",
    "extractedAt": "2026-07-13T23:07:30.993Z",
    "coverImageNeedsReview": true,
    "commentCount": 7,
    "comments": [
      {
        "id": "tag:blogger.com,1999:blog-6818054921907446479.post-164474554789955140",
        "bloggerPostId": "164474554789955140",
        "author": "Anonymous",
        "authorProfile": null,
        "published": "2022-12-10T17:38:11.167+01:00",
        "updated": "2022-12-10T17:38:11.167+01:00",
        "content": "A ďakujem p. Orgoňovi za jeho zaujímavé bádanie.",
        "inReplyToArticle": "http://www.hradiska.sk/2011/09/muzla-cenkov.html",
        "replyToBloggerId": "6949410029742996501",
        "replyToFeedHref": "http://www.blogger.com/feeds/6818054921907446479/5370336738199795489/comments/default/6949410029742996501"
      },
      {
        "id": "tag:blogger.com,1999:blog-6818054921907446479.post-6949410029742996501",
        "bloggerPostId": "6949410029742996501",
        "author": "Anonymous",
        "authorProfile": null,
        "published": "2022-12-10T17:36:35.719+01:00",
        "updated": "2022-12-10T17:36:35.719+01:00",
        "content": "Ak môžem: asi pôjdem na miesto, pretože ma zaujala aj iná vec. Pravdepodobný zmysel tohoto hradiska. Na google earth vidím asi vysypanú, dnes samozrejme poškodenú cestu cez širšiu, asi 1km cestu cez Dunaj na ostrov, z ktorého sa pokračovalo možno na pltiach, či člnoch preťahovaním pomocou lana (?). Takže toto hradisko mohlo mať ochranný účel pre tento prechod, možno aj ubytovanie pocestného pred, či po prechode. Alan Dolog",
        "inReplyToArticle": "http://www.hradiska.sk/2011/09/muzla-cenkov.html",
        "replyToBloggerId": null,
        "replyToFeedHref": null
      },
      {
        "id": "tag:blogger.com,1999:blog-6818054921907446479.post-1493434721078152675",
        "bloggerPostId": "1493434721078152675",
        "author": "Anonymous",
        "authorProfile": "https://www.blogger.com/profile/05541373807947835313",
        "published": "2013-07-18T11:32:32.594+02:00",
        "updated": "2013-07-18T11:32:32.594+02:00",
        "content": "Článok nájdete tu: http://sturovo.com/drupal/18-07-2013/359/historia/cenkov-slovanske-hradisko Ďakujem.",
        "inReplyToArticle": "http://www.hradiska.sk/2011/09/muzla-cenkov.html",
        "replyToBloggerId": "5299274488121948437",
        "replyToFeedHref": "http://www.blogger.com/feeds/6818054921907446479/5370336738199795489/comments/default/5299274488121948437"
      },
      {
        "id": "tag:blogger.com,1999:blog-6818054921907446479.post-7296973361202878669",
        "bloggerPostId": "7296973361202878669",
        "author": "Anonymous",
        "authorProfile": null,
        "published": "2013-07-18T11:08:03.458+02:00",
        "updated": "2013-07-18T11:08:03.458+02:00",
        "content": "Až by ste tomuto rozumeli http://www.scribd.com/doc/154375368/Muzsla-hataraban-talalhato-regeszeti-lel%C5%91helyek tu je celý archeologický prieskum v okolí obce Mužla opísaný. ",
        "inReplyToArticle": "http://www.hradiska.sk/2011/09/muzla-cenkov.html",
        "replyToBloggerId": null,
        "replyToFeedHref": null
      },
      {
        "id": "tag:blogger.com,1999:blog-6818054921907446479.post-5299274488121948437",
        "bloggerPostId": "5299274488121948437",
        "author": "Orgon 3 mail - sept 2012",
        "authorProfile": "https://www.blogger.com/profile/15597061075982487419",
        "published": "2013-07-17T22:20:25.963+02:00",
        "updated": "2013-07-17T22:20:25.963+02:00",
        "content": "Ano môžte a pošlite mi potom prosím link na ten článok",
        "inReplyToArticle": "http://www.hradiska.sk/2011/09/muzla-cenkov.html",
        "replyToBloggerId": null,
        "replyToFeedHref": null
      },
      {
        "id": "tag:blogger.com,1999:blog-6818054921907446479.post-4765269605024282092",
        "bloggerPostId": "4765269605024282092",
        "author": "Anonymous",
        "authorProfile": "https://www.blogger.com/profile/05541373807947835313",
        "published": "2013-07-17T22:13:33.497+02:00",
        "updated": "2013-07-17T22:13:33.497+02:00",
        "content": "Dobrý deň. Mohol by som uverejniť tento článok na <a href=\"http://www.sturovo.com\" rel=\"nofollow\">www.sturovo.com</a> s uvedením aktívneho odkazu na váš web?",
        "inReplyToArticle": "http://www.hradiska.sk/2011/09/muzla-cenkov.html",
        "replyToBloggerId": null,
        "replyToFeedHref": null
      },
      {
        "id": "tag:blogger.com,1999:blog-6818054921907446479.post-4545595325413504551",
        "bloggerPostId": "4545595325413504551",
        "author": "Anonymous",
        "authorProfile": null,
        "published": "2012-11-16T11:01:27.033+01:00",
        "updated": "2012-11-16T11:01:27.033+01:00",
        "content": "Velkè vdaka tÿmu ktory to zverejnili aby aspoñ zlomok z minulosti ostalo pre buducu generáciu:-) s pozdravom Pinkeovà",
        "inReplyToArticle": "http://www.hradiska.sk/2011/09/muzla-cenkov.html",
        "replyToBloggerId": null,
        "replyToFeedHref": null
      }
    ],
    "checks": {
      "nativeHeadings": [],
      "nativeHeadingCount": 0,
      "mapIframeCount": 1,
      "mapIframeSrcs": [
        "http://maps.google.com/maps?hl=sk&ie=UTF8&t=h&vpsrc=0&ll=47.762984,18.528914&spn=0.013126,0.018239&z=15&output=embed"
      ],
      "nonMapIframeCount": 2,
      "nonMapIframeSrcs": [
        "https://www.youtube.com/embed/oDujLc1u4-w",
        "https://www.youtube.com/embed/l6LqWu4IdaU"
      ],
      "italicCaptionCount": 0,
      "totalImages": 27,
      "captionedImages": 4,
      "separatorImages": 23
    },
    "poemCount": 0,
    "poemSingleFlags": [],
    "sanityFlags": [
      "hasNonMapIframes"
    ]
  },
  "blogPost": {
    "title": "Mužla - Čenkov",
    "slug": "muzla-cenkov",
    "excerpt": "Na lokalite Mužla-Čenkov sa v 9. až 10. storočí rozprestieralo slovanské hradisko, ktorého časti sa dnes nachádzajú na polohe Vilmakert a Orechový sad. Možno ho zaradiť medzi hradiská s dominujúcou strážnou a vojenskou funkciou (Hulínek). Lokalita…",
    "authorName": "Orgon",
    "publishedAt": "2011-09-14T16:56:00.004+02:00",
    "originalPublishedDate": "2011-09-14T16:56:00.004+02:00",
    "updatedAt": "2020-08-25T10:51:31.152+02:00",
    "readingTime": 10,
    "featured": false,
    "coverImage": {
      "sourceUrl": "https://blogger.googleusercontent.com/img/b/R29vZ2xl/AVvXsEgZ3KQPAoJPz0YONuBW_e9HYuagXofAuauIXM8V4cjckRWdvsTZY8CdHjpA1lU4EKyKueeY8Q1uG26VosZy5CicbdA34TzcebpWoMwItGeOwDyF3wPLJvkVXyIByjqLXMm7d34kHdEckaY/s0/P7275733.JPG",
      "fallbackUrl": "https://blogger.googleusercontent.com/img/b/R29vZ2xl/AVvXsEgZ3KQPAoJPz0YONuBW_e9HYuagXofAuauIXM8V4cjckRWdvsTZY8CdHjpA1lU4EKyKueeY8Q1uG26VosZy5CicbdA34TzcebpWoMwItGeOwDyF3wPLJvkVXyIByjqLXMm7d34kHdEckaY/s1600/P7275733.JPG",
      "filename": "P7275733.JPG",
      "blogger": {
        "anchorHref": "https://blogger.googleusercontent.com/img/b/R29vZ2xl/AVvXsEgZ3KQPAoJPz0YONuBW_e9HYuagXofAuauIXM8V4cjckRWdvsTZY8CdHjpA1lU4EKyKueeY8Q1uG26VosZy5CicbdA34TzcebpWoMwItGeOwDyF3wPLJvkVXyIByjqLXMm7d34kHdEckaY/s1600/P7275733.JPG",
        "displayedWidth": 320,
        "displayedHeight": 185,
        "originalWidth": null,
        "originalHeight": null
      }
    },
    "gallery": [
      {
        "sourceUrl": "https://blogger.googleusercontent.com/img/b/R29vZ2xl/AVvXsEgZ3KQPAoJPz0YONuBW_e9HYuagXofAuauIXM8V4cjckRWdvsTZY8CdHjpA1lU4EKyKueeY8Q1uG26VosZy5CicbdA34TzcebpWoMwItGeOwDyF3wPLJvkVXyIByjqLXMm7d34kHdEckaY/s0/P7275733.JPG",
        "fallbackUrl": "https://blogger.googleusercontent.com/img/b/R29vZ2xl/AVvXsEgZ3KQPAoJPz0YONuBW_e9HYuagXofAuauIXM8V4cjckRWdvsTZY8CdHjpA1lU4EKyKueeY8Q1uG26VosZy5CicbdA34TzcebpWoMwItGeOwDyF3wPLJvkVXyIByjqLXMm7d34kHdEckaY/s1600/P7275733.JPG",
        "filename": "P7275733.JPG",
        "blogger": {
          "anchorHref": "https://blogger.googleusercontent.com/img/b/R29vZ2xl/AVvXsEgZ3KQPAoJPz0YONuBW_e9HYuagXofAuauIXM8V4cjckRWdvsTZY8CdHjpA1lU4EKyKueeY8Q1uG26VosZy5CicbdA34TzcebpWoMwItGeOwDyF3wPLJvkVXyIByjqLXMm7d34kHdEckaY/s1600/P7275733.JPG",
          "displayedWidth": 320,
          "displayedHeight": 185,
          "originalWidth": null,
          "originalHeight": null
        },
        "caption": "Naša predstava o vzhľade hradiska. Autor: T. Humaj"
      },
      {
        "sourceUrl": "https://blogger.googleusercontent.com/img/b/R29vZ2xl/AVvXsEjqzSp9XJW05SjtAe8vYQRs57fkJMxjW0KdWNHmfO0LcHCMmwP6JuVZo7EuYijPlQ3JvG318DqqeOWFzVP05LiSXnMUt_cjnpYmr68yOAvGebiZuzxkzIKADK1JCHhEO2ydQe8W2QYCNrI/s0/mapa+1+VM.png",
        "fallbackUrl": "https://blogger.googleusercontent.com/img/b/R29vZ2xl/AVvXsEjqzSp9XJW05SjtAe8vYQRs57fkJMxjW0KdWNHmfO0LcHCMmwP6JuVZo7EuYijPlQ3JvG318DqqeOWFzVP05LiSXnMUt_cjnpYmr68yOAvGebiZuzxkzIKADK1JCHhEO2ydQe8W2QYCNrI/s1600/mapa+1+VM.png",
        "filename": "mapa+1+VM.png",
        "blogger": {
          "anchorHref": "https://blogger.googleusercontent.com/img/b/R29vZ2xl/AVvXsEjqzSp9XJW05SjtAe8vYQRs57fkJMxjW0KdWNHmfO0LcHCMmwP6JuVZo7EuYijPlQ3JvG318DqqeOWFzVP05LiSXnMUt_cjnpYmr68yOAvGebiZuzxkzIKADK1JCHhEO2ydQe8W2QYCNrI/s1600/mapa+1+VM.png",
          "displayedWidth": 320,
          "displayedHeight": 176,
          "originalWidth": null,
          "originalHeight": null
        },
        "caption": "A tu máme 1. vojenské mapovanie (1764 – 1787). Je na ňom vyznačené hradisko?"
      },
      {
        "sourceUrl": "https://blogger.googleusercontent.com/img/b/R29vZ2xl/AVvXsEiBQ9JEM-CZXumiPwsoBD_pEA-KgxnXV3tZBGNc6VYJWkm_Uv4Rf6nlEo-q8lGJk2Z_skKMvFzxl_oUTlC9fimBvQ0uE2GpoLXN1tWFr-786H9TYXh1KJ6Oo5ADxvLhljACfc6Qhge1Cx8/s0/14958088_218955318527133_1816232901_o.jpg",
        "fallbackUrl": "https://blogger.googleusercontent.com/img/b/R29vZ2xl/AVvXsEiBQ9JEM-CZXumiPwsoBD_pEA-KgxnXV3tZBGNc6VYJWkm_Uv4Rf6nlEo-q8lGJk2Z_skKMvFzxl_oUTlC9fimBvQ0uE2GpoLXN1tWFr-786H9TYXh1KJ6Oo5ADxvLhljACfc6Qhge1Cx8/s1600/14958088_218955318527133_1816232901_o.jpg",
        "filename": "14958088_218955318527133_1816232901_o.jpg",
        "blogger": {
          "anchorHref": "https://blogger.googleusercontent.com/img/b/R29vZ2xl/AVvXsEiBQ9JEM-CZXumiPwsoBD_pEA-KgxnXV3tZBGNc6VYJWkm_Uv4Rf6nlEo-q8lGJk2Z_skKMvFzxl_oUTlC9fimBvQ0uE2GpoLXN1tWFr-786H9TYXh1KJ6Oo5ADxvLhljACfc6Qhge1Cx8/s1600/14958088_218955318527133_1816232901_o.jpg",
          "displayedWidth": 320,
          "displayedHeight": 180,
          "originalWidth": null,
          "originalHeight": null
        },
        "caption": "Objekt X. Počas výskumu slovanského hradiska objavil Dr. Hanuliak v jeho priestore stavbu, ktorá je svojimi rozmermi unikátna v slovanskom období na území Slovenska. Stála na návrší vo vnútri hradiska a okolo nej sa nachádzalo niekoľko hrobov s bohatou výbavou. Stavba mohla mať jednak náboženský charakter, ale zároveň mohla slúžiť aj ako reprezentačná budova šľachty. Modla nie je na tom mieste doložená. Koly pri hroboch tiež nie, ale Dr. Hanuliak predpokladá, že tam mohli byť. Taktiež sa predpokladá ohradenie areálu ľahkým plotom."
      },
      {
        "sourceUrl": "https://blogger.googleusercontent.com/img/b/R29vZ2xl/AVvXsEj8gtHZg0UCO3BSZ5RMx58d4wQBF4vMzw7i-MefWmicJRlP571RSElqZYkzN9Ca_Nqo228vMEF7UhbU813thjSM-ny3TnjLujydhZgHpgmvOeysn0uPocEVh5cZ6DDh45YlS7YED0N2p4k/s0/Sni%25CC%2581mka+obrazovky+2016-09-16+o%25C2%25A019.30.32.png",
        "fallbackUrl": "https://blogger.googleusercontent.com/img/b/R29vZ2xl/AVvXsEj8gtHZg0UCO3BSZ5RMx58d4wQBF4vMzw7i-MefWmicJRlP571RSElqZYkzN9Ca_Nqo228vMEF7UhbU813thjSM-ny3TnjLujydhZgHpgmvOeysn0uPocEVh5cZ6DDh45YlS7YED0N2p4k/s1600/Sni%25CC%2581mka+obrazovky+2016-09-16+o%25C2%25A019.30.32.png",
        "filename": "Sni%CC%81mka+obrazovky+2016-09-16+o%C2%A019.30.32.png",
        "blogger": {
          "anchorHref": "https://blogger.googleusercontent.com/img/b/R29vZ2xl/AVvXsEj8gtHZg0UCO3BSZ5RMx58d4wQBF4vMzw7i-MefWmicJRlP571RSElqZYkzN9Ca_Nqo228vMEF7UhbU813thjSM-ny3TnjLujydhZgHpgmvOeysn0uPocEVh5cZ6DDh45YlS7YED0N2p4k/s1600/Sni%25CC%2581mka+obrazovky+2016-09-16+o%25C2%25A019.30.32.png",
          "displayedWidth": 320,
          "displayedHeight": 180,
          "originalWidth": null,
          "originalHeight": null
        },
        "caption": null
      },
      {
        "sourceUrl": "https://blogger.googleusercontent.com/img/b/R29vZ2xl/AVvXsEgxAXXnMMXMUVZOywJ2e3noqHtt5ZVu-or4Ughmew_w4oDiclAb6Rs0WeK42mnmNwKAOlVLY43kfWYRiJ-C3V12jU2tSOhEpHPjuvlOpS0wE9DKLYviK9XeVZbAD30355Q4gTGSvmEAczo/s0/Sni%25CC%2581mka+obrazovky+2016-09-16+o%25C2%25A019.31.28.png",
        "fallbackUrl": "https://blogger.googleusercontent.com/img/b/R29vZ2xl/AVvXsEgxAXXnMMXMUVZOywJ2e3noqHtt5ZVu-or4Ughmew_w4oDiclAb6Rs0WeK42mnmNwKAOlVLY43kfWYRiJ-C3V12jU2tSOhEpHPjuvlOpS0wE9DKLYviK9XeVZbAD30355Q4gTGSvmEAczo/s1600/Sni%25CC%2581mka+obrazovky+2016-09-16+o%25C2%25A019.31.28.png",
        "filename": "Sni%CC%81mka+obrazovky+2016-09-16+o%C2%A019.31.28.png",
        "blogger": {
          "anchorHref": "https://blogger.googleusercontent.com/img/b/R29vZ2xl/AVvXsEgxAXXnMMXMUVZOywJ2e3noqHtt5ZVu-or4Ughmew_w4oDiclAb6Rs0WeK42mnmNwKAOlVLY43kfWYRiJ-C3V12jU2tSOhEpHPjuvlOpS0wE9DKLYviK9XeVZbAD30355Q4gTGSvmEAczo/s1600/Sni%25CC%2581mka+obrazovky+2016-09-16+o%25C2%25A019.31.28.png",
          "displayedWidth": 320,
          "displayedHeight": 180,
          "originalWidth": null,
          "originalHeight": null
        },
        "caption": null
      },
      {
        "sourceUrl": "https://blogger.googleusercontent.com/img/b/R29vZ2xl/AVvXsEicu-LEFDDNHaobI6KBtGFuU22T06rKMixE5Psau9_vwrtBnH_7ekgXE6i9FL2Nnm4ZugyASFVaZyklz7CURrNIlHRcmQm7nwluYOsQ1VSCTIUuXfOirxHjMJtMWFNjN7ZkbzyaA0CUzGo/s0/Sni%25CC%2581mka+obrazovky+2016-09-16+o%25C2%25A019.32.00.png",
        "fallbackUrl": "https://blogger.googleusercontent.com/img/b/R29vZ2xl/AVvXsEicu-LEFDDNHaobI6KBtGFuU22T06rKMixE5Psau9_vwrtBnH_7ekgXE6i9FL2Nnm4ZugyASFVaZyklz7CURrNIlHRcmQm7nwluYOsQ1VSCTIUuXfOirxHjMJtMWFNjN7ZkbzyaA0CUzGo/s1600/Sni%25CC%2581mka+obrazovky+2016-09-16+o%25C2%25A019.32.00.png",
        "filename": "Sni%CC%81mka+obrazovky+2016-09-16+o%C2%A019.32.00.png",
        "blogger": {
          "anchorHref": "https://blogger.googleusercontent.com/img/b/R29vZ2xl/AVvXsEicu-LEFDDNHaobI6KBtGFuU22T06rKMixE5Psau9_vwrtBnH_7ekgXE6i9FL2Nnm4ZugyASFVaZyklz7CURrNIlHRcmQm7nwluYOsQ1VSCTIUuXfOirxHjMJtMWFNjN7ZkbzyaA0CUzGo/s1600/Sni%25CC%2581mka+obrazovky+2016-09-16+o%25C2%25A019.32.00.png",
          "displayedWidth": 320,
          "displayedHeight": 180,
          "originalWidth": null,
          "originalHeight": null
        },
        "caption": null
      },
      {
        "sourceUrl": "https://blogger.googleusercontent.com/img/b/R29vZ2xl/AVvXsEj-IQgTSkXo8yuf8ZYURFfKzJzrksAInvCgdahH8il8Te2eFZEvip4XQTyfH8O1PD1ZVGNtnikg8CoqLhl1B_m8rimdyFJvYNpr9iDB3Z3qVaw8VOj6ksXgElqEgUYmfBrvbVpevbkIa5o/s0/na%25CC%2581lezy1.jpg",
        "fallbackUrl": "https://blogger.googleusercontent.com/img/b/R29vZ2xl/AVvXsEj-IQgTSkXo8yuf8ZYURFfKzJzrksAInvCgdahH8il8Te2eFZEvip4XQTyfH8O1PD1ZVGNtnikg8CoqLhl1B_m8rimdyFJvYNpr9iDB3Z3qVaw8VOj6ksXgElqEgUYmfBrvbVpevbkIa5o/s1600/na%25CC%2581lezy1.jpg",
        "filename": "na%CC%81lezy1.jpg",
        "blogger": {
          "anchorHref": "https://blogger.googleusercontent.com/img/b/R29vZ2xl/AVvXsEj-IQgTSkXo8yuf8ZYURFfKzJzrksAInvCgdahH8il8Te2eFZEvip4XQTyfH8O1PD1ZVGNtnikg8CoqLhl1B_m8rimdyFJvYNpr9iDB3Z3qVaw8VOj6ksXgElqEgUYmfBrvbVpevbkIa5o/s1600/na%25CC%2581lezy1.jpg",
          "displayedWidth": 209,
          "displayedHeight": 320,
          "originalWidth": null,
          "originalHeight": null
        },
        "caption": null
      },
      {
        "sourceUrl": "https://blogger.googleusercontent.com/img/b/R29vZ2xl/AVvXsEjIXLTftye4V7wgZmhSFm-NmBm0BbIxMT8SbiYl6nOoBrk5ipQJFiaNCqh8eh-UDbZK9WVo-ZPE_lIV-MzXNwG2hmv5620qDyK2pnn4S9hOk_asK0bXncboqiXE_HM3VBdUp-kwbFZTUjU/s0/VM+Gombi%CC%81k.jpg",
        "fallbackUrl": "https://blogger.googleusercontent.com/img/b/R29vZ2xl/AVvXsEjIXLTftye4V7wgZmhSFm-NmBm0BbIxMT8SbiYl6nOoBrk5ipQJFiaNCqh8eh-UDbZK9WVo-ZPE_lIV-MzXNwG2hmv5620qDyK2pnn4S9hOk_asK0bXncboqiXE_HM3VBdUp-kwbFZTUjU/s1600/VM+Gombi%CC%81k.jpg",
        "filename": "VM+Gombík.jpg",
        "blogger": {
          "anchorHref": "https://blogger.googleusercontent.com/img/b/R29vZ2xl/AVvXsEjIXLTftye4V7wgZmhSFm-NmBm0BbIxMT8SbiYl6nOoBrk5ipQJFiaNCqh8eh-UDbZK9WVo-ZPE_lIV-MzXNwG2hmv5620qDyK2pnn4S9hOk_asK0bXncboqiXE_HM3VBdUp-kwbFZTUjU/s1600/VM+Gombi%CC%81k.jpg",
          "displayedWidth": 165,
          "displayedHeight": 320,
          "originalWidth": null,
          "originalHeight": null
        },
        "caption": "honosný veľkomoravský gombík z hradiska"
      },
      {
        "sourceUrl": "https://blogger.googleusercontent.com/img/b/R29vZ2xl/AVvXsEhsm2Tw1NdzFyZdPYPxYRzPAiyw1lQdZYC0Duz5HmE4pf3qWOeYRV5eaFTtTiiWxdBJODxo8PZ_JF39THdeP3vY-PoEkvgtApF203TgvIHWp_rHJBmikyXASywT3u-v_TX8cpKnG1K8suo/s0/14964156_218955325193799_830176762_o.jpg",
        "fallbackUrl": "https://blogger.googleusercontent.com/img/b/R29vZ2xl/AVvXsEhsm2Tw1NdzFyZdPYPxYRzPAiyw1lQdZYC0Duz5HmE4pf3qWOeYRV5eaFTtTiiWxdBJODxo8PZ_JF39THdeP3vY-PoEkvgtApF203TgvIHWp_rHJBmikyXASywT3u-v_TX8cpKnG1K8suo/s1600/14964156_218955325193799_830176762_o.jpg",
        "filename": "14964156_218955325193799_830176762_o.jpg",
        "blogger": {
          "anchorHref": "https://blogger.googleusercontent.com/img/b/R29vZ2xl/AVvXsEhsm2Tw1NdzFyZdPYPxYRzPAiyw1lQdZYC0Duz5HmE4pf3qWOeYRV5eaFTtTiiWxdBJODxo8PZ_JF39THdeP3vY-PoEkvgtApF203TgvIHWp_rHJBmikyXASywT3u-v_TX8cpKnG1K8suo/s1600/14964156_218955325193799_830176762_o.jpg",
          "displayedWidth": 320,
          "displayedHeight": 153,
          "originalWidth": null,
          "originalHeight": null
        },
        "caption": null
      },
      {
        "sourceUrl": "https://blogger.googleusercontent.com/img/b/R29vZ2xl/AVvXsEig3FRVZS62ohGKVQQSFldFFr9JzfMRMNu8DvohFkDBLDMW9PRXlpggP_83TKdUHvsbLm-zN3dGrNcwWlgav83SqK5GOAPfzt_KgV48iKnJBGTf10izkgSsRxFYdhu-gWuOftvBr5073v0/s0/na%25CC%2581lezy2.jpg",
        "fallbackUrl": "https://blogger.googleusercontent.com/img/b/R29vZ2xl/AVvXsEig3FRVZS62ohGKVQQSFldFFr9JzfMRMNu8DvohFkDBLDMW9PRXlpggP_83TKdUHvsbLm-zN3dGrNcwWlgav83SqK5GOAPfzt_KgV48iKnJBGTf10izkgSsRxFYdhu-gWuOftvBr5073v0/s1600/na%25CC%2581lezy2.jpg",
        "filename": "na%CC%81lezy2.jpg",
        "blogger": {
          "anchorHref": "https://blogger.googleusercontent.com/img/b/R29vZ2xl/AVvXsEig3FRVZS62ohGKVQQSFldFFr9JzfMRMNu8DvohFkDBLDMW9PRXlpggP_83TKdUHvsbLm-zN3dGrNcwWlgav83SqK5GOAPfzt_KgV48iKnJBGTf10izkgSsRxFYdhu-gWuOftvBr5073v0/s1600/na%25CC%2581lezy2.jpg",
          "displayedWidth": 219,
          "displayedHeight": 320,
          "originalWidth": null,
          "originalHeight": null
        },
        "caption": null
      },
      {
        "sourceUrl": "https://blogger.googleusercontent.com/img/b/R29vZ2xl/AVvXsEhRfnI1ZvFmb77AdtCy4UclbsBz4IbeUJ0MNbTBNKBMTy1kjPF0MPM3eCcofucTBnsSyYnDn2XxHAdfbt-dqzfmu7u4r7XBEFfm2m_h8YcluVzuktXXEA9t61h53azJZp7Zw_EaCLyFp8g/s0/na%25CC%2581l3.jpg",
        "fallbackUrl": "https://blogger.googleusercontent.com/img/b/R29vZ2xl/AVvXsEhRfnI1ZvFmb77AdtCy4UclbsBz4IbeUJ0MNbTBNKBMTy1kjPF0MPM3eCcofucTBnsSyYnDn2XxHAdfbt-dqzfmu7u4r7XBEFfm2m_h8YcluVzuktXXEA9t61h53azJZp7Zw_EaCLyFp8g/s1600/na%25CC%2581l3.jpg",
        "filename": "na%CC%81l3.jpg",
        "blogger": {
          "anchorHref": "https://blogger.googleusercontent.com/img/b/R29vZ2xl/AVvXsEhRfnI1ZvFmb77AdtCy4UclbsBz4IbeUJ0MNbTBNKBMTy1kjPF0MPM3eCcofucTBnsSyYnDn2XxHAdfbt-dqzfmu7u4r7XBEFfm2m_h8YcluVzuktXXEA9t61h53azJZp7Zw_EaCLyFp8g/s1600/na%25CC%2581l3.jpg",
          "displayedWidth": 225,
          "displayedHeight": 320,
          "originalWidth": null,
          "originalHeight": null
        },
        "caption": null
      },
      {
        "sourceUrl": "https://blogger.googleusercontent.com/img/b/R29vZ2xl/AVvXsEg_96KV6kOkeJQtKvKPAMgPnD9W-0vLRsfvxU_Pk8fezf44OlcZUcApPCd_gS6b8YwjmAECo1RYXM-gHXIXJRqRBN1FCUHXVDd_iW1XqwquEirxnsR7azzDihwBTJ9YXDMuu7UAN7mtNd0/s0/na%25CC%2581l4.jpg",
        "fallbackUrl": "https://blogger.googleusercontent.com/img/b/R29vZ2xl/AVvXsEg_96KV6kOkeJQtKvKPAMgPnD9W-0vLRsfvxU_Pk8fezf44OlcZUcApPCd_gS6b8YwjmAECo1RYXM-gHXIXJRqRBN1FCUHXVDd_iW1XqwquEirxnsR7azzDihwBTJ9YXDMuu7UAN7mtNd0/s1600/na%25CC%2581l4.jpg",
        "filename": "na%CC%81l4.jpg",
        "blogger": {
          "anchorHref": "https://blogger.googleusercontent.com/img/b/R29vZ2xl/AVvXsEg_96KV6kOkeJQtKvKPAMgPnD9W-0vLRsfvxU_Pk8fezf44OlcZUcApPCd_gS6b8YwjmAECo1RYXM-gHXIXJRqRBN1FCUHXVDd_iW1XqwquEirxnsR7azzDihwBTJ9YXDMuu7UAN7mtNd0/s1600/na%25CC%2581l4.jpg",
          "displayedWidth": 227,
          "displayedHeight": 320,
          "originalWidth": null,
          "originalHeight": null
        },
        "caption": null
      },
      {
        "sourceUrl": "https://blogger.googleusercontent.com/img/b/R29vZ2xl/AVvXsEisIrlBT1AZpj0K4Ha68dwtOawXWiD7ojhyphenhyphenV9lIzTVORAeR0lEQDWu9L0bvgYx6Ome2ILeBsj3j60ODHRGGhjaQHgID1_XpY0rbZ1_UnCL1Kh-4KWVPRavdj7gVBMPqSpMldShNBj2SSGM/s0/naus%CC%8Cnica.png",
        "fallbackUrl": "https://blogger.googleusercontent.com/img/b/R29vZ2xl/AVvXsEisIrlBT1AZpj0K4Ha68dwtOawXWiD7ojhyphenhyphenV9lIzTVORAeR0lEQDWu9L0bvgYx6Ome2ILeBsj3j60ODHRGGhjaQHgID1_XpY0rbZ1_UnCL1Kh-4KWVPRavdj7gVBMPqSpMldShNBj2SSGM/s1600/naus%CC%8Cnica.png",
        "filename": "naušnica.png",
        "blogger": {
          "anchorHref": "https://blogger.googleusercontent.com/img/b/R29vZ2xl/AVvXsEisIrlBT1AZpj0K4Ha68dwtOawXWiD7ojhyphenhyphenV9lIzTVORAeR0lEQDWu9L0bvgYx6Ome2ILeBsj3j60ODHRGGhjaQHgID1_XpY0rbZ1_UnCL1Kh-4KWVPRavdj7gVBMPqSpMldShNBj2SSGM/s1600/naus%CC%8Cnica.png",
          "displayedWidth": 320,
          "displayedHeight": 171,
          "originalWidth": null,
          "originalHeight": null
        },
        "caption": null
      },
      {
        "sourceUrl": "https://blogger.googleusercontent.com/img/b/R29vZ2xl/AVvXsEgtDM-UkqkemH3o_e6S02vHBvhMF-dWKsYB6FZkKYkyPajfcMtXFx03EdsJdPwfq6kYykz2AoogBkyQI_C434xBux_0ZosIul2F8x_5cCFKnX-s6gMHhmWXd5yrdWl0sLziD_rasktpr5w/s0/IMG_1075.JPG",
        "fallbackUrl": "https://blogger.googleusercontent.com/img/b/R29vZ2xl/AVvXsEgtDM-UkqkemH3o_e6S02vHBvhMF-dWKsYB6FZkKYkyPajfcMtXFx03EdsJdPwfq6kYykz2AoogBkyQI_C434xBux_0ZosIul2F8x_5cCFKnX-s6gMHhmWXd5yrdWl0sLziD_rasktpr5w/s1600/IMG_1075.JPG",
        "filename": "IMG_1075.JPG",
        "blogger": {
          "anchorHref": "https://blogger.googleusercontent.com/img/b/R29vZ2xl/AVvXsEgtDM-UkqkemH3o_e6S02vHBvhMF-dWKsYB6FZkKYkyPajfcMtXFx03EdsJdPwfq6kYykz2AoogBkyQI_C434xBux_0ZosIul2F8x_5cCFKnX-s6gMHhmWXd5yrdWl0sLziD_rasktpr5w/s1600/IMG_1075.JPG",
          "displayedWidth": 320,
          "displayedHeight": 213,
          "originalWidth": null,
          "originalHeight": null
        },
        "caption": null
      },
      {
        "sourceUrl": "https://blogger.googleusercontent.com/img/b/R29vZ2xl/AVvXsEhCvwNTYXHdhAGQAjAEx0Q6pvWCe27HJthCNBtwIwpuRgGNBaBZX-MZxpuExaIer8lzFDLzHhd0DOoAKp4HlfVWj41QGGUitMuORtRR4-xtzf1SjgxVOnfEq3cUxsLYrU-ptYKxWFFiN4I/s0/IMG_1080.JPG",
        "fallbackUrl": "https://blogger.googleusercontent.com/img/b/R29vZ2xl/AVvXsEhCvwNTYXHdhAGQAjAEx0Q6pvWCe27HJthCNBtwIwpuRgGNBaBZX-MZxpuExaIer8lzFDLzHhd0DOoAKp4HlfVWj41QGGUitMuORtRR4-xtzf1SjgxVOnfEq3cUxsLYrU-ptYKxWFFiN4I/s1600/IMG_1080.JPG",
        "filename": "IMG_1080.JPG",
        "blogger": {
          "anchorHref": "https://blogger.googleusercontent.com/img/b/R29vZ2xl/AVvXsEhCvwNTYXHdhAGQAjAEx0Q6pvWCe27HJthCNBtwIwpuRgGNBaBZX-MZxpuExaIer8lzFDLzHhd0DOoAKp4HlfVWj41QGGUitMuORtRR4-xtzf1SjgxVOnfEq3cUxsLYrU-ptYKxWFFiN4I/s1600/IMG_1080.JPG",
          "displayedWidth": 320,
          "displayedHeight": 213,
          "originalWidth": null,
          "originalHeight": null
        },
        "caption": null
      },
      {
        "sourceUrl": "https://blogger.googleusercontent.com/img/b/R29vZ2xl/AVvXsEjAy3YjRfmyojwYAuEWAHDC02aqgRzmPXvrv9LlS_7ubTk4a0Bfp4263KnhZv_1dPj6ZMUr6iKVapVBbhdQ2_2TruLFTTVPik1qYoimxVyya6bxfrrlDJgyAZ-CauHs15fVdx00MDrr3Go/s0/IMG_1081.JPG",
        "fallbackUrl": "https://blogger.googleusercontent.com/img/b/R29vZ2xl/AVvXsEjAy3YjRfmyojwYAuEWAHDC02aqgRzmPXvrv9LlS_7ubTk4a0Bfp4263KnhZv_1dPj6ZMUr6iKVapVBbhdQ2_2TruLFTTVPik1qYoimxVyya6bxfrrlDJgyAZ-CauHs15fVdx00MDrr3Go/s1600/IMG_1081.JPG",
        "filename": "IMG_1081.JPG",
        "blogger": {
          "anchorHref": "https://blogger.googleusercontent.com/img/b/R29vZ2xl/AVvXsEjAy3YjRfmyojwYAuEWAHDC02aqgRzmPXvrv9LlS_7ubTk4a0Bfp4263KnhZv_1dPj6ZMUr6iKVapVBbhdQ2_2TruLFTTVPik1qYoimxVyya6bxfrrlDJgyAZ-CauHs15fVdx00MDrr3Go/s1600/IMG_1081.JPG",
          "displayedWidth": 320,
          "displayedHeight": 213,
          "originalWidth": null,
          "originalHeight": null
        },
        "caption": null
      },
      {
        "sourceUrl": "https://blogger.googleusercontent.com/img/b/R29vZ2xl/AVvXsEirFNTawiyWPkOsiVZHhm10_FKNM8O0oESB_XVUR418mpSBJG9so_icsf-yiFPP2uCv7M4FI4oVI-seMt1geYkSMAVUqDY3APC9Z1bHhWVQ0TB7cCaXvLEWk6ouSndLu5Lx1kveaIDVNlM/s0/IMG_1092.JPG",
        "fallbackUrl": "https://blogger.googleusercontent.com/img/b/R29vZ2xl/AVvXsEirFNTawiyWPkOsiVZHhm10_FKNM8O0oESB_XVUR418mpSBJG9so_icsf-yiFPP2uCv7M4FI4oVI-seMt1geYkSMAVUqDY3APC9Z1bHhWVQ0TB7cCaXvLEWk6ouSndLu5Lx1kveaIDVNlM/s1600/IMG_1092.JPG",
        "filename": "IMG_1092.JPG",
        "blogger": {
          "anchorHref": "https://blogger.googleusercontent.com/img/b/R29vZ2xl/AVvXsEirFNTawiyWPkOsiVZHhm10_FKNM8O0oESB_XVUR418mpSBJG9so_icsf-yiFPP2uCv7M4FI4oVI-seMt1geYkSMAVUqDY3APC9Z1bHhWVQ0TB7cCaXvLEWk6ouSndLu5Lx1kveaIDVNlM/s1600/IMG_1092.JPG",
          "displayedWidth": 213,
          "displayedHeight": 320,
          "originalWidth": null,
          "originalHeight": null
        },
        "caption": null
      },
      {
        "sourceUrl": "https://blogger.googleusercontent.com/img/b/R29vZ2xl/AVvXsEijv6lPnr1xOaHrKKOaIP6TefAM8Bfc3x5UsUuvmnUsFTI0L4wsUESp3vyn2CTOpwweM05kZU2zo2gZd9M2ocbM7BL9vGFpkLg-eOEIpm_RzxUGA4hl09N_KtoWkxQdvqbYfh0vhQ6QZlE/s0/IMG_1093.JPG",
        "fallbackUrl": "https://blogger.googleusercontent.com/img/b/R29vZ2xl/AVvXsEijv6lPnr1xOaHrKKOaIP6TefAM8Bfc3x5UsUuvmnUsFTI0L4wsUESp3vyn2CTOpwweM05kZU2zo2gZd9M2ocbM7BL9vGFpkLg-eOEIpm_RzxUGA4hl09N_KtoWkxQdvqbYfh0vhQ6QZlE/s1600/IMG_1093.JPG",
        "filename": "IMG_1093.JPG",
        "blogger": {
          "anchorHref": "https://blogger.googleusercontent.com/img/b/R29vZ2xl/AVvXsEijv6lPnr1xOaHrKKOaIP6TefAM8Bfc3x5UsUuvmnUsFTI0L4wsUESp3vyn2CTOpwweM05kZU2zo2gZd9M2ocbM7BL9vGFpkLg-eOEIpm_RzxUGA4hl09N_KtoWkxQdvqbYfh0vhQ6QZlE/s1600/IMG_1093.JPG",
          "displayedWidth": 320,
          "displayedHeight": 213,
          "originalWidth": null,
          "originalHeight": null
        },
        "caption": null
      },
      {
        "sourceUrl": "https://blogger.googleusercontent.com/img/b/R29vZ2xl/AVvXsEgvK2gsi0xAb9Vfe3yfx3BrozpR2thfwmPHkTw15fQkw3WKI-k07otwjUdiKdqAzR2hkw-3hz49EKaHkfaB_Hp5_Pe7X0YpaM9BJvdHFwP6s9kAKzu2utTxjAWzpD4v-8tPsIF6MdSdzMo/s0/IMG_1098.JPG",
        "fallbackUrl": "https://blogger.googleusercontent.com/img/b/R29vZ2xl/AVvXsEgvK2gsi0xAb9Vfe3yfx3BrozpR2thfwmPHkTw15fQkw3WKI-k07otwjUdiKdqAzR2hkw-3hz49EKaHkfaB_Hp5_Pe7X0YpaM9BJvdHFwP6s9kAKzu2utTxjAWzpD4v-8tPsIF6MdSdzMo/s1600/IMG_1098.JPG",
        "filename": "IMG_1098.JPG",
        "blogger": {
          "anchorHref": "https://blogger.googleusercontent.com/img/b/R29vZ2xl/AVvXsEgvK2gsi0xAb9Vfe3yfx3BrozpR2thfwmPHkTw15fQkw3WKI-k07otwjUdiKdqAzR2hkw-3hz49EKaHkfaB_Hp5_Pe7X0YpaM9BJvdHFwP6s9kAKzu2utTxjAWzpD4v-8tPsIF6MdSdzMo/s1600/IMG_1098.JPG",
          "displayedWidth": 320,
          "displayedHeight": 213,
          "originalWidth": null,
          "originalHeight": null
        },
        "caption": null
      },
      {
        "sourceUrl": "https://blogger.googleusercontent.com/img/b/R29vZ2xl/AVvXsEgZDtp3WlvDFYLAvtFyIHoJ_L4tjZjdyDyQaXS6_AiOX9UKN2MSGU03XZpz1WyyNE89Fs3LJqiDt8zJOd1hdCkErjg2F5QGuipwu8F7W_pSXqDFejO6JCrnOjj8Y5mF8rJG4d41rxGp-vM/s0/IMG_1099.JPG",
        "fallbackUrl": "https://blogger.googleusercontent.com/img/b/R29vZ2xl/AVvXsEgZDtp3WlvDFYLAvtFyIHoJ_L4tjZjdyDyQaXS6_AiOX9UKN2MSGU03XZpz1WyyNE89Fs3LJqiDt8zJOd1hdCkErjg2F5QGuipwu8F7W_pSXqDFejO6JCrnOjj8Y5mF8rJG4d41rxGp-vM/s1600/IMG_1099.JPG",
        "filename": "IMG_1099.JPG",
        "blogger": {
          "anchorHref": "https://blogger.googleusercontent.com/img/b/R29vZ2xl/AVvXsEgZDtp3WlvDFYLAvtFyIHoJ_L4tjZjdyDyQaXS6_AiOX9UKN2MSGU03XZpz1WyyNE89Fs3LJqiDt8zJOd1hdCkErjg2F5QGuipwu8F7W_pSXqDFejO6JCrnOjj8Y5mF8rJG4d41rxGp-vM/s1600/IMG_1099.JPG",
          "displayedWidth": 320,
          "displayedHeight": 213,
          "originalWidth": null,
          "originalHeight": null
        },
        "caption": null
      },
      {
        "sourceUrl": "https://blogger.googleusercontent.com/img/b/R29vZ2xl/AVvXsEiuKcav0iIrI6zAY2wX5a5C_zOt0_wzSItcjkZsUEk8WIeEyXcvUqfqZ75Q_90W0jq-d3gMOuwOWzseGX0QRbtf8lfnuDfltMnCtKCatuC49fFfXhOhCCECyFfp7Uf4n_ccFRDpheBAdkI/s0/IMG_1109.JPG",
        "fallbackUrl": "https://blogger.googleusercontent.com/img/b/R29vZ2xl/AVvXsEiuKcav0iIrI6zAY2wX5a5C_zOt0_wzSItcjkZsUEk8WIeEyXcvUqfqZ75Q_90W0jq-d3gMOuwOWzseGX0QRbtf8lfnuDfltMnCtKCatuC49fFfXhOhCCECyFfp7Uf4n_ccFRDpheBAdkI/s1600/IMG_1109.JPG",
        "filename": "IMG_1109.JPG",
        "blogger": {
          "anchorHref": "https://blogger.googleusercontent.com/img/b/R29vZ2xl/AVvXsEiuKcav0iIrI6zAY2wX5a5C_zOt0_wzSItcjkZsUEk8WIeEyXcvUqfqZ75Q_90W0jq-d3gMOuwOWzseGX0QRbtf8lfnuDfltMnCtKCatuC49fFfXhOhCCECyFfp7Uf4n_ccFRDpheBAdkI/s1600/IMG_1109.JPG",
          "displayedWidth": 320,
          "displayedHeight": 213,
          "originalWidth": null,
          "originalHeight": null
        },
        "caption": null
      },
      {
        "sourceUrl": "https://blogger.googleusercontent.com/img/b/R29vZ2xl/AVvXsEhw8vUNOxiq-GjF9fS1wkcg5g4yuyzhPdlYQEpaP6s60tr1_o56ehfCozvFmY6rC0Fdq1ipgwuxR_N_cdQPff-uGdzcl0q7aGFFNK13bONIM69rIta7iqpAwpu5nUBHWvADFviDEaAxbeg/s0/IMG_1124.JPG",
        "fallbackUrl": "https://blogger.googleusercontent.com/img/b/R29vZ2xl/AVvXsEhw8vUNOxiq-GjF9fS1wkcg5g4yuyzhPdlYQEpaP6s60tr1_o56ehfCozvFmY6rC0Fdq1ipgwuxR_N_cdQPff-uGdzcl0q7aGFFNK13bONIM69rIta7iqpAwpu5nUBHWvADFviDEaAxbeg/s1600/IMG_1124.JPG",
        "filename": "IMG_1124.JPG",
        "blogger": {
          "anchorHref": "https://blogger.googleusercontent.com/img/b/R29vZ2xl/AVvXsEhw8vUNOxiq-GjF9fS1wkcg5g4yuyzhPdlYQEpaP6s60tr1_o56ehfCozvFmY6rC0Fdq1ipgwuxR_N_cdQPff-uGdzcl0q7aGFFNK13bONIM69rIta7iqpAwpu5nUBHWvADFviDEaAxbeg/s1600/IMG_1124.JPG",
          "displayedWidth": 320,
          "displayedHeight": 213,
          "originalWidth": null,
          "originalHeight": null
        },
        "caption": null
      },
      {
        "sourceUrl": "https://blogger.googleusercontent.com/img/b/R29vZ2xl/AVvXsEgVDyv4aE2sfYJ-nW5QdByXQtS7iFqAKOHJqH3BoR07UL-UcAlyRQOIBK-jkFaGEupvcf-upJKMGsCdqDzwLSbjpPVBZ6roUdqBpKlFOzKdBCudIOh8iVPCuNfgM3P8CuhuNHaqPud8QiU/s0/IMG_1126.JPG",
        "fallbackUrl": "https://blogger.googleusercontent.com/img/b/R29vZ2xl/AVvXsEgVDyv4aE2sfYJ-nW5QdByXQtS7iFqAKOHJqH3BoR07UL-UcAlyRQOIBK-jkFaGEupvcf-upJKMGsCdqDzwLSbjpPVBZ6roUdqBpKlFOzKdBCudIOh8iVPCuNfgM3P8CuhuNHaqPud8QiU/s1600/IMG_1126.JPG",
        "filename": "IMG_1126.JPG",
        "blogger": {
          "anchorHref": "https://blogger.googleusercontent.com/img/b/R29vZ2xl/AVvXsEgVDyv4aE2sfYJ-nW5QdByXQtS7iFqAKOHJqH3BoR07UL-UcAlyRQOIBK-jkFaGEupvcf-upJKMGsCdqDzwLSbjpPVBZ6roUdqBpKlFOzKdBCudIOh8iVPCuNfgM3P8CuhuNHaqPud8QiU/s1600/IMG_1126.JPG",
          "displayedWidth": 320,
          "displayedHeight": 213,
          "originalWidth": null,
          "originalHeight": null
        },
        "caption": null
      },
      {
        "sourceUrl": "https://blogger.googleusercontent.com/img/b/R29vZ2xl/AVvXsEgI3AjVvpM4srqZzlzzaket764LVzjj1Ko36I_ME5IWdUSakGsAZCUmmxlSSP_xtLpH1V_JdlP2sANy6SqXTrn2FXsVndlewgDJbqbfcUyeQyqo468IxKZ-ENP0_hPdpIflKiz9ex6hNDY/s0/IMG_1136.JPG",
        "fallbackUrl": "https://blogger.googleusercontent.com/img/b/R29vZ2xl/AVvXsEgI3AjVvpM4srqZzlzzaket764LVzjj1Ko36I_ME5IWdUSakGsAZCUmmxlSSP_xtLpH1V_JdlP2sANy6SqXTrn2FXsVndlewgDJbqbfcUyeQyqo468IxKZ-ENP0_hPdpIflKiz9ex6hNDY/s1600/IMG_1136.JPG",
        "filename": "IMG_1136.JPG",
        "blogger": {
          "anchorHref": "https://blogger.googleusercontent.com/img/b/R29vZ2xl/AVvXsEgI3AjVvpM4srqZzlzzaket764LVzjj1Ko36I_ME5IWdUSakGsAZCUmmxlSSP_xtLpH1V_JdlP2sANy6SqXTrn2FXsVndlewgDJbqbfcUyeQyqo468IxKZ-ENP0_hPdpIflKiz9ex6hNDY/s1600/IMG_1136.JPG",
          "displayedWidth": 320,
          "displayedHeight": 213,
          "originalWidth": null,
          "originalHeight": null
        },
        "caption": null
      },
      {
        "sourceUrl": "https://blogger.googleusercontent.com/img/b/R29vZ2xl/AVvXsEheNL_cOUvKG_f5Euty0PtzU_PVQOpdHFoQ2fLRuz35Bmp6YSyUWcxt3249uDUmIJviKBuFd-Q5d6vWDCEcWKJOB520IdMpu4IBc8naifqMPLL_y8JvS4jqfrroVUjUM5Q12wlq_soBCk8/s0/IMG_1161.JPG",
        "fallbackUrl": "https://blogger.googleusercontent.com/img/b/R29vZ2xl/AVvXsEheNL_cOUvKG_f5Euty0PtzU_PVQOpdHFoQ2fLRuz35Bmp6YSyUWcxt3249uDUmIJviKBuFd-Q5d6vWDCEcWKJOB520IdMpu4IBc8naifqMPLL_y8JvS4jqfrroVUjUM5Q12wlq_soBCk8/s1600/IMG_1161.JPG",
        "filename": "IMG_1161.JPG",
        "blogger": {
          "anchorHref": "https://blogger.googleusercontent.com/img/b/R29vZ2xl/AVvXsEheNL_cOUvKG_f5Euty0PtzU_PVQOpdHFoQ2fLRuz35Bmp6YSyUWcxt3249uDUmIJviKBuFd-Q5d6vWDCEcWKJOB520IdMpu4IBc8naifqMPLL_y8JvS4jqfrroVUjUM5Q12wlq_soBCk8/s1600/IMG_1161.JPG",
          "displayedWidth": 320,
          "displayedHeight": 213,
          "originalWidth": null,
          "originalHeight": null
        },
        "caption": null
      },
      {
        "sourceUrl": "https://blogger.googleusercontent.com/img/b/R29vZ2xl/AVvXsEj1Tw8AejNmPvKpG6eszD5vFeEy8VXvHrsLFanrdYJxthkiLMREzTzZHl5l-oPdnZFFNGe_s0IbnNt4RAAgP9JYqx286pM2l0SxKkUbiA_UQ6AC423ttSO8bxc5T-vccVU8nzTBHfQRErY/s0/IMG_1171.JPG",
        "fallbackUrl": "https://blogger.googleusercontent.com/img/b/R29vZ2xl/AVvXsEj1Tw8AejNmPvKpG6eszD5vFeEy8VXvHrsLFanrdYJxthkiLMREzTzZHl5l-oPdnZFFNGe_s0IbnNt4RAAgP9JYqx286pM2l0SxKkUbiA_UQ6AC423ttSO8bxc5T-vccVU8nzTBHfQRErY/s1600/IMG_1171.JPG",
        "filename": "IMG_1171.JPG",
        "blogger": {
          "anchorHref": "https://blogger.googleusercontent.com/img/b/R29vZ2xl/AVvXsEj1Tw8AejNmPvKpG6eszD5vFeEy8VXvHrsLFanrdYJxthkiLMREzTzZHl5l-oPdnZFFNGe_s0IbnNt4RAAgP9JYqx286pM2l0SxKkUbiA_UQ6AC423ttSO8bxc5T-vccVU8nzTBHfQRErY/s1600/IMG_1171.JPG",
          "displayedWidth": 320,
          "displayedHeight": 213,
          "originalWidth": null,
          "originalHeight": null
        },
        "caption": null
      },
      {
        "sourceUrl": "https://blogger.googleusercontent.com/img/b/R29vZ2xl/AVvXsEjCSno30acUcoPI-rMLBrG-ZJxg785468TpwidH9n_xiTNz0xyncBAJ7rA0sgWsYSexhdRopUXLSsVGu_BFkgGhgCiWyKyfRoF-eUWMfIicgRq1ZBee-mLWm1jrKAzRxOSFwDja007Auf8/s0/IMG_1176.JPG",
        "fallbackUrl": "https://blogger.googleusercontent.com/img/b/R29vZ2xl/AVvXsEjCSno30acUcoPI-rMLBrG-ZJxg785468TpwidH9n_xiTNz0xyncBAJ7rA0sgWsYSexhdRopUXLSsVGu_BFkgGhgCiWyKyfRoF-eUWMfIicgRq1ZBee-mLWm1jrKAzRxOSFwDja007Auf8/s1600/IMG_1176.JPG",
        "filename": "IMG_1176.JPG",
        "blogger": {
          "anchorHref": "https://blogger.googleusercontent.com/img/b/R29vZ2xl/AVvXsEjCSno30acUcoPI-rMLBrG-ZJxg785468TpwidH9n_xiTNz0xyncBAJ7rA0sgWsYSexhdRopUXLSsVGu_BFkgGhgCiWyKyfRoF-eUWMfIicgRq1ZBee-mLWm1jrKAzRxOSFwDja007Auf8/s1600/IMG_1176.JPG",
          "displayedWidth": 320,
          "displayedHeight": 213,
          "originalWidth": null,
          "originalHeight": null
        },
        "caption": null
      }
    ],
    "tags": [
      "Mužla - Čenkov"
    ],
    "category": null,
    "location": {
      "name": "Mužla - Čenkov",
      "latitude": 47.762984,
      "longitude": 18.528914,
      "region": null,
      "country": null
    },
    "keyFacts": [
      {
        "label": "Poloha",
        "value": "Hradisko leží priamo na brehu Dunaja, na jednej z mála výrazne vyvýšených polôh medzi Štúrovom a Komárnom",
        "icon": "map"
      },
      {
        "label": "Opevnenie",
        "value": "Poloha Vilmakert bola z troch strán obohnaná valom so zachovanou dĺžkou cca 500 m, na strane k Dunaju ju chránil 3 až 5 m vysoký strmý breh",
        "icon": "shield"
      },
      {
        "label": "Rozloha",
        "value": "Súčasná rozloha polohy Vilmakert je 2,79 ha, pôvodnú rozlohu kvôli erózii dunajského brehu nemožno určiť",
        "icon": "mountain"
      },
      {
        "label": "Sídliskové objekty",
        "value": "Na hradisku bolo preskúmaných 271 sídliskových objektov, prevažne zvyškov zahĺbených stavieb štvoruholníkového pôdorysu",
        "icon": "building"
      },
      {
        "label": "Objekt X",
        "value": "Dr. Hanuliak objavil vo vnútri hradiska stavbu unikátnych rozmerov v rámci slovanského obdobia na území Slovenska, obklopenú hrobmi s bohatou výbavou",
        "icon": "star"
      },
      {
        "label": "Obživa",
        "value": "Archeozoologické zistenia dokladajú chov hovädzieho dobytka, ošípaných, sčasti oviec, kôz i hydiny, doplnený lovom a rybolovom",
        "icon": "custom"
      },
      {
        "label": "Písomné pramene",
        "value": "Gesta Hungarorum Šimona z Kézy spomína dobytie hradu pri brode Zub, hypoteticky spájané s Čenkovom; z roku 1135 pochádza doklad o „predium in villa Chenka“",
        "icon": "book"
      }
    ],
    "timeline": [
      {
        "year": "9. – 10. storočie",
        "title": "Existencia slovanského hradiska",
        "description": "Na lokalite Mužla-Čenkov sa v 9. až 10. storočí rozprestieralo slovanské hradisko, ktorého časti sa dnes nachádzajú na polohe Vilmakert a Orechový sad.",
        "type": "era"
      },
      {
        "year": "2. štvrtina 9. storočia",
        "title": "Osídlenie lokality",
        "description": "Lokalita bola osídlená najneskôr v druhej štvrtine 9. storočia kolonizačným spôsobom väčšou skupinou obyvateľstva, ktorá bola schopná plánovite zastavať vybranú plochu a opevniť ju valom solídnej konštrukcie.",
        "type": "founding"
      },
      {
        "year": "2. tretina 9. storočia",
        "title": "Vybudovanie opevnenia prvého horizontu",
        "description": "V súvislosti s rastúcim napätím medzi Východofranskou a Veľkomoravskou ríšou možno s týmto obdobím spájať na čenkovskom hradisku systém opevnenia a nálezy militantného charakteru z prvého horizontu osídlenia.",
        "type": "construction"
      },
      {
        "year": "861",
        "title": "Vojenské strety a pripojenie územia k Veľkej Morave",
        "description": "Na základe výsledkov vojenských stretov bolo k teritóriu Veľkej Moravy pripojené územie od Ostrihomu k Vesprému, Bakonskému lesu a dolnému toku Ráby, čo mohlo priniesť obrat vo funkčnosti čenkovského opevneného sídliska (druhý horizont).",
        "type": "battle"
      },
      {
        "year": "1135",
        "title": "Písomná zmienka „villa Chenka“",
        "description": "Nedochovaný doklad z roku 1135 spomína „predium in villa Chenka“, ktoré daroval Štefan I. jednému z predkov rodu Hunt-Poznan; označenie villa svedčí o strate funkcie opevnenia.",
        "type": "event"
      },
      {
        "year": "2. – 3. tretina 10. storočia",
        "title": "Redukcia osídlenia v treťom horizonte",
        "description": "V treťom horizonte osídlenia, patriacom do poveľkomoravského obdobia, dochádza k výraznej redukcii koncentrácie osídlenia, pričom z pôvodných obyvateľov zostáva iba malá časť; archeológovia vylučujú katastrofický zánik vojenskou akciou.",
        "type": "event"
      },
      {
        "year": "11. – 12. storočie",
        "title": "Štvrté obdobie - malá osada",
        "description": "Trend redukcie osídlenia pokračuje aj do štvrtého obdobia; v pôvodnom sídliskovom areáli sa objavujú objekty malej osady rozptýleného typu, zachytenej v písomných prameňoch ako villa.",
        "type": "event"
      }
    ],
    "quotes": [],
    "blocks": [
      {
        "__component": "content.rich-text",
        "body": [
          {
            "type": "paragraph",
            "children": [
              {
                "type": "text",
                "text": "Na lokalite Mužla-Čenkov sa v 9. až 10. storočí rozprestieralo slovanské hradisko, ktorého časti sa dnes nachádzajú na polohe Vilmakert a Orechový sad. Možno ho zaradiť medzi hradiská s dominujúcou strážnou a vojenskou funkciou (Hulínek). Lokalita leží priamo na brehu Dunaja. Ide o polykultúrnu lokalitu, na ktorej bolo doposiaľ zistené osídlenie kultúry s mladšou lineárnou keramikou, želiezovskej skupiny, badenskej kultúry, skupiny Kosihy-Čaka, nálezy z prelomu staršej a strednej doby bronzovej, vekerzugskej kultúry, doby laténskej a obdobia včasného stredoveku - 9. až 12. storočia. Ide o jednu z mála výrazne vyvýšených polôh priamo na brehu Dunaja, medzi Štúrovom a Komárnom. "
              }
            ]
          }
        ]
      },
      {
        "__component": "content.embed",
        "provider": "youtube",
        "embedId": "oDujLc1u4-w",
        "url": "https://www.youtube.com/embed/oDujLc1u4-w",
        "caption": ""
      },
      {
        "__component": "content.embed",
        "provider": "youtube",
        "embedId": "l6LqWu4IdaU",
        "url": "https://www.youtube.com/embed/l6LqWu4IdaU",
        "caption": ""
      },
      {
        "__component": "content.rich-text",
        "body": [
          {
            "type": "heading",
            "level": 2,
            "children": [
              {
                "type": "text",
                "text": "Opevnenie"
              }
            ]
          }
        ]
      },
      {
        "__component": "content.rich-text",
        "body": [
          {
            "type": "paragraph",
            "children": [
              {
                "type": "text",
                "text": "Poloha Vilmakert bola pôvodne obohnaná z troch strán valom, na strane k Dunaju je 3 až 5 m vysoký, strmý breh. Súčasná rozloha polohy je 2,79 ha. Pôvodnú rozlohu, vzhľadom na eróziu brehu, nie je možné určiť. Celá plocha lokality vystupuje v teréne oproti okolitej úrovni cca o 1 m. Ako už bolo spomenuté, lokalita je obohnaná z troch strán valom. Najlepšie je zachovaný na SV strane, kde dosahuje oproti vnútornému areálu prevýšenie 2 až 3 m. Na SZ strane bol kultiváciou znížený a na Z strane čiastočne porušený výstavbou protipovodňovej hrádze. Tvar opevnenia je lichobežníkový a celková zachovaná dĺžka je cca 500 m. Pôvodnú dĺžku valu v dôsledku erózie dunajského brehu je ťažko odhadnúť. Opevnenie na tejto strane však vzhľadom na výšku brehu nebolo nutné budovať rovnakým spôsobom ako smerom do vnútrozemia. Pozostávalo azda iba z palisády. Odkrytá bola deštrukcia valu z drobnejších lomových kameňov, tiahnuca sa v smere von z opevnenia, až po úroveň terajšieho terénu. Nebolo v nej však možné jednoznačne rozoznať čelný múr, tak ako ešte v päťdesiatych rokoch. "
              }
            ]
          }
        ]
      },
      {
        "__component": "content.image-block",
        "imageRef": {
          "sourceUrl": "https://blogger.googleusercontent.com/img/b/R29vZ2xl/AVvXsEgZ3KQPAoJPz0YONuBW_e9HYuagXofAuauIXM8V4cjckRWdvsTZY8CdHjpA1lU4EKyKueeY8Q1uG26VosZy5CicbdA34TzcebpWoMwItGeOwDyF3wPLJvkVXyIByjqLXMm7d34kHdEckaY/s0/P7275733.JPG",
          "fallbackUrl": "https://blogger.googleusercontent.com/img/b/R29vZ2xl/AVvXsEgZ3KQPAoJPz0YONuBW_e9HYuagXofAuauIXM8V4cjckRWdvsTZY8CdHjpA1lU4EKyKueeY8Q1uG26VosZy5CicbdA34TzcebpWoMwItGeOwDyF3wPLJvkVXyIByjqLXMm7d34kHdEckaY/s1600/P7275733.JPG",
          "filename": "P7275733.JPG",
          "blogger": {
            "anchorHref": "https://blogger.googleusercontent.com/img/b/R29vZ2xl/AVvXsEgZ3KQPAoJPz0YONuBW_e9HYuagXofAuauIXM8V4cjckRWdvsTZY8CdHjpA1lU4EKyKueeY8Q1uG26VosZy5CicbdA34TzcebpWoMwItGeOwDyF3wPLJvkVXyIByjqLXMm7d34kHdEckaY/s1600/P7275733.JPG",
            "displayedWidth": 320,
            "displayedHeight": 185,
            "originalWidth": null,
            "originalHeight": null
          }
        },
        "alt": "Naša predstava o vzhľade hradiska. Autor: T. Humaj",
        "caption": "Naša predstava o vzhľade hradiska. Autor: T. Humaj",
        "position": "center",
        "showCaption": true,
        "width": "60",
        "aspectRatio": "auto",
        "rounded": true,
        "shadow": true
      },
      {
        "__component": "content.rich-text",
        "body": [
          {
            "type": "paragraph",
            "children": [
              {
                "type": "text",
                "text": "Na reze opevnenia upúta hnedočierna vrstva, tiahnuca sa po celej dĺžke a plynule prechádzajúca do priekopy. Je pomerne hutná, avšak obsahuje archeologický materiál zo všetkých období. Kamenná deštrukcia valu vo všetkých známych profiloch sa nachádza na tejto vrstve. Tvorená je z lomového kameňa bridlicového typu, dobre štiepateľného. Vo vzdialenosti 190 cm od jej začiatku z vnútornej strany opevnenia sa nachádzali zvyšky čelného múru vybudovaného z nasucho kladených väčších plochých kameňov. Hrúbka sa pohybovala okolo 60 cm. Smerom von z opevnenia výška deštrukcie nepravidelne klesala až do vzdialenosti 400 cm od čelného múru. V tejto časti sa nachádzali väčšie lomové kamene pieskovcového charakteru. Možno sa tak domnievať, že pri výstavbe múru bol použitý dvojaký materiál. V spodnej časti plochý, štiepateľný a teda pre tieto účely nanajvýš vhodný, v hornej, resp. na korunu múru nepravidelný lomový kameň. Prakticky celá deštrukcia bola prepálená, tehlovej farby, miestami premiešaná značným množstvom uhlíkov. Väčšie kusy uhlíkov sa nachádzali najmä v okolí vnútorného okraja deštrukcie. Bez stôp prepálenia bola iba časť v tesnej blízkosti čelného múru do výšky cca 40 cm a pod ním. To by azda umožňovalo uvažovať o prihrnutí päty múru z vonkajšej strany. Celá vonkajšia časť deštrukcie je prekrytá zásypom z hnedej zeminy. Smerom od deštrukcie dovnútra areálu, vo vzdialenosti 80 cm od nej, začína hnedočerný násyp dlhý 500 cm a vysoký 30 – 60 cm, oddelený od základnej vrstvy tenkou pieskovou vrstvičkou. Zrejme ide o vnútornú bermu. Je v podstate toho istého charakteru ako vrstva pod ním, no na rozdiel od nej však obsahuje i primes drobného riečneho štrku. Celá berma je ukončená zásypom svetlejšej hnedej zeminy piesčitého charakteru, siahajúcim až po úroveň ornice. Pomerne nedostatočné informácie máme o priekope, pretože ju z technických príčin nebolo možné úplne preskúmať. Môžeme iba konštatovať, že začína vo vzdialenosti 610 cm od čelného múru. "
              }
            ]
          }
        ]
      },
      {
        "__component": "content.image-block",
        "imageRef": {
          "sourceUrl": "https://blogger.googleusercontent.com/img/b/R29vZ2xl/AVvXsEjqzSp9XJW05SjtAe8vYQRs57fkJMxjW0KdWNHmfO0LcHCMmwP6JuVZo7EuYijPlQ3JvG318DqqeOWFzVP05LiSXnMUt_cjnpYmr68yOAvGebiZuzxkzIKADK1JCHhEO2ydQe8W2QYCNrI/s0/mapa+1+VM.png",
          "fallbackUrl": "https://blogger.googleusercontent.com/img/b/R29vZ2xl/AVvXsEjqzSp9XJW05SjtAe8vYQRs57fkJMxjW0KdWNHmfO0LcHCMmwP6JuVZo7EuYijPlQ3JvG318DqqeOWFzVP05LiSXnMUt_cjnpYmr68yOAvGebiZuzxkzIKADK1JCHhEO2ydQe8W2QYCNrI/s1600/mapa+1+VM.png",
          "filename": "mapa+1+VM.png",
          "blogger": {
            "anchorHref": "https://blogger.googleusercontent.com/img/b/R29vZ2xl/AVvXsEjqzSp9XJW05SjtAe8vYQRs57fkJMxjW0KdWNHmfO0LcHCMmwP6JuVZo7EuYijPlQ3JvG318DqqeOWFzVP05LiSXnMUt_cjnpYmr68yOAvGebiZuzxkzIKADK1JCHhEO2ydQe8W2QYCNrI/s1600/mapa+1+VM.png",
            "displayedWidth": 320,
            "displayedHeight": 176,
            "originalWidth": null,
            "originalHeight": null
          }
        },
        "alt": "A tu máme 1. vojenské mapovanie (1764 – 1787). Je na ňom vyznačené hradisko?",
        "caption": "A tu máme 1. vojenské mapovanie (1764 – 1787). Je na ňom vyznačené hradisko?",
        "position": "right",
        "showCaption": true,
        "width": "60",
        "aspectRatio": "auto",
        "rounded": true,
        "shadow": true
      },
      {
        "__component": "content.rich-text",
        "body": [
          {
            "type": "paragraph",
            "children": [
              {
                "type": "text",
                "text": "K otázke vzniku a zániku opevnenia môže byť zaujímavá zmienka Šimona z Kézy v známej knihe bájí a povestí Gesta Hungarorum, týkajúca sa starých Maďarov: „Vyšli tedy se vztyčenými prapory, s ženami, dětmi a stády a přešli Dunaj v Pešti a u brodu Zub (Szob) a tam dobyli jakýsi hrad v okolí Dunaje, v němž se shromáždili Svatoplukovi vojáci, kteří se zachránili útěkem, když jejich pán zahynul“. I keď je hodnovernosť tohto prameňa nízka a daná časom jeho vzniku v rokoch 1282 až 1285 (zachovaný iba v odpise z 15. stor.), treba poukázať na skutočnosť, že v prípade Čenkova ide o dosiaľ jediné známe hradisko v oblasti Dunaja. Na druhej strane sa však na sídlisku nezistil katastrofický horizont. Hoci teda hypoteticky by sme mohli spájať uvedenú správu s lokalitou v Čenkove, ich jednoznačné stotožnenie zostáva viac ako problematické. Ďalšia písomná správa, nepriamo sa viažuca k opevneniu, pochádza z nedochovaného dokladu z roku 1135, kde sa spomína „predium in villa Chenka“, ktoré daroval Štefan I. jednému z predkov rodu Hunt-Poznan. Označenie villa sa v latinskej terminológii 11. – 12. stor. používa pre neopevnený sídliskový celok s viacerými rodinami, čo teda svedčí o strate funkcie opevnenia."
              }
            ]
          }
        ]
      },
      {
        "__component": "content.image-block",
        "imageRef": {
          "sourceUrl": "https://blogger.googleusercontent.com/img/b/R29vZ2xl/AVvXsEiBQ9JEM-CZXumiPwsoBD_pEA-KgxnXV3tZBGNc6VYJWkm_Uv4Rf6nlEo-q8lGJk2Z_skKMvFzxl_oUTlC9fimBvQ0uE2GpoLXN1tWFr-786H9TYXh1KJ6Oo5ADxvLhljACfc6Qhge1Cx8/s0/14958088_218955318527133_1816232901_o.jpg",
          "fallbackUrl": "https://blogger.googleusercontent.com/img/b/R29vZ2xl/AVvXsEiBQ9JEM-CZXumiPwsoBD_pEA-KgxnXV3tZBGNc6VYJWkm_Uv4Rf6nlEo-q8lGJk2Z_skKMvFzxl_oUTlC9fimBvQ0uE2GpoLXN1tWFr-786H9TYXh1KJ6Oo5ADxvLhljACfc6Qhge1Cx8/s1600/14958088_218955318527133_1816232901_o.jpg",
          "filename": "14958088_218955318527133_1816232901_o.jpg",
          "blogger": {
            "anchorHref": "https://blogger.googleusercontent.com/img/b/R29vZ2xl/AVvXsEiBQ9JEM-CZXumiPwsoBD_pEA-KgxnXV3tZBGNc6VYJWkm_Uv4Rf6nlEo-q8lGJk2Z_skKMvFzxl_oUTlC9fimBvQ0uE2GpoLXN1tWFr-786H9TYXh1KJ6Oo5ADxvLhljACfc6Qhge1Cx8/s1600/14958088_218955318527133_1816232901_o.jpg",
            "displayedWidth": 320,
            "displayedHeight": 180,
            "originalWidth": null,
            "originalHeight": null
          }
        },
        "alt": "Objekt X. Počas výskumu slovanského hradiska objavil Dr. Hanuliak v jeho priestore stavbu, ktorá je svojimi rozmermi unikátna v slovanskom období na území Slovenska. Stála na návrší vo vnútri hradiska a okolo nej sa nachádzalo niekoľko hrobov s bohatou vý",
        "caption": "Objekt X. Počas výskumu slovanského hradiska objavil Dr. Hanuliak v jeho priestore stavbu, ktorá je svojimi rozmermi unikátna v slovanskom období na území Slovenska. Stála na návrší vo vnútri hradiska a okolo nej sa nachádzalo niekoľko hrobov s bohatou výbavou. Stavba mohla mať jednak náboženský charakter, ale zároveň mohla slúžiť aj ako reprezentačná budova šľachty. Modla nie je na tom mieste doložená. Koly pri hroboch tiež nie, ale Dr. Hanuliak predpokladá, že tam mohli byť.",
        "position": "left",
        "showCaption": true,
        "width": "60",
        "aspectRatio": "auto",
        "rounded": true,
        "shadow": true
      },
      {
        "__component": "content.rich-text",
        "body": [
          {
            "type": "paragraph",
            "children": [
              {
                "type": "text",
                "text": "Taktiež sa predpokladá ohradenie areálu ľahkým plotom."
              }
            ]
          }
        ]
      },
      {
        "__component": "content.rich-text",
        "body": [
          {
            "type": "heading",
            "level": 2,
            "children": [
              {
                "type": "text",
                "text": "Vnútorná štruktúra zástavby"
              }
            ]
          }
        ]
      },
      {
        "__component": "content.rich-text",
        "body": [
          {
            "type": "paragraph",
            "children": [
              {
                "type": "text",
                "text": "Doterajšie poznatky o intenzite a kvalite osídlenia tejto lokality naznačujú, že sa tu nachádzala nezvykle veľká koncentrácia sídliskových objektov z obdobia raného stredoveku (najmä 9. a 10. stor.). Na hradisku sa našlo 271 sídliskových objektov, ktorými sú prevažne zvyšky zahĺbených stavieb štvoruholníkového pôdorysu, konštrukcií a zariadení, najmä vykurovacích zariadení a jám, najmä obilníc. Rozloženie stavieb pripomína najviac nepravidelný, zhlukový typ zástavby. Detailné analýzy pôdorysného plánu preskúmanej časti lokality viedli k záveru o tom, že zástavba lokality bola pravdepodobne uskutočňovaná plánovito podľa vopred stanovených pravidiel, medzi ktorými hlavným bolo dodržiavanie dištančných pomerov, resp. vzájomných vzdialeností medzi jednotlivými stavbami (nárožiami stavieb), v procese ich zakladania. Základnú jednotku osídlenia tvorila skupina 2 – 6 domov (rodín) usporiadaných do urbanistických celkov.\n \n "
              }
            ]
          }
        ]
      },
      {
        "__component": "content.image-block",
        "imageRef": {
          "sourceUrl": "https://blogger.googleusercontent.com/img/b/R29vZ2xl/AVvXsEj8gtHZg0UCO3BSZ5RMx58d4wQBF4vMzw7i-MefWmicJRlP571RSElqZYkzN9Ca_Nqo228vMEF7UhbU813thjSM-ny3TnjLujydhZgHpgmvOeysn0uPocEVh5cZ6DDh45YlS7YED0N2p4k/s0/Sni%25CC%2581mka+obrazovky+2016-09-16+o%25C2%25A019.30.32.png",
          "fallbackUrl": "https://blogger.googleusercontent.com/img/b/R29vZ2xl/AVvXsEj8gtHZg0UCO3BSZ5RMx58d4wQBF4vMzw7i-MefWmicJRlP571RSElqZYkzN9Ca_Nqo228vMEF7UhbU813thjSM-ny3TnjLujydhZgHpgmvOeysn0uPocEVh5cZ6DDh45YlS7YED0N2p4k/s1600/Sni%25CC%2581mka+obrazovky+2016-09-16+o%25C2%25A019.30.32.png",
          "filename": "Sni%CC%81mka+obrazovky+2016-09-16+o%C2%A019.30.32.png",
          "blogger": {
            "anchorHref": "https://blogger.googleusercontent.com/img/b/R29vZ2xl/AVvXsEj8gtHZg0UCO3BSZ5RMx58d4wQBF4vMzw7i-MefWmicJRlP571RSElqZYkzN9Ca_Nqo228vMEF7UhbU813thjSM-ny3TnjLujydhZgHpgmvOeysn0uPocEVh5cZ6DDh45YlS7YED0N2p4k/s1600/Sni%25CC%2581mka+obrazovky+2016-09-16+o%25C2%25A019.30.32.png",
            "displayedWidth": 320,
            "displayedHeight": 180,
            "originalWidth": null,
            "originalHeight": null
          }
        },
        "alt": "Mužla - Čenkov",
        "caption": "",
        "position": "left",
        "showCaption": false,
        "width": "60",
        "aspectRatio": "auto",
        "rounded": true,
        "shadow": true
      },
      {
        "__component": "content.rich-text",
        "body": [
          {
            "type": "heading",
            "level": 2,
            "children": [
              {
                "type": "text",
                "text": "Postavenie obyvateľov hradiska"
              }
            ]
          }
        ]
      },
      {
        "__component": "content.rich-text",
        "body": [
          {
            "type": "paragraph",
            "children": [
              {
                "type": "text",
                "text": "Obraz o úrovni socio-ekonomického prostredia odkrývaného sídliskového celku dostáva konkrétnejšiu podobu po preukázaní jeho spätosti s opevňovacím systémom pozostávajúcim z drevozemného valu s kamennou plentou a priekopou. Sídliskový útvar možno potom stotožniť s jedným z nížinných hradísk veľkomoravského typu. Doklady o vyššej socio-ekonomickej úrovni daného sídliska, tradične spájaného s touto kategóriou, nie sú jednoznačné. Podiel má na tom aj nízky počet výskumom získaných predmetov akými sú zbrane a súčasti bojovníckeho výstroja, sekerovité hrivny, misky sliezskeho typu i vedierka. Ich reprezentanti bývajú totiž v hojnej miere frekventovaní v súvekých administratívno-hospodárskych centrách a ich sídliskových aglomeráciách. Zvyšné predmety materiálnej kultúry, spolu s podstatnou časťou keramického fondu nálezov, informujú skôr o priemernosti. Iba menej početná kolekcia nádob nesie znaky vyššej výrobno-technickej dokonalosti vyhotovenia. Výnimočnosť niektorých jej foriem a spôsob aplikácie výzdoby zodpovedá vyšším funkčno-estetickým nárokom užívateľov a nepriamo presviedča o prostredí relatívne vyššej vrstvy. Do kategórie takýchto nálezov patrí aj nájdená ostroha so súčasťami upínania-remeňa. V hrobe tohto jedinca, z kategórie jazdeckých bojovníkov, sa výnimočne našli aj stopy po vnútornej úprave hrobovej jamy. Ostatní jedinci z hrobov i sídliskových objektov patria do skupiny priemerne až podpriemerne vystrojených. Relatívna uniformita, konštrukčná jednoduchosť stavieb spolu s absenciou špecializovaných remeselných zariadení, svedčí takisto o neveľkých ekonomických a sociálnych diferenciáciách medzi obyvateľmi hradiska."
              }
            ]
          }
        ]
      },
      {
        "__component": "content.image-block",
        "imageRef": {
          "sourceUrl": "https://blogger.googleusercontent.com/img/b/R29vZ2xl/AVvXsEgxAXXnMMXMUVZOywJ2e3noqHtt5ZVu-or4Ughmew_w4oDiclAb6Rs0WeK42mnmNwKAOlVLY43kfWYRiJ-C3V12jU2tSOhEpHPjuvlOpS0wE9DKLYviK9XeVZbAD30355Q4gTGSvmEAczo/s0/Sni%25CC%2581mka+obrazovky+2016-09-16+o%25C2%25A019.31.28.png",
          "fallbackUrl": "https://blogger.googleusercontent.com/img/b/R29vZ2xl/AVvXsEgxAXXnMMXMUVZOywJ2e3noqHtt5ZVu-or4Ughmew_w4oDiclAb6Rs0WeK42mnmNwKAOlVLY43kfWYRiJ-C3V12jU2tSOhEpHPjuvlOpS0wE9DKLYviK9XeVZbAD30355Q4gTGSvmEAczo/s1600/Sni%25CC%2581mka+obrazovky+2016-09-16+o%25C2%25A019.31.28.png",
          "filename": "Sni%CC%81mka+obrazovky+2016-09-16+o%C2%A019.31.28.png",
          "blogger": {
            "anchorHref": "https://blogger.googleusercontent.com/img/b/R29vZ2xl/AVvXsEgxAXXnMMXMUVZOywJ2e3noqHtt5ZVu-or4Ughmew_w4oDiclAb6Rs0WeK42mnmNwKAOlVLY43kfWYRiJ-C3V12jU2tSOhEpHPjuvlOpS0wE9DKLYviK9XeVZbAD30355Q4gTGSvmEAczo/s1600/Sni%25CC%2581mka+obrazovky+2016-09-16+o%25C2%25A019.31.28.png",
            "displayedWidth": 320,
            "displayedHeight": 180,
            "originalWidth": null,
            "originalHeight": null
          }
        },
        "alt": "Mužla - Čenkov",
        "caption": "",
        "position": "center",
        "showCaption": false,
        "width": "60",
        "aspectRatio": "auto",
        "rounded": true,
        "shadow": true
      },
      {
        "__component": "content.rich-text",
        "body": [
          {
            "type": "heading",
            "level": 2,
            "children": [
              {
                "type": "text",
                "text": "Obživa obyvateľov hradiska"
              }
            ]
          }
        ]
      },
      {
        "__component": "content.rich-text",
        "body": [
          {
            "type": "paragraph",
            "children": [
              {
                "type": "text",
                "text": "Predstavy o výrobnej základni tamojšej komunity doplnili výsledky archeozoologických zistení. Priniesli údaje o cielenom chove hovädzieho dobytka, ošípaných, sčasti aj oviec, kôz i hydiny, doplneného lovom a rybolovom. Paleobotanické expertízy presvedčili zasa o prevahe tradičných druhov obilovín. Vylúčiť nemožno ani dorábanie uvedených plodín vo vzdialenejších regiónoch a dopravovaných do čenkovského hradiska obchodnými trasami. Podobným spôsobom boli na lokalitu transportované žarnovy a brúsiky zhotovované z kamennej suroviny exploatovanej v prostredí stredného Pohronia. Na možnosť zhromažďovania poľnohospodárskych plodín zo vzdialenejšieho územia, na úkor miestnej produkcie, nepriamo poukazujú zistenia o prevažne zalesnenom najbližšom okolí čenkovského sídliska. Iným momentom je sporadický výskyt poľnohospodárskeho náradia, sotva zrovnateľný s predstavami o intenzívnej poľnohospodárskej výrobe. "
              }
            ]
          }
        ]
      },
      {
        "__component": "content.image-block",
        "imageRef": {
          "sourceUrl": "https://blogger.googleusercontent.com/img/b/R29vZ2xl/AVvXsEicu-LEFDDNHaobI6KBtGFuU22T06rKMixE5Psau9_vwrtBnH_7ekgXE6i9FL2Nnm4ZugyASFVaZyklz7CURrNIlHRcmQm7nwluYOsQ1VSCTIUuXfOirxHjMJtMWFNjN7ZkbzyaA0CUzGo/s0/Sni%25CC%2581mka+obrazovky+2016-09-16+o%25C2%25A019.32.00.png",
          "fallbackUrl": "https://blogger.googleusercontent.com/img/b/R29vZ2xl/AVvXsEicu-LEFDDNHaobI6KBtGFuU22T06rKMixE5Psau9_vwrtBnH_7ekgXE6i9FL2Nnm4ZugyASFVaZyklz7CURrNIlHRcmQm7nwluYOsQ1VSCTIUuXfOirxHjMJtMWFNjN7ZkbzyaA0CUzGo/s1600/Sni%25CC%2581mka+obrazovky+2016-09-16+o%25C2%25A019.32.00.png",
          "filename": "Sni%CC%81mka+obrazovky+2016-09-16+o%C2%A019.32.00.png",
          "blogger": {
            "anchorHref": "https://blogger.googleusercontent.com/img/b/R29vZ2xl/AVvXsEicu-LEFDDNHaobI6KBtGFuU22T06rKMixE5Psau9_vwrtBnH_7ekgXE6i9FL2Nnm4ZugyASFVaZyklz7CURrNIlHRcmQm7nwluYOsQ1VSCTIUuXfOirxHjMJtMWFNjN7ZkbzyaA0CUzGo/s1600/Sni%25CC%2581mka+obrazovky+2016-09-16+o%25C2%25A019.32.00.png",
            "displayedWidth": 320,
            "displayedHeight": 180,
            "originalWidth": null,
            "originalHeight": null
          }
        },
        "alt": "Mužla - Čenkov",
        "caption": "",
        "position": "right",
        "showCaption": false,
        "width": "60",
        "aspectRatio": "auto",
        "rounded": true,
        "shadow": true
      },
      {
        "__component": "content.rich-text",
        "body": [
          {
            "type": "heading",
            "level": 2,
            "children": [
              {
                "type": "text",
                "text": "Obyvatelia hradiska - pohania"
              }
            ]
          }
        ]
      },
      {
        "__component": "content.rich-text",
        "body": [
          {
            "type": "paragraph",
            "children": [
              {
                "type": "text",
                "text": "Archeológovia uvádzajú, že zaznamenané prejavy pohrebných zvyklostí spolu s rozptýleným spôsobom rozmiestňovania hrobov v rámci sídliskovej plochy i výskytom jedincov v zásobných jamách sú typické najmä pre prostredie pohanských názorových predstáv. Z hľadiska kvality ide o záverečnú etapu pohanstva s dokladom krízových prejavov objavujúcich sa spravidla po strate dôvery v tradičné náboženské dogmy. Svedectvá akéhokoľvek druhu o prenikajúcom vplyve novej kresťanskej ideológie zatiaľ chýbajú."
              }
            ]
          }
        ]
      },
      {
        "__component": "content.rich-text",
        "body": [
          {
            "type": "heading",
            "level": 2,
            "children": [
              {
                "type": "text",
                "text": "Zhrnutie"
              }
            ]
          }
        ]
      },
      {
        "__component": "content.rich-text",
        "body": [
          {
            "type": "paragraph",
            "children": [
              {
                "type": "text",
                "text": "Na podklade sídliskových analýz možno uzavrieť, že lokalita bola osídlená najneskôr v druhej štvrtine 9. stor. kolonizačným spôsobom väčšou skupinou obyvateľstva. Toto spoločenstvo ľudí bolo málo sociálne stratifikované, ale jednotne organizované do tej miery, že bolo schopné nielen plánovite zastavať vybranú plochu, ale ju i opevniť valom solídnej konštrukcie a mohutnosti. Samotný rozvoj osídlenia lokality nemožno interpretovať ako súčasť či vyvrcholenie spontánneho a prirodzeného vývoja osídlenia tamojšieho mikroregiónu, dovtedy Slovanmi prakticky neosídleného. Kostrové pohrebiská z doby avarského kaganátu v Štúrove, Štúrove-Obide a Radvani nad Dunajom koncom 8. stor. zanikli. V Mužle-Čenkove nebol zistený žiadny vplyv ich materiálnej kultúry. Iné výraznejšie predveľkomoravské osídlenia z blízkeho okolia zatiaľ nepoznáme. Pravdepodobne išlo o kolonizačný proces riadený, resp. umožnený, vyššími zložkami vtedajšej spoločenskej štruktúry.\n \n "
              }
            ]
          }
        ]
      },
      {
        "__component": "content.image-block",
        "imageRef": {
          "sourceUrl": "https://blogger.googleusercontent.com/img/b/R29vZ2xl/AVvXsEj-IQgTSkXo8yuf8ZYURFfKzJzrksAInvCgdahH8il8Te2eFZEvip4XQTyfH8O1PD1ZVGNtnikg8CoqLhl1B_m8rimdyFJvYNpr9iDB3Z3qVaw8VOj6ksXgElqEgUYmfBrvbVpevbkIa5o/s0/na%25CC%2581lezy1.jpg",
          "fallbackUrl": "https://blogger.googleusercontent.com/img/b/R29vZ2xl/AVvXsEj-IQgTSkXo8yuf8ZYURFfKzJzrksAInvCgdahH8il8Te2eFZEvip4XQTyfH8O1PD1ZVGNtnikg8CoqLhl1B_m8rimdyFJvYNpr9iDB3Z3qVaw8VOj6ksXgElqEgUYmfBrvbVpevbkIa5o/s1600/na%25CC%2581lezy1.jpg",
          "filename": "na%CC%81lezy1.jpg",
          "blogger": {
            "anchorHref": "https://blogger.googleusercontent.com/img/b/R29vZ2xl/AVvXsEj-IQgTSkXo8yuf8ZYURFfKzJzrksAInvCgdahH8il8Te2eFZEvip4XQTyfH8O1PD1ZVGNtnikg8CoqLhl1B_m8rimdyFJvYNpr9iDB3Z3qVaw8VOj6ksXgElqEgUYmfBrvbVpevbkIa5o/s1600/na%25CC%2581lezy1.jpg",
            "displayedWidth": 209,
            "displayedHeight": 320,
            "originalWidth": null,
            "originalHeight": null
          }
        },
        "alt": "Mužla - Čenkov",
        "caption": "",
        "position": "right",
        "showCaption": false,
        "width": "40",
        "aspectRatio": "auto",
        "rounded": true,
        "shadow": true
      },
      {
        "__component": "content.rich-text",
        "body": [
          {
            "type": "paragraph",
            "children": [
              {
                "type": "text",
                "text": "Počiatky čenkovského osídlenia možno dať do súvisu s procesom budovania a územného zjednocovania Nitrianskeho kniežatstva. Po dosiahnutí významného hraničného predelu, akým je Dunaj, v danom priestore možno vcelku reálne očakávať založenie sídliska s militantným poslaním jeho obyvateľstva. Okrem demonštrácie územno-štátnej suverenity stálou vojenskou posádkou mohlo k poslaniu patriť i sledovanie diania na území južne od Dunaja. Zvýšenie potrieb tohto druhu informácií možno očakávať najmä v priebehu druhej tretiny 9. stor. Počas neho v dôsledku vývoja politicko-vojenských ambícií Východofranskej a Veľkomoravskej ríše badať vo vzájomných vzťahoch rast napätia. So spomenutým obdobím možno na čenkovskom hradisku spájať aj systém opevnenia a nálezy militantného charakteru z prvého horizontu osídlenia."
              }
            ]
          }
        ]
      },
      {
        "__component": "content.image-block",
        "imageRef": {
          "sourceUrl": "https://blogger.googleusercontent.com/img/b/R29vZ2xl/AVvXsEjIXLTftye4V7wgZmhSFm-NmBm0BbIxMT8SbiYl6nOoBrk5ipQJFiaNCqh8eh-UDbZK9WVo-ZPE_lIV-MzXNwG2hmv5620qDyK2pnn4S9hOk_asK0bXncboqiXE_HM3VBdUp-kwbFZTUjU/s0/VM+Gombi%CC%81k.jpg",
          "fallbackUrl": "https://blogger.googleusercontent.com/img/b/R29vZ2xl/AVvXsEjIXLTftye4V7wgZmhSFm-NmBm0BbIxMT8SbiYl6nOoBrk5ipQJFiaNCqh8eh-UDbZK9WVo-ZPE_lIV-MzXNwG2hmv5620qDyK2pnn4S9hOk_asK0bXncboqiXE_HM3VBdUp-kwbFZTUjU/s1600/VM+Gombi%CC%81k.jpg",
          "filename": "VM+Gombík.jpg",
          "blogger": {
            "anchorHref": "https://blogger.googleusercontent.com/img/b/R29vZ2xl/AVvXsEjIXLTftye4V7wgZmhSFm-NmBm0BbIxMT8SbiYl6nOoBrk5ipQJFiaNCqh8eh-UDbZK9WVo-ZPE_lIV-MzXNwG2hmv5620qDyK2pnn4S9hOk_asK0bXncboqiXE_HM3VBdUp-kwbFZTUjU/s1600/VM+Gombi%CC%81k.jpg",
            "displayedWidth": 165,
            "displayedHeight": 320,
            "originalWidth": null,
            "originalHeight": null
          }
        },
        "alt": "honosný veľkomoravský gombík z hradiska",
        "caption": "honosný veľkomoravský gombík z hradiska",
        "position": "left",
        "showCaption": true,
        "width": "40",
        "aspectRatio": "auto",
        "rounded": true,
        "shadow": true
      },
      {
        "__component": "content.rich-text",
        "body": [
          {
            "type": "paragraph",
            "children": [
              {
                "type": "text",
                "text": "Funkčné ťažisko osídlenia v druhom horizonte sa presúva do hospodárskej sféry (pestovanie plodín a chov dobytka a tiež obchod s poľnohospodárskymi produktmi), čo dokladajú aj zmeny v sídliskovej štruktúre. V tomto období došlo k zníženiu koncentrácie obytných stavieb, nárastu počtu hospodárskych zariadení obzvlášť obilných jám. K spomínanému obratu vo funkčnosti čenkovského opevneného sídliska mohlo dôjsť po udalostiach z roku 861. Na základe výsledkov vojenských stretov bolo k teritóriu Veľkej Moravy pripojené územie od Ostrihomu k Vesprému, Bakonskému lesu a dolnému toku Ráby. Tieto zmeny mohli byť priamym impulzom vytrácania sa pôvodného militantného zamerania obyvateľov sledovanej lokality. Väčší význam môže naopak nadobúdať možnosť spojenia protiľahlých brehov prostredníctvom riečneho prepraviska, ktorého existencia v tesnej blízkosti hradiska má historické opodstatnenie. Odraz ďalších zmien v dovtedajšom charaktere osídlenia registrujeme v treťom horizonte osídlenia, vypĺňajúceho úsek poveľkomoravského obdobia (druhá a tretia tretina 10. stor.). Prejavuje sa vo výraznej redukcii koncentrácie osídlenia, keď tu z pôvodných obyvateľov zostáva iba malá časť. Archeológovia však upozorňujú, že nejde o katastrofický zánik v dôsledku priamej vojenskej akcie z čias obsadzovania dnešného Slovenska príslušníkmi maďarského etnika. Pre takúto úvahu chýbajú v nálezových situáciách akékoľvek indície. Posledné výsledky našej historiografie (Steinhübel) vylučujú stotožňovanie Čenkova s hradiskom, ktoré podľa Šimona z Kézy dobyli starí Maďari. Zdôvodnenie výraznej redukcie intenzity osídlenia môžeme hypoteticky predpokladať vo vytratení sa primárnych determinantov podmieňujúcich pôvodnú koncentráciu osídlenia. Trend redukcie osídlenia pokračuje aj do štvrtého obdobia, patriaceho rámcovo do 11. – 12. stor. V danom období sa v pôvodnom sídliskovom areáli objavujú objekty malej osady rozptýleného typu, zachytenej v písomných prameňoch ako villa. V latinskej terminológii ide o označenie neopevneného celku agrárneho typu. "
              }
            ]
          }
        ]
      },
      {
        "__component": "content.image-block",
        "imageRef": {
          "sourceUrl": "https://blogger.googleusercontent.com/img/b/R29vZ2xl/AVvXsEhsm2Tw1NdzFyZdPYPxYRzPAiyw1lQdZYC0Duz5HmE4pf3qWOeYRV5eaFTtTiiWxdBJODxo8PZ_JF39THdeP3vY-PoEkvgtApF203TgvIHWp_rHJBmikyXASywT3u-v_TX8cpKnG1K8suo/s0/14964156_218955325193799_830176762_o.jpg",
          "fallbackUrl": "https://blogger.googleusercontent.com/img/b/R29vZ2xl/AVvXsEhsm2Tw1NdzFyZdPYPxYRzPAiyw1lQdZYC0Duz5HmE4pf3qWOeYRV5eaFTtTiiWxdBJODxo8PZ_JF39THdeP3vY-PoEkvgtApF203TgvIHWp_rHJBmikyXASywT3u-v_TX8cpKnG1K8suo/s1600/14964156_218955325193799_830176762_o.jpg",
          "filename": "14964156_218955325193799_830176762_o.jpg",
          "blogger": {
            "anchorHref": "https://blogger.googleusercontent.com/img/b/R29vZ2xl/AVvXsEhsm2Tw1NdzFyZdPYPxYRzPAiyw1lQdZYC0Duz5HmE4pf3qWOeYRV5eaFTtTiiWxdBJODxo8PZ_JF39THdeP3vY-PoEkvgtApF203TgvIHWp_rHJBmikyXASywT3u-v_TX8cpKnG1K8suo/s1600/14964156_218955325193799_830176762_o.jpg",
            "displayedWidth": 320,
            "displayedHeight": 153,
            "originalWidth": null,
            "originalHeight": null
          }
        },
        "alt": "Mužla - Čenkov",
        "caption": "",
        "position": "right",
        "showCaption": false,
        "width": "60",
        "aspectRatio": "auto",
        "rounded": true,
        "shadow": true
      },
      {
        "__component": "content.sources",
        "title": "Zdroje a literatúra",
        "intro": null,
        "items": [
          {
            "text": "Hanuliak, Šalkovský, Kuzma: Mužla-Čenkov I. Osídlenie z 9. – 12. st., Nitra 1993",
            "url": null
          },
          {
            "text": "M. Hanuliak: Materiálna kultúra 9. – 10. storočia z opevneného sídliska v Mužle-Čenkove, Archaeologia historica. 2013, roč. 38, č. 1, s. 157 – 174",
            "url": null
          }
        ]
      }
    ],
    "citations": [
      {
        "type": "attribution",
        "text": "Spracoval: Orgoň"
      },
      {
        "type": "book",
        "text": "Hanuliak, Šalkovský, Kuzma: Mužla-Čenkov I. Osídlenie z 9. – 12. st., Nitra 1993"
      },
      {
        "type": "book",
        "text": "M. Hanuliak: Materiálna kultúra 9. – 10. storočia z opevneného sídliska v Mužle-Čenkove, Archaeologia historica. 2013, roč. 38, č. 1, s. 157 – 174"
      },
      {
        "type": "attribution",
        "text": "Foto 10.12.2014 (Orgoň):"
      }
    ]
  }
}